Workbook
Name \a: #REF!
Name \a: #REF!
Name \a: #REF!
Name \a: #REF!
Name \a: #REF!
Name \a: #REF!
Name \a: #REF!
Name \a: #REF!
Name \a: #REF!
Name \a: #REF!
Name \a: #REF!
Name \a: #REF!
Name \a: #REF!
Name \a: #REF!
Name \a: #REF!
Name \a: #REF!
Name \a: #REF!
Name \a: #REF!
Name \a: #REF!
Name \a: #REF!
Name \a: #REF!
Name \a: #REF!
Name \a: #REF!
Name \a: #REF!
Name \a: #REF!
Name \a: #REF!
Name \a: #REF!
Name \a: #REF!
Name \a: #REF!
Name \a: #REF!
Name \a: #REF!
Name \a: #REF!
Name \a: #REF!
Name \a: #REF!
Name \a: #REF!
Name \a: #REF!
Name \a: #REF!
Name \a: #REF!
Name \a: #REF!
Name \a: #REF!
Name \a: #REF!
Name \a: #REF!
Name \a: #REF!
Name \a: #REF!
Name \a: #REF!
Name \a: #REF!
Name \a: #REF!
Name \a: #REF!
Name \a: #REF!
Name \a: #REF!
Name \a: #REF!
Name \a: #REF!
Name \a: #REF!
Name \a: #REF!
Name \a: #REF!
Name \a: #REF!
Name \a: #REF!
Name \a: #REF!
Name \a: #REF!
Name \a: #REF!

Sheet 封面-全星科技
F18: 浙江全星科技新材料股份有限公司
D26: 产品质量先期策划（APQP）
D37: 项目名称： | K37: 通用材料用工业长丝-大块金事业部PH25657
D38: Project Name: | K38: Nylon 66 tire cord fabric industrial yarn-Tire cord fabric Department PH25657
D40: 项目周期： Project Cycle | K40: 2023/8-2025.8

Sheet 目录
B1: 密级：秘密★★，未经允许不可查看；保存期限：长期
A2: 产品质量先期策划（APQP）项目资料
A3: 目 录
A4: 序号 | B4: 文件/记录名称 | C4: 全星根据体系老师建议调整 （调整的做链接可点开） | D4: 全星科技确认后记录 | E4: 文件/记录编号 | F4: 备注 | G4: 日期
A5: 第零阶段：项目启动阶段
A6: 0.01 | B6: 新产品制造可行性分析报告 | C6: 1增加设备能力（生产线实际能力） | D6: B列链接是全星科技最新版 | E6: HLD/CF-04-041-003 | G6: 2023年8月14日 | H6: 45152
A7: 0.02 | B7: 新产品开发申请/立项报告 | C7: 表单可行 | E7: HLD/CF-04-041-005 | G7: 2023年8月15日 | H7: 45153
A8: 0.03 | B8: 新产品开发小组成员及职责表 | C8: 增加了客户、供应商信息，选填 | D8: 化纤不加客户 供应商，还是按照客户原版 | E8: HLD/CF-04-041-006 | G8: 2023年8月15日 | H8: 45153
A9: 0.04 | B9: 新产品APQP开发计划 | C9: 表单可行 | E9: HLD/CF-04-041-007 | G9: 2023年8月15日 | H9: 45153
A10: 0.05 | B10: 设计评审/验证/确认记录（设计开发输入） | C10: 评审项目改成了评审阶段，点链接查看修改版 | D10: OK，按照修改版 | E10: HLD/CF-04-041-008 | G10: 2023年8月16日 | H10: 45154
A11: 第一阶段：策划和定义项目
A12: 1.01 | B12: 设计开发任务书 | C12: 表单可行 | E12: HLD/CF-04-041-009 | G12: 2023年8月17日 | H12: 45155
A13: 1.02 | B13: 初始材料清单（BOM） | C13: 表单可行 | E13: HLD/CF-04-041-011 | G13: 2023年8月18日 | H13: 45156
A14: 1.03 | B14: 成本核算及报价表 | C14: 表单可行，内容加了水电 | E14: HLD/CF-04-041-004 | G14: 2023年8月18日 | H14: 45156
A15: 1.04 | B15: 过程流程图（初始） | C15: 表单可行 | E15: HLD/CF-03-041-*** | F15: 文件 | G15: 2023年8月19日 | H15: 45157
A16: 1.05 | B16: 特殊特性符合转化表 | C16: 表单可行 | E16: HLD/CF-04-041-025 | G16: 2023年8月20日 | H16: 45158
A17: 1.06 | B17: 产品/过程特殊特性清单（初始） | C17: 表单可行 | E17: HLD/CF-04-041-012 | G17: 2023年8月20日 | H17: 45158
A18: 1.07 | B18: 产品安全识别表 | C18: 表单可行，内容增加了有害物质 | E18: HLD/CF-04-041-047 | G18: 2023年8月21日 | H18: 45159
A19: 1.08 | B19: 产品保证计划 | C19: 表单可行，包装要求中的控制方法写管控要求 | E19: HLD/CF-04-041-010 | G19: 2023年8月21日 | H19: 45159
A20: 1.09 | B20: 项目变更登记表 | C20: 表单可行 | E20: HLD/CF-04-041-048 | G20: 2023年8月21日 | H20: 45159
A21: 1.10 | B21: 风险评估和缓解计划 | C21: 表单可行 | E21: HLD/CF-04-041-049 | G21: 2023年8月21日 | H21: 45159
A22: 1.11 | B22: 设计评审/验证/确认记录（产品设计输入） | C22: 同0.05 | E22: HLD/CF-04-041-008 | G22: 2023年8月22日 | H22: 45160
A23: 1.12 | B23: 阶段性总结和管理者支持（第一阶段） | C23: 增加了问题清单 | D23: 替换二大项，确保内容项不要缺失 ，问题清单不打印，但系统保留这个列表 | E23: HLD/CF-04-041-013 | G23: 2023年8月22日 | H23: 45160
A24: 第二阶段：产品设计开发
A25: 2.01 | B25: DFMEA | C25: 内容：其中关注要素原丝改成纱线，老师会议中提出失效分析需考虑元素结合，另预防措施中建议写具体方法，目前的有点笼统，这部分讨论比较多，主要针对内容，会议视频已发出，时间大概在10:30这个视频包中 | E25: HLD/CF-03-041-*** | F25: 文件 | G25: 2023年8月22日 | H25: 45160
A26: 2.02 | B26: DFMEA检查表 | C26: 表单可行 | E26: HLD/CF-04-041-035 | G26: 2023年8月22日 | H26: 45160
A27: 2.03 | B27: 产品技术规范 | C27: 表单可行 | E27: HLD/CF-04-041-014 | G27: 2023年8月23日 | H27: 45161
A28: 2.04 | B28: 设计评审/验证/确认记录（可制造性评审） | C28: 表单可行 | E28: HLD/CF-04-041-008 | G28: 2023年8月23日 | H28: 45161
A29: 2.05 | B29: 控制计划（样件） | C29: 表单可行 | E29: HLD/CF-03-041-*** | F29: 文件 | G29: 2023年8月24日 | H29: 45162
A30: 2.06 | B30: 控制计划检查表（样件） | C30: 表单可行 | E30: HLD/CF-04-041-027 | G30: 2023年8月24日 | H30: 45162
A31: 2.07 | B31: 工艺标准（样件） | C31: 表单可行 | E31: HLD/CF-04-041-*** | F31: 文件 | G31: 2023年8月25日 | H31: 45163
A32: 2.08 | B32: 生产通知单（样件） | C32: 表单可行 | E32: QR/HLD-04-03-01 | F32: 生产计划 | G32: 2023年8月26日 | H32: 45164
A33: 2.09 | B33: 设计验证报告 | C33: 表单可行 | E33: HLD/CF-04-041-050 | G33: 2023年8月28日 | H33: 45166
A34: 2.10 | B34: 设计评审/验证/确认记录（产品设计输出） | C34: 表单可行 | E34: HLD/CF-04-041-008 | G34: 2023年8月29日 | H34: 45167
A35: 2.11 | B35: 设计更改记录 | C35: 表单可行 | E35: HLD/CF-04-041-028 | G35: 2023年12月22日 | H35: 45282 | I35: 2024年6月4日 | J35: 45447
A36: 2.12 | B36: 工程规范确认表 | C36: 表单可行 | E36: HLD/CF-04-041-015 | G36: 2023年8月30日 | H36: 45168
A37: 2.13 | B37: 材料规范确认表 | C37: 表单可行 | E37: HLD/CF-04-041-016 | G37: 2023年8月31日 | H37: 45169
A38: 2.14 | B38: 设备、工装和设施清单 | C38: 表单可行 | E38: HLD/CF-04-041-017 | G38: 2023年9月1日 | H38: 45170
A39: 2.15 | B39: 量具/试验设备清单 | C39: 修改版增加一列精度/规格是否满足 | D39: OK，按照修改版 | E39: HLD/CF-04-041-051 | G39: 2023年9月1日 | H39: 45170
A40: 2.16 | B40: 产品/过程特殊特性清单（产品设计后更新） | C40: 表单可行 | E40: HLD/CF-04-041-012 | F40: 如有变化需更新 | G40: 2023年9月2日 | H40: 45171
A41: 2.17 | B41: 小组可行性承诺 | C41: 表单可行 | E41: HLD/CF-04-041-020 | G41: 2023年9月3日 | H41: 45172
A42: 2.18 | B42: 阶段性总结和管理者支持（第二阶段） | C42: 有调整（全星参考） 改动位置链接有详细注明 | D42: 替换二大项，确保内容项不要缺失 ，问题清单不打印，但系统保留这个列表 | E42: HLD/CF-04-041-013 | G42: 2023年9月4日 | H42: 45173
A43: 第三阶段：过程设计开发
A44: 3.01 | B44: 设计评审/验证/确认记录（过程设计输入） | C44: 表单可行 | E44: HLD/CF-04-041-008 | G44: 2024年5月28日 | H44: 45440
A45: 3.02 | B45: 产品包装标准及规范 | C45: 表单可行 | E45: HLD/CF-04-041-029 | G45: 2024年5月28日 | H45: 45440
A46: 3.03 | B46: 产品/过程质量体系检查表 | C46: 表单可行 | E46: HLD/CF-04-041-021 | G46: 2024年5月29日 | H46: 45441
A47: 3.04 | B47: 车间平面布置图 | C47: 表单可行 | D47: 2025/9/18表单确认会议上提出：车间平面布置图部分在嵌入对应表单时，希望可以实现自由选择平面布置图的功能，例如平面布置图共有4种，准备不同产品的APQP资料时，可以根据需要选择不同的平面布置图。——张亚慧——时间待定 | E47: HLD/CF-04-041-022 | G47: 2024年5月29日 | H47: 45441
A48: 3.05 | B48: 过程流程图（过程设计） | C48: 表单可行 | E48: HLD/CF-03-041-*** | F48: 文件 | G48: 2024年5月30日 | H48: 45442
A49: 3.06 | B49: 过程流程图检查表 | C49: 表单可行 | E49: HLD/CF-04-041-023 | G49: 2024年5月30日 | H49: 45442
A50: 3.07 | B50: 特性矩阵图 | C50: 表单可行 | E50: HLD/CF-04-041-026 | G50: 2024年5月31日 | H50: 45443
A51: 3.08 | B51: PFMEA | C51: 主要针对内容沟通：1：4M要素是主要针对现场操作工，质量员等岗位的人不需要记录在内 2：失效起因只标明人为操作失误，尽量深究什么导致操作失误，可以更详细注明 3：过程步骤功能和过程特性未描述出特性要求 这部分也是讨论较多，在下午三点钟左右的会议视频内，会发出具体 | E51: HLD/CF-03-041-*** | F51: 文件 | G51: 2024年6月1日 | H51: 45444
A52: 3.09 | B52: PFMEA检查表 | E52: HLD/CF-04-041-024 | G52: 2024年6月1日 | H52: 45444
A53: 3.10 | B53: 控制计划（试生产） | C53: 内容是可行的，其中提到客户投诉这点，若有关联可以更新控制计划，没关联不用更新 | E53: HLD/CF-03-041-*** | F53: 文件 | G53: 2024年6月2日 | H53: 45445
A54: 3.11 | B54: 控制计划检查表（试生产） | C54: 表单可行 | E54: HLD/CF-04-041-027 | G54: 2024年6月2日 | H54: 45445
A55: 3.12 | B55: 标准文件核查表 | C55: 表单可行 | E55: HLD/CF-04-041-030 | G55: 2024年6月3日 | H55: 45446
A56: 3.13 | B56: 测量系统分析（MSA）计划 | C56: 表单可行 | E56: HLD/CF-04-132-009 | G56: 2024年6月4日 | H56: 45447
A57: 3.14 | B57: 初始过程能力研究计划 | C57: 表单可行 | E57: HLD/CF-04-041-031 | G57: 2024年6月4日 | H57: 45447
A58: 3.15 | B58: 设备过程能力研究计划 | C58: 表单可行 | E58: HLD/CF-04-111-100 | G58: 2024年6月4日 | H58: 45447
A59: 3.16 | B59: 防错装置清单 | C59: 表单可行 | E59: HLD/CF-04-041-052 | G59: 2024年6月5日 | H59: 45448
A60: 3.17 | B60: 设备维护保养计划 | C60: 表单可行 | E60: HLD/CF-04-041-053 | G60: 2024年6月5日 | H60: 45448
A61: 3.18 | B61: 阶段性总结和管理者支持（第三阶段） | C61: 有调整（全星参考） 改动位置链接有详细注明 | E61: HLD/CF-04-041-013 | G61: 2024年6月6日 | H61: 45449
A62: 第四阶段：产品和过程确认
A63: 4.01 | B63: 工艺标准（试生产） | C63: 表单可行 | E63: HLD/CF-04-041-*** | F63: 文件 | G63: 2024年6月6日 | H63: 45449
A64: 4.02 | B64: 生产通知单（试生产） | C64: 表单可行 | E64: QR/HLD-04-03-01 | F64: 生产计划 | G64: 2024年6月7日 | H64: 45450
A65: 4.03 | B65: 防错验证报告 | C65: 表单可行 | E65: HLD/CF-04-041-054 | G65: 2024年6月7日 | H65: 45450
A66: 4.04 | B66: 测量系统分析报告 | C66: 上传形式 | E66: HLD/CF-04-132-010 | G66: 2025年7月21日 | H66: 45859
A67: 4.05 | B67: 初始过程能力、设备过程能力分析报告 | C67: 表单可行 | E67: HLD/CF-04-041-032 | G67: 2024年6月20日 | H67: 45463
A68: 4.06 | B68: 设计验证报告 | C68: 表单可行 | E68: HLD/CF-04-041-050 | G68: 2024年6月22日 | H68: 45465
A69: 4.07 | B69: 设计评审/验证/确认记录（过程设计输出） | C69: 表单可行 | E69: HLD/CF-04-041-008 | G69: 2024年6月22日 | H69: 45465
A70: 4.08 | B70: 设计更改记录 | C70: 表单可行 | E70: HLD/CF-04-041-028 | G70: 2025年5月6日 | H70: 45783
A71: 4.09 | B71: 包装评价报告 | C71: 荷重试验需要列出什么时间、试验结果、结论，可点击查看修改版 | D71: 评审标准不放在APQP流程体现，全星科技额外做记录，还按照原版 | E71: HLD/CF-04-041-055 | G71: 2025年3月15日 | H71: 45731
A72: 4.10 | B72: 控制计划（量产） | C72: 位置统一移到4.20后 | E72: HLD/CF-03-041-*** | F72: 文件 | G72: 2025年3月20日 | H72: 45736
A73: 4.11 | B73: 控制计划检查表（量产） | E73: HLD/CF-04-041-027 | G73: 2025年3月21日 | H73: 45737
A74: 4.12 | B74: 零件提交保证书（PSW） | D74: 这个做上传形式 | E74: HLD/CF-04-041-035 | G74: 2025年4月24日 | H74: 45771
A75: 4.13 | B75: 控制计划（安全投产） | C75: 表单可行 | E75: HLD/CF-03-041-*** | F75: 文件 | G75: 2025年4月29日 | H75: 45776
A76: 4.14 | B76: 控制计划检查表（安全投产） | C76: 表单可行 | E76: HLD/CF-04-041-027 | G76: 2025年4月30日 | H76: 45777
A77: 4.15 | B77: 工艺标准（安全投产） | C77: 表单可行 | E77: HLD/CF-04-041-*** | F77: 文件 | G77: 2025年5月6日 | H77: 45783
A78: 4.16 | B78: 生产通知单（安全投产） | C78: 表单可行 | E78: QR/HLD-04-03-01 | F78: 生产计划 | G78: 2025年5月7日 | H78: 45784
A79: 4.17 | B79: 设计验证报告 | C79: 表单可行，内容7.后加8.改善问题点，可点击查看 | D79: 按照客户原版 | E79: HLD/CF-04-041-050 | G79: 2025年7月26日 | H79: 45864
A80: 4.18 | B80: 包装评价报告 | C80: 表单可行 | E80: HLD/CF-04-041-055 | G80: 2025年7月26日 | H80: 45864
A81: 4.19 | B81: 设计评审/验证/确认记（安全投产评审） | C81: 表单可行 | E81: HLD/CF-04-041-008 | G81: 2025年7月26日 | H81: 45864
A82: 4.20 | B82: 设计更改记录 | C82: 表单可行 | E82: HLD/CF-04-041-028
A83: 4.21 | B83: 产品质量策划总结和认定报告 | C83: 修改版-初始能力改成过程能力研究等，可点链接 | D83: OK，按照修改版 | E83: HLD/CF-04-041-033 | G83: 2025年7月26日 | H83: 45864
A84: 4.22 | B84: 阶段性总结和管理者支持（第四阶段） | C84: 有调整（全星参考） 改动位置链接有详细注明 | E84: HLD/CF-04-041-013 | G84: 2025年7月26日 | H84: 45864
A85: 第五阶段：反馈、评定和纠正措施（持续改进）
A86: 5.01 | B86: 项目移交清单 | C86: 表单可行 | E86: HLD/CF-04-041-034 | G86: 2025年7月26日 | H86: 45864
A87: 5.02 | B87: 设计评审/验证/确认记录（量产输出） | C87: 评审结果前加客户反馈情况、交付满足情况、经验借鉴情况，可点链接 | D87: 暂定，等全星科技确认 | E87: HLD/CF-04-041-008 | G87: 2025年8月26日 | H87: 45895
A88: 5.02 | B88: 量产评审
B89: 尼龙66轮胎帘子布用工业长丝-帘子布事业部PH25657 Nylon 66 tire cord fabric industrial yarn-Tire cord fabric Department PH25657
B90: PH25657-2800dtex/432f
B91: 帘子布事业部
B92: 顾锋、顾钰炜、谢明智、俞锋、宋琴、熊初珍、叶莉莎、冯梦婷、崔真真、蒋佳贤、马俞锋、谢陈龙、朱翌熹

Sheet 0.01
E1: 密级：秘密★★，未经允许不可查看；保存期限：长期
A2: 新产品制造可行性分析报告 New product manufacturing feasibility analysis report
H3: 序号NO.： | K3: 0.01
A4: 新产品名称 The name of the new product | C4: 大块金用工业长丝-帘子布事业部PH25657 Nylon 66 tire cord fabric industrial yarn-Tire cord fabric Department PH25657 | F4: 新产品批号和规格Batch number and specification of new products | H4: PH25657-2800dtex/432f
F5: 顾 客 名 称 The customer name | H5: 帘子布事业部
A6: 评估部门The department responsible for evaluation | C6: 销售部/技术部 | F6: 评估日期 Date of assessment | H6: =目录!G6 -> 2023年8月14日
A7: 一、制造国，目的国，销售国的法律法规及环境方面的法律法规概述：Overview of laws and regulations of the country of manufacture, destination and seller and environmental laws and regulations:
A8: 本次开发的大块金用工业长丝制造国在中国，销售目的地为浙江海利得新材料股份有限公司帘子布事业部。 本项目开发的大块金用工业长丝产品符合GB/T 30512-2014《汽车禁用物质要求》，并已通过ROHS、REACH测试，其余法律法规的识别详见法务部《法律合规合规性评价表》。
A9: 二、顾客概况（包括：人员、工厂规模、现有主要车型、年产量、企业性质、生产经营状况、近几年发展情况等）：Customer profile (including: personnel, factory scale, existing main models, annual output, enterprise nature, production and operation status, development in recent years, etc.) :
A10: 帘子布事业部成立于2010年，2011年正式投产，员工大约650人，经营范围包括轮胎帘子布和涤纶工业长丝的设计开发，产品应用于轮胎、空气弹簧、橡胶履带、海洋软管等，纺丝产能5万吨/年，捻织7.5万吨/年，浸胶布7.2万吨/年，面积约280000㎡
A11: 三、顾客对新产品开发项目的质量和技术要求及其它基本要求（如涉及新工艺、新材料、新技术，需评估可行性）：Customer's quality and technical requirements and other basic requirements for new product development projects (if new processes, new materials and new technologies are involved, the feasibility shall be evaluated) :
A12: 按照质量和技术标准。
A13: 四、顾客对新产品的竞争选点情况（包括：有几家竞争对手与顾客配套、竞争对手的质量和技术状况、竞争对手的设计和开发能力状况等）：Customer's competitive points for new products (including: several competitors supporting customers, quality and technical status of competitors, design and development ability of competitors, etc.)
A14: 英威达/PHP神马/晓星/中维都有合作，晓星和中维为主，在PA66纱线领域都有较丰富的生产经验和开发经验
A15: 五、顾客对新产品定点及认可程序：Customer approval procedures for new products:
A16: 样品提交的认定程序如下： 1、首先进行样件或小批量的确认，具体以客户需求为准。 2、经过批量试用后开始进行批量供货。
A17: 六、市场预测：Market forecast:
A18: 预计采购量200 T/年，客户从我公司的采购量会根据我司产品研发情况再决定。
... A34: 通过以上分析，认为项目开发可行
A35: 编制/日期 Compilation/Date | F35: 审批/日期Approval/Date
A36: 表单编号： Form No : | C36: HLD/CF-04-041-003 | G36: 格式版次：第一版，第1次修改 Format edition: first edition, 1 revision

Sheet 0.01修改版
E1: 密级：秘密★★，未经允许不可查看；保存期限：长期
A2: 新产品制造可行性分析报告 New product manufacturing feasibility analysis report
A3: 序号NO.：0.01
A4: 新产品名称 The name of the new product | C4: 大块金用工业长丝-帘子布事业部PH25657 Nylon 66 tire cord fabric industrial yarn-Tire cord fabric Department PH25657 | F4: 新产品批号和规格Batch number and specification of new products | H4: PH25657-2800dtex/432f
F5: 顾 客 名 称 The customer name | H5: 帘子布事业部
A6: 评估部门 The department responsible for evaluation | C6: 技术部/销售部/生管部/供应商管理部/质量管理部/财务部/设备部 | F6: 评估日期 Date of assessment | H6: 2023年8月14日
A7: 评估项目 | D7: 分析说明 | E7: 参考附件 | F7: 可行性评估 | H7: 问题点解决对策 | J7: 负责人 | K7: 部门
F8: 可行 | G8: 不可行
A9: 1 | B9: 制造国，目的国，销售国的法律法规及环境方面的法律法规等是否识别完全 | C9: 产品是否满足环境及法律法规的要求？ | D9: 本次开发的大块金用工业长丝制造国在中国，销售目的地为浙江海利得新材料股份有限公司帘子布事业部。 本项目开发的大块金用工业长丝产品符合GB/T 30512-2014《汽车禁用物质要求》，并已通过ROHS、REACH测试，其余法律法规的识别详见法务部《法律合规合规性评价表》。 | E9: ROHS测试报告、REACH测试报告、《法律合规合规性评价表》 | K9: 技术部
C10: 产品包装是否满足环境及法律法规的要求？ | D10: 产品无出口要求，常规包装即可满足要求。
C11: 客户对安全说明的要求是否满足? | D11: 产品强力、伸长为安全特性能够满足客户要求，要求在产品标准中体现。 | E11: 《新产品开发申请/立项报告》
C12: 客户对产品使用环境的要求是否满足? | D12: 强力保持率的测试方法和要求在产品标准中体现 | E12: 《新产品开发申请/立项报告》
C13: 客户对产品使用寿命的要求是否满足? | D13: 客户无老化测试的要求，内部老化测试的测试方法和要求按照行业经验
A14: 2 | B14: 客户信息、要求是否完整 | C14: 顾客概况（包括：人员、工厂规模、现有主要车型、年产量、企业性质、生产经营状况、近几年发展情况等） | D14: 帘子布事业部成立于2010年，2011年正式投产，员工大约650人，经营范围包括轮胎帘子布和涤纶工业长丝的设计开发，产品应用于轮胎、空气弹簧、橡胶履带、海洋软管等，纺丝产能5万吨/年，捻织7.5万吨/年，浸胶布7.2万吨/年，面积约280000㎡ | K14: 销售
C15: 顾客有关部门/人员的联系电话和地址情况（包括：设计和开发部门、质量管理部门、采购部门、工程技术部门等主要负责人的联系电话和地址） | D15: 质量：万鹏辉penghui.wan@halead.com； 技术：王君毅wjy8386@halead.com
C16: 顾客对新产品开发项目的质量和技术要求及其它基本要求（如涉及新工艺、新材料、新技术，需评估可行性） | D16: 按照双方初步达成的质量标准进行设计开发；客户没有特殊要求。 | E16: 《新产品开发申请/立项报告》
A17: 3 | B17: 市场研究 | C17: 顾客对新产品的竞争选点情况（包括：有几家竞争对手与顾客配套、竞争对手的质量和技术状况、竞争对手的设计和开发能力状况等） | D17: 英威达/PHP神马/晓星/中维都有合作，晓星和中维为主，在PA66纱线领域都有较丰富的生产经验和开发经验；前期也对这些竞争对手的产品进行了测试分析，对比我司产品性能无明显差异，无风险。 | E17: 《样品检测报告》（涉密信息，不体现在APQP资料中） | K17: 销售
C18: 市场预测 | D18: 预计采购量200 T/年，客户从我公司的采购量会根据我司产品研发情况再决定。
A19: 4 | B19: 产品技术可行性分析 | C19: 技术要求（包括外观、尺寸、性能、材料要求等）是否能满足规格？ | D19: 材料为尼龙66，性能与类似产品差异不大， | K19: 技术部
C20: 如技术要求无法满足，是否得到了客户的偏差认可？ | D20: 规格可以满足要求
C21: 是否有特殊特性要求？如有，请附特殊特性清单。 | D21: 参考特殊特性清单 | E21: 特殊特性清单
C22: 是否与公司现有产品类似？如是，类似产品是？主要差异是？ | D22: 与现有开发及量产LGD车载型号类似，主要差异为BL尺寸差异（该型号为27寸大尺寸），现有开发过的最大尺寸为15.8寸 | E22: 公司现有产品类似对比
C23: 新产品先行试验和关键技术问题及风险分析（包括过去客诉、产品质量问题反馈、经验等） | D23: 1、 技术上参照现有尼龙66工业长丝生产线的工艺参数，工艺条件无风险。 2、 从客户提供的指标要求中看，生产有能力满足客户要求，风险可控。 | E23: 《经验教训总结库》
C24: 新产品开发的制造技术替代选择 | D24: 越南尼龙生产线可做F、H线的替代生产线。
A25: 5 | B25: 检测与试验能力分析 | C25: 4.1現有检测设备是否能够满足制造要求？ | D25: 可满足 | E25: MSA、《设备、工装和设施清单》 | K25: 质量管理部
C26: 4.2現有试验设备能力是否足够？ | D26: 可满足 | E26: 《量具/试验设备清单》
C27: 3.目前作业流程是否适用?作业方法作业条件是否适用? | D27: 该产品涉及的检测项目都已建立作业指导书，测试方法、条件均已与客户达成共识。 | E27: 相关检测作业指导书
A28: 6 | B28: 制造能力分析 | C28: 有特殊工艺要求/流程吗？如有，请注明 | D28: 无 | E28: 《过程流程图》 | K28: 设备部
C29: 客户指定了制造能力（CPK值，PPK值）吗？ | D29: 客户无要求时，CC/SC项按照PPK/CPK≥1.67 | E29: 《设计开发任务书》
C30: 厂内已具备该类产品之生产设备? | D30: 本产品在已有尼龙纺丝设备F、H线上生产 | E30: 《过程流程图》
A31: 7 | B31: 产能分析 | C31: 5.1生产场地和仓库场地是否足够？ | D31: 现有生产场地及仓库能够满足新产品的开发需求。 | E31: 《车间平面布置图》 | K31: 生管部
C32: 5.2人力资源是否足够？员工技能是否能够满足该产品的需求？ | D32: 每条生产线一名管线工艺员、一名质量工程师、三名操作工、三名检验人员等；员工培训后满足岗位技能要求方能上岗，每三个月会进行一次技能盘点。 | E32: 《员工技能矩阵图》
C33: 5.3产能是否能满足量产需求？ | D33: 预计2条线产能：1000T/年，剩余产量：500T/年，可以满足客户预计采购量。
A34: 8 | B34: 产品开发周期 | C34: 新产品开发的日程是否能满足？ | D34: 作为公司内部客户新项目认证的产品，计划2023年8月完成试样，试生产、批量生产需得到客户批准，具体日期待客户确定。 | E34: 《新产品APQP开发计划》 | K34: 生管部
C35: 顾客对新产品定点及认可程序 | D35: 样品提交的认定程序如下：1.首先进行样件或小批量的确认，具体以客户需求为准；2.经过批量试用后开始进行批量供货。
C36: 是否投入新的生产设备？如是，日程是否能满足？ | D36: 无 | E36: 《设备、工装和设施清单》
C37: 是否投入新的测试设备？如是，日程是否能满足？ | D37: 无 | E37: 《量具/试验设备清单》
A38: 9 | B38: 采购可行性分析 | C38: 供应商资源是否满足项目需求？ | D38: 涉及的原辅材料均已准入，无涉及新材料的开发 | E38: 《初始材料清单（BOM）》 | K38: 供应商管理部
A39: 10 | B39: 物流分析 | C39: 8.1包装规范中是否加入特殊要求(例如清洁度、渗漏、热处理、外观、防护等级、可追溯代码等)? | D39: 包装无特殊要求，目前现有包装规范能够满足要求 | E39: 《化纤事业部包装作业指导书》 | K39: 生管部
A40: 11 | B40: 财务分析 | C40: 投资预算（包括：人员投资、设施/设备投资等） | D40: 本产品在尼龙纺丝设备F、H线上生产,每条生产线一名管线工艺员、一名质量工程师、三名操作工、三名检验人员等。 | K40: 财务部
C41: 新产品的成本估算、价格预算 | D41: 销售价格预测：*RMB/T；成本价格预测：*RMB/T | E41: 见财务报表（涉密信息，不体现在APQP资料中）
C42: 销售渠道及其它情况 | D42: 内部客户直接按照商议价格按照内部交易流程进行结算。
A43: 结论conclusion | B43: 可行
B44: 不可行
A45: 编制/日期 Compilation/Date | E45: 审批/日期 Approval/Date
A46: 表单编号：HLD/CF-04-041-003 Form No : HLD/CF-04-041-003 | G46: 格式版次：第一版，第2次修改 Format edition: first edition, 2 revision

Sheet 0.02
E1: 密级：秘密★★，未经允许不可查看；保存期限：长期
A2: 新产品开发申请/立项报告 New product development application/project approval report
I3: 序号NO.： | J3: 0.02
A4: 新产品名称 The name of the new product | C4: ='0.01'!C4:E5 -> 大块金用工业长丝-帘子布事业部PH25657 Nylon 66 tire cord fabric industrial yarn-Tire cord fabric Department PH25657 | F4: 新产品批号和规格Batch number and specification of new products | H4: ='0.01'!H4:K4 -> PH25657-2800dtex/432f
F5: 顾 客 名 称 The customer name | H5: ='0.01'!H5:K5 -> 帘子布事业部
A6: 评估部门The department responsible for evaluation | C6: 技术部 | F6: 评估日期 Date of assessment | H6: =目录!G7 -> 2023年8月15日
A7: 新产品项目开发来源/依据Source/basis of new product project development | C7: 顾客要求/海利得尼龙66轮胎帘子布用工业长丝生产技术
A8: 新 产 品 项 目 开 发 要 求 和 / 或 顾 客 要 求 New product project development requirements and/or customer requirements
A9: 1、指标要求：
A10: NO. | B10: 项目Item | E10: 单位 Unit | G10: 开发要求standard | I10: 测试方法Method of testing
A11: 1 | B11: 线密度 Linear Density | E11: dtex | G11: 2880±30 | I11: GB/T14343
A12: 2 | B12: 线密度变异系数 CV of Linear Density | E12: % | G12: ≤1.60 | I12: GB/T14343
A13: 3 | B13: 断裂强力 Breaking Strength | E13: N | G13: ≥245.0 | I13: GB/T14344
A14: 4 | B14: 断裂强度 Tenacity | E14: cN/dtex | G14: ≥8.50 | I14: GB/T14344
A15: 5 | B15: 强度变异系数CV CV of Tenacity | E15: % | G15: ≤3.00 | I15: GB/T14344
A16: 6 | B16: 断裂伸长率 Breaking Elongation Ratio | E16: % | G16: 20.0±3.0 | I16: GB/T14344
A17: 7 | B17: 伸长变异系数CV CV of Elongation | E17: % | G17: ≤5.00 | I17: GB/T14344
A18: 8 | B18: 中间伸长4.7cN/dtex E.@4.7CN/dtex Load | E18: % | G18: 11.0±1.5 | I18: GB/T14344
A19: 9 | B19: 干热收缩率（177℃×2min×0.05cN/dtex) Shrinkage in Hot Air | E19: % | G19: 6.2±1.5 | I19: HLD method
A20: 10 | B20: 网络度（钩针法） Intermingles（Needle） | E20: nodes/m | G20: 6.0±3.0 | I20: HLD method
A21: 11 | B21: 含油率 Spin Finish Oil | E21: % | G21: 0.90±0.30 | I21: GB/T6504-NMR
A22: 12 | B22: 强力保持率（180℃×4h） Strength retention rate | E22: % | G22: ≥90 | I22: HLD method
A23: 2、产品尺寸要求：
A24: NO. | B24: 项目Item | C24: 单位 Unit | D24: 开发要求standard
A25: 1 | B25: 丝筒卷绕重量 | C25: kg | D25: 4.87±0.15
A26: 2 | B26: 丝筒卷绕米长 | C26: m | D26: Target value16500
A27: 3 | B27: 丝筒外径 | C27: mm | D27: ≤230
A28: 4 | B28: 动程 | C28: mm | D28: 252±10
A29: 5 | B29: 纸管高度 | C29: mm | D29: 300.00+0.2/-0.1
A30: 6 | B30: 纸管内径 | C30: mm | D30: 94.00+0.2/-0.1
A31: 7 | B31: 纸管外径 | C31: mm | D31: 106.00+0.2/-0.1
A32: 8 | B32: 纸管颜色 | C32: / | D32: 墨白条
A33: 3、可靠性评估参考尼龙工业长丝老化测试。
A34: 4、外观依照尼龙工业长丝外观标准。
A35: 5、双方共同试验尼龙66轮胎帘子布用工业长丝。
A36: 6、依据《新产品制造可行性分析报告》可知，该产品与涤纶高模低缩产品类似，且有尼龙工业长丝开发经验，故制造过程的风险可控。
A37: 备注Remarks
A38: 编制/日期 Compilation/Date | F38: 审批/日期Approval/Date
A39: 表单编号： Form No ： | C39: HLD/CF-04-041-005 | G39: 格式版次：第一版，第1次修改 Format edition: first edition, 1 revision

Sheet 0.02 (变更1)
E1: 密级：秘密★★，未经允许不可查看；保存期限：长期
A2: 新产品开发申请/立项报告 New product development application/project approval report
A3: 序号NO.：0.02
A4: 新产品名称 The name of the new product | C4: ='0.01'!C4:E5 -> 大块金用工业长丝-帘子布事业部PH25657 Nylon 66 tire cord fabric industrial yarn-Tire cord fabric Department PH25657 | F4: 新产品批号和规格Batch number and specification of new products | H4: ='0.01'!H4:K4 -> PH25657-2800dtex/432f
F5: 顾 客 名 称 The customer name | H5: ='0.01'!H5:K5 -> 帘子布事业部
A6: 评估部门The department responsible for evaluation | C6: 技术部 | F6: 评估日期 Date of assessment | H6: =目录!G35 -> 2023年12月22日
A7: 新产品项目开发来源/依据Source/basis of new product project development | C7: ='0.02'!C7 -> 顾客要求/海利得尼龙66轮胎帘子布用工业长丝生产技术
A8: 新 产 品 项 目 开 发 要 求 和 / 或 顾 客 要 求 New product project development requirements and/or customer requirements
A9: 1、指标要求：
A10: NO. | B10: 项目Item | E10: 单位 Unit | G10: 开发要求standard | I10: 测试方法Method of testing
A11: 1 | B11: 线密度 Linear Density | E11: dtex | G11: 2880±30 | I11: GB/T14343
A12: 2 | B12: 线密度变异系数 CV of Linear Density | E12: % | G12: ≤1.60 | I12: GB/T14343
A13: 3 | B13: 断裂强力 Breaking Strength | E13: N | G13: ≥245.0 | I13: GB/T14344
A14: 4 | B14: 断裂强度 Tenacity | E14: cN/dtex | G14: ≥8.50 | I14: GB/T14344
A15: 5 | B15: 强度变异系数CV CV of Tenacity | E15: % | G15: ≤3.00 | I15: GB/T14344
A16: 6 | B16: 断裂伸长率 Breaking Elongation Ratio | E16: % | G16: 20.0±3.0 | I16: GB/T14344
A17: 7 | B17: 伸长变异系数CV CV of Elongation | E17: % | G17: ≤5.00 | I17: GB/T14344
A18: 8 | B18: 中间伸长4.7cN/dtex E.@4.7CN/dtex Load | E18: % | G18: 11.0±1.5 | I18: GB/T14344
A19: 9 | B19: 干热收缩率（177℃×2min×0.05cN/dtex) Shrinkage in Hot Air | E19: % | G19: 6.2±1.5 | I19: HLD method
A20: 10 | B20: 网络度（钩针法） Intermingles（Needle） | E20: nodes/m | G20: 6.0±3.0 | I20: HLD method
A21: 11 | B21: 含油率 Spin Finish Oil | E21: % | G21: 0.90±0.30 | I21: GB/T6504-NMR
A22: 2、产品尺寸要求：
A23: NO. | B23: 项目Item | C23: 单位 Unit | D23: 开发要求standard
A24: 1 | B24: 丝筒卷绕重量 | C24: kg | D24: 5.34±0.15
A25: 2 | B25: 丝筒卷绕米长 | C25: m | D25: Target value18500
A26: 3 | B26: 丝筒外径 | C26: mm | D26: ≤230
A27: 4 | B27: 动程 | C27: mm | D27: 252±10
A28: 5 | B28: 纸管高度 | C28: mm | D28: 300.00+0.2/-0.1
A29: 6 | B29: 纸管内径 | C29: mm | D29: 94.00+0.2/-0.1
A30: 7 | B30: 纸管外径 | C30: mm | D30: 106.00+0.2/-0.1
A31: 8 | B31: 纸管颜色 | C31: / | D31: 墨白条
A32: 3、可靠性评估参考尼龙工业长丝老化测试。
A33: 4、外观依照尼龙工业长丝外观标准。
A34: 5、双方共同试验尼龙66轮胎帘子布用工业长丝。
A35: 6、依据《新产品制造可行性分析报告》可知，该产品与涤纶高模低缩产品类似，且有尼龙工业长丝开发经验，故制造过程的风险可控。
A36: 备注Remarks
A37: 编制/日期 Compilation/Date | F37: 审批/日期Approval/Date
A38: 表单编号：HLD/CF-04-041-005 Form No : HLD/CF-04-041-005 | H38: 格式版次：第一版，第1次修改 Format edition: first edition, 1 revision

Sheet 0.02 (变更2)
E1: 密级：秘密★★，未经允许不可查看；保存期限：长期
A2: 新产品开发申请/立项报告 New product development application/project approval report
I3: 序号NO.： | J3: 0.02
A4: 新产品名称 The name of the new product | C4: ='0.01'!C4:E5 -> 大块金用工业长丝-帘子布事业部PH25657 Nylon 66 tire cord fabric industrial yarn-Tire cord fabric Department PH25657 | F4: 新产品批号和规格Batch number and specification of new products | H4: ='0.01'!H4:K4 -> PH25657-2800dtex/432f
F5: 顾 客 名 称 The customer name | H5: ='0.01'!H5:K5 -> 帘子布事业部
A6: 评估部门The department responsible for evaluation | C6: 技术部 | F6: 评估日期 Date of assessment | H6: =目录!I35 -> 2024年6月4日
A7: 新产品项目开发来源/依据Source/basis of new product project development | C7: ='0.02'!C7 -> 顾客要求/海利得尼龙66轮胎帘子布用工业长丝生产技术
A8: 新 产 品 项 目 开 发 要 求 和 / 或 顾 客 要 求 New product project development requirements and/or customer requirements
A9: 1、指标要求：
A10: NO. | B10: 项目Item | E10: 单位 Unit | G10: 开发要求standard | I10: 测试方法Method of testing
A11: 1 | B11: 线密度 Linear Density | E11: dtex | G11: 2880±30 | I11: GB/T14343
A12: 2 | B12: 线密度变异系数 CV of Linear Density | E12: % | G12: ≤1.60 | I12: GB/T14343
A13: 3 | B13: 断裂强力 Breaking Strength | E13: N | G13: ≥245.0 | I13: GB/T14344
A14: 4 | B14: 断裂强度 Tenacity | E14: cN/dtex | G14: ≥8.50 | I14: GB/T14344
A15: 5 | B15: 强度变异系数CV CV of Tenacity | E15: % | G15: ≤3.00 | I15: GB/T14344
A16: 6 | B16: 断裂伸长率 Breaking Elongation Ratio | E16: % | G16: 20.0±3.0 | I16: GB/T14344
A17: 7 | B17: 伸长变异系数CV CV of Elongation | E17: % | G17: ≤5.00 | I17: GB/T14344
A18: 8 | B18: 中间伸长4.7cN/dtex E.@4.7CN/dtex Load | E18: % | G18: 11.0±1.5 | I18: GB/T14344
A19: 9 | B19: 干热收缩率（177℃×2min×0.05cN/dtex) Shrinkage in Hot Air | E19: % | G19: 5.2±1.5 | I19: HLD method
A20: 10 | B20: 网络度（钩针法） Intermingles（Needle） | E20: nodes/m | G20: 6.0±3.0 | I20: HLD method
A21: 11 | B21: 含油率 Spin Finish Oil | E21: % | G21: 0.90±0.30 | I21: GB/T6504-NMR
A22: 2、产品尺寸要求：
A23: NO. | B23: 项目Item | C23: 单位 Unit | D23: 开发要求standard
A24: 1 | B24: 丝筒卷绕重量 | C24: kg | D24: 5.34±0.15
A25: 2 | B25: 丝筒卷绕米长 | C25: m | D25: Target value18500
A26: 3 | B26: 丝筒外径 | C26: mm | D26: ≤230
A27: 4 | B27: 动程 | C27: mm | D27: 252±10
A28: 5 | B28: 纸管高度 | C28: mm | D28: 300.00+0.2/-0.1
A29: 6 | B29: 纸管内径 | C29: mm | D29: 94.00+0.2/-0.1
A30: 7 | B30: 纸管外径 | C30: mm | D30: 106.00+0.2/-0.1
A31: 8 | B31: 纸管颜色 | C31: / | D31: 墨白条
A32: 3、可靠性评估参考尼龙工业长丝老化测试。
A33: 4、外观依照尼龙工业长丝外观标准。
A34: 5、双方共同试验尼龙66轮胎帘子布用工业长丝。
A35: 6、依据《新产品制造可行性分析报告》可知，该产品与涤纶高模低缩产品类似，且有尼龙工业长丝开发经验，故制造过程的风险可控。
A36: 备注Remarks
A37: 编制/日期 Compilation/Date | F37: 审批/日期Approval/Date
A38: 表单编号： Form No ： | C38: HLD/CF-04-041-005 | G38: 格式版次：第一版，第1次修改 Format edition: first edition, 1 revision

Sheet 0.03
B1: 密级：秘密★★，未经允许不可查看；保存期限：长期
A2: 新产品开发小组成员及职责表 New product development team members and responsibilities
Q3: 序号NO.： | T3: 0.03
A4: 新产品名称 The name of the new product | C4: ='0.01'!C4:E5 -> 大块金用工业长丝-帘子布事业部PH25657 Nylon 66 tire cord fabric industrial yarn-Tire cord fabric Department PH25657 | I4: 新产品批号和规格 Batch number and specification of new products | L4: ='0.01'!H4 -> PH25657-2800dtex/432f
A5: 顾 客 名 称 The customer name | C5: ='0.01'!H5 -> 帘子布事业部 | I5: 成立日期 Date of Establishment | L5: =目录!G8 -> 2023年8月15日
A6: 一、事业部总经理任命APQP小组组长 The DEPUTY General Manager APQP team leader
A7: 二、多方论证小组成员 Member of the multi-argument team
A8: 序号 STT | B8: 姓 名 name | C8: 部 门 department | D8: 联系方式 Contact information | F8: 职责/工作内容 Responsibilities/Work content | M8: 工作负荷是否能满足 Whether the workload can be met | N8: 技能要求 Skill requirement
D9: 电话号码 telephone | E9: 邮箱地址 e-mail | N9: APQP | O9: CP | P9: DFMEA | Q9: PFMEA | R9: MSA | S9: SPC | T9: PPAP | U9: CAD
A10: 组长 The group leader | B10: 顾锋 | C10: 技术部 | D10: 13819374644 | E10: gufeng@halead.com | F10: 组建小组、确定小组成员每一部门代表方的角色和职责及工作，对所提出来的设计、性能要求和制造过程评定其可行性； | M10: 满足 | N10: √ | O10: √ | P10: √ | Q10: √ | S10: √ | T10: √
A11: 组员Team members | B11: 顾钰炜 | C11: 生产部 | D11: 13567303680 | E11: yuwei.gu@halead.com | F11: 负责样品的生产过程实现； | M11: 满足 | N11: √ | O11: √ | Q11: √ | S11: √
B12: 谢明智 | C12: 生产部 | D12: 15968349927 | E12: mingzhi.xie@halead.com | F12: 负责样品在试制过程中的工艺参数的调整及指标跟踪，写试样总结报告； | M12: 满足 | N12: √ | O12: √ | Q12: √ | S12: √
B13: 俞锋 | C13: 技术部 | D13: 15967393217 | E13: feng.yu@halead.com | F13: 负责样品试制的记录汇总；新物料试用评定，建立技术规范； | M13: 满足 | N13: √ | O13: √ | P13: √ | Q13: √ | S13: √ | T13: √
B14: 宋琴 | C14: 供应部 | D14: 13757338425 | E14: qin.song@halead.com | F14: 负责原辅材料采购； | M14: 满足 | N14: √ | O14: √ | T14: √
B15: 熊初珍 | C15: 供应商管理部 | D15: 13967338690 | E15: hrxcz@halead.com | F15: 负责将客户要求传达给供应商；新供应商、新物料开发； | M15: 满足 | N15: √ | O15: √ | T15: √
B16: 叶莉莎 | C16: 财务部 | D16: 15957342609 | E16: lisa@halead.com | F16: 负责财务预算； | M16: 满足 | N16: √
B17: 冯梦婷 | C17: 生管部 | D17: 13750732823 | E17: fmt@halead.com | F17: 负责安排生产计划，开发进度、交付/提交时间及其它必须考虑的限制条件； | M17: 满足 | N17: √ | O17: √
B18: 崔真真 | C18: 质量管理部 | D18: 18268406852 | E18: czz@halead.com | F18: 整个过程产品的质量管理，数据收集整理汇总,与客户质量沟通与对接； | M18: 满足 | N18: √ | O18: √ | Q18: √ | R18: √ | S18: √ | T18: √
B19: 蒋佳贤 | C19: 质量管理部 | D19: 18205839553 | E19: jiaxian.jiang@halead.com | F19: 负责样品在试制过程中的产品检测、数据收集整理； | M19: 满足 | N19: √ | O19: √ | Q19: √ | R19: √ | S19: √ | T19: √
B20: 马俞锋 | C20: 设备动力部 | D20: 13750742172 | E20: myf@halead.com | F20: 负责开发过程中相关设备方面的支持； | M20: 满足 | N20: √ | O20: √ | U20: √
B21: 谢陈龙 | C21: 设备动力部 | D21: 18258360325 | E21: chenlong.xie@halead.com | M21: 满足
B22: 朱翌熹 | C22: 销售部 | D22: 13567301718 | E22: zyx123@halead.com | F22: 负责与客户的联系、沟通、样品试制进程的反馈等。 | M22: 满足 | N22: √ | O22: √ | T22: √
A23: 三、APQP小组所有成员对产品、图样、技术文件、数据资料保密。All members of the APQP team keep confidential the products, drawings, technical documents and data.
A24: 四、当小组成员调岗、离岗或者执行任务超出权限时，由组长负责协调或者指派其他人员负责，必要时更新《小组开发成员责任表》。When team members are transferred, leave their posts, or perform tasks beyond their authority, the team leader is responsible for coordinating or appointing other personnel to be responsible, and update the "Group Development Member Responsibility Form" if necessary.
A25: 编制/日期 Compilation/Date | H25: 审批/日期Approval/Date
A26: 表单编号： Form No： | E26: HLD/CF-04-041-006 | J26: 格式版次：第一版，第2次修改 Format edition: first edition, 2 revision

Sheet 0.03修改版
B1: 密级：秘密★★，未经允许不可查看；保存期限：长期
A2: 新产品开发小组成员及职责表 New product development team members and responsibilities
Q3: 序号NO.： | T3: 0.03
A4: 新产品名称 The name of the new product | C4: ='0.01'!C4:E5 -> 大块金用工业长丝-帘子布事业部PH25657 Nylon 66 tire cord fabric industrial yarn-Tire cord fabric Department PH25657 | I4: 新产品批号和规格 Batch number and specification of new products | L4: ='0.01'!H4 -> PH25657-2800dtex/432f
A5: 顾 客 名 称 The customer name | C5: ='0.01'!H5 -> 帘子布事业部 | I5: 成立日期 Date of Establishment | L5: =目录!G8 -> 2023年8月15日
A6: 一、事业部总经理任命APQP小组组长 The DEPUTY General Manager APQP team leader
A7: 二、多方论证小组成员 Member of the multi-argument team
A8: 序号 STT | B8: 姓 名 name | C8: 部 门 department | D8: 联系方式 Contact information | F8: 职责/工作内容 Responsibilities/Work content | M8: 工作负荷是否能满足 Whether the workload can be met | N8: 技能要求 Skill requirement
D9: 电话号码 telephone | E9: 邮箱地址 e-mail | N9: APQP | O9: CP | P9: DFMEA | Q9: PFMEA | R9: MSA | S9: SPC | T9: PPAP | U9: CAD
A10: 组长 The group leader | B10: 顾锋 | C10: 技术部 | D10: 13819374644 | E10: gufeng@halead.com | F10: 组建小组、确定小组成员每一部门代表方的角色和职责及工作，对所提出来的设计、性能要求和制造过程评定其可行性； | M10: 满足 | N10: √ | O10: √ | P10: √ | Q10: √ | S10: √ | T10: √
A11: 组员Team members | B11: 顾钰炜 | C11: 生产部 | D11: 13567303680 | E11: yuwei.gu@halead.com | F11: 负责样品的生产过程实现； | M11: 满足 | N11: √ | O11: √ | Q11: √ | S11: √
B12: 谢明智 | C12: 生产部 | D12: 15968349927 | E12: mingzhi.xie@halead.com | F12: 负责样品在试制过程中的工艺参数的调整及指标跟踪，写试样总结报告； | M12: 满足 | N12: √ | O12: √ | Q12: √ | S12: √
B13: 俞锋 | C13: 技术部 | D13: 15967393217 | E13: feng.yu@halead.com | F13: 负责样品试制的记录汇总；新物料试用评定，建立技术规范； | M13: 满足 | N13: √ | O13: √ | P13: √ | Q13: √ | S13: √ | T13: √
B14: 宋琴 | C14: 供应部 | D14: 13757338425 | E14: qin.song@halead.com | F14: 负责原辅材料采购； | M14: 满足 | N14: √ | O14: √ | T14: √
B15: 熊初珍 | C15: 供应商管理部 | D15: 13967338690 | E15: hrxcz@halead.com | F15: 负责将客户要求传达给供应商；新供应商、新物料开发； | M15: 满足 | N15: √ | O15: √ | T15: √
B16: 叶莉莎 | C16: 财务部 | D16: 15957342609 | E16: lisa@halead.com | F16: 负责财务预算； | M16: 满足 | N16: √
B17: 冯梦婷 | C17: 生管部 | D17: 13750732823 | E17: fmt@halead.com | F17: 负责安排生产计划，开发进度、交付/提交时间及其它必须考虑的限制条件； | M17: 满足 | N17: √ | O17: √
B18: 崔真真 | C18: 质量管理部 | D18: 18268406852 | E18: czz@halead.com | F18: 整个过程产品的质量管理，数据收集整理汇总,与客户质量沟通与对接； | M18: 满足 | N18: √ | O18: √ | Q18: √ | R18: √ | S18: √ | T18: √
B19: 蒋佳贤 | C19: 质量管理部 | D19: 18205839553 | E19: jiaxian.jiang@halead.com | F19: 负责样品在试制过程中的产品检测、数据收集整理； | M19: 满足 | N19: √ | O19: √ | Q19: √ | R19: √ | S19: √ | T19: √
B20: 马俞锋 | C20: 设备动力部 | D20: 13750742172 | E20: myf@halead.com | F20: 负责开发过程中相关设备方面的支持； | M20: 满足 | N20: √ | O20: √ | U20: √
B21: 谢陈龙 | C21: 设备动力部 | D21: 18258360325 | E21: chenlong.xie@halead.com | M21: 满足
B22: 朱翌熹 | C22: 销售部 | D22: 13567301718 | E22: zyx123@halead.com | F22: 负责与客户的联系、沟通、样品试制进程的反馈等。 | M22: 满足 | N22: √ | O22: √ | T22: √
A23: 客户信息
A24: 序号 STT | B24: 姓 名 name | C24: 部 门 department | D24: 联系方式 Contact information | F24: 职责/工作内容 Responsibilities/Work content | M24: 工作负荷是否能满足 Whether the workload can be met | N24: 技能要求 Skill requirement
D25: 电话号码 telephone | E25: 邮箱地址 e-mail | N25: APQP | O25: CP | P25: DFMEA | Q25: PFMEA | R25: MSA | S25: SPC | T25: PPAP | U25: CAD
A27: 供应商信息
A28: 序号 STT | B28: 姓 名 name | C28: 部 门 department | D28: 联系方式 Contact information | F28: 职责/工作内容 Responsibilities/Work content | M28: 工作负荷是否能满足 Whether the workload can be met | N28: 技能要求 Skill requirement
D29: 电话号码 telephone | E29: 邮箱地址 e-mail | N29: APQP | O29: CP | P29: DFMEA | Q29: PFMEA | R29: MSA | S29: SPC | T29: PPAP | U29: CAD
A31: 三、APQP小组所有成员对产品、图样、技术文件、数据资料保密。All members of the APQP team keep confidential the products, drawings, technical documents and data.
A33: 四、当小组成员调岗、离岗或者执行任务超出权限时，由组长负责协调或者指派其他人员负责，必要时更新《小组开发成员责任表》。When team members are transferred, leave their posts, or perform tasks beyond their authority, the team leader is responsible for coordinating or appointing other personnel to be responsible, and update the "Group Development Member Responsibility Form" if necessary.
A35: 编制/日期 Compilation/Date | H35: 审批/日期Approval/Date
A36: 表单编号： Form No： | E36: HLD/CF-04-041-006 | J36: 格式版次：第一版，第2次修改 Format edition: first edition, 2 revision

Sheet 0.04
P1: 密级：秘密★★，未经允许不可查看；保存期限：长期
A2: 新产品APQP开发计划 New product APQP development plan
BT3: 序号NO.： | BV3: 0.04
A4: 新产品名称 The name of the new product | C4: ='0.01'!C4:E5 -> 大块金用工业长丝-帘子布事业部PH25657 Nylon 66 tire cord fabric industrial yarn-Tire cord fabric Department PH25657 | E4: 新产品批号和规格 Batch number and specification of new products | M4: ='0.01'!H4 -> PH25657-2800dtex/432f | AA4: 顾 客 名 称 The customer name | AL4: ='0.01'!H5 -> 帘子布事业部 | BB4: 日期 Date | BU4: 2023年8月15日
A5: 序号 STT | B5: 工作内容 Job content | D5: 责任部门The responsibility department | E5: 负责人head | F5: 计划plan | J5: 实际The actual | N5: 2023年 | V5: 2024年 | AT5: 2025年 | BU5: 签字 Signature | BV5: 状态
F6: 开始时间 The start time | H6: 结束时间 The end of time | J6: 开始时间 The start time | L6: 完成时间 Completion time | N6: W | O6: W | P6: W | Q6: W | R6: W | S6: W | T6: W | U6: W | V6: W | W6: W | X6: W | Y6: W | Z6: W | AA6: W | AB6: W | AC6: W | AD6: W | AE6: W | AF6: W | AG6: W | AH6: W | AI6: W | AJ6: W | AK6: W | AL6: W | AM6: W | AN6: W | AO6: W | AP6: W | AQ6: W | AR6: W | AS6: W | AT6: W | AU6: W | AV6: W | AW6: W | AX6: W | AY6: W | AZ6: W | BA6: W | BB6: W | BC6: W | BD6: W | BE6: W | BF6: W | BG6: W | BH6: W | BI6: W | BJ6: W | BK6: W | BL6: W | BM6: W | BN6: W | BO6: W | BP6: W | BQ6: W | BR6: W | BS6: W | BT6: W | BV6: 完成 | BW6: 执行中 | BX6: 未完成
N7: 32 | O7: 33 | P7: 34 | Q7: 35 | R7: 36 | S7: 37 | T7: 38 | U7: 51 | V7: 20 | W7: 21 | X7: 22 | Y7: 23 | Z7: 24 | AA7: 25 | AB7: 26 | AC7: 27 | AD7: 29 | AE7: 34 | AF7: 35 | AG7: 36 | AH7: 37 | AI7: 38 | AJ7: 43 | AK7: 44 | AL7: 45 | AM7: 46 | AN7: 47 | AO7: 49 | AP7: 50 | AQ7: 51 | AR7: 52 | AS7: 53 | AT7: 10 | AU7: 11 | AV7: 12 | AW7: 13 | AX7: 14 | AY7: 15 | AZ7: 16 | BA7: 17 | BB7: 18 | BC7: 19 | BD7: 20 | BE7: 21 | BF7: 22 | BG7: 23 | BH7: 24 | BI7: 25 | BJ7: 29 | BK7: 30 | BL7: 35 | BM7: 36 | BN7: 37 | BO7: 38 | BP7: 39 | BQ7: 40 | BR7: 41 | BS7: 50 | BT7: 51 | BW7: 执行中 | BX7: 未完成
A8: 0 | B8: 项目启动阶段 Project start-up phase
A9: 0.01 | B9: 新产品制造可行性分析报告 New product manufacturing feasibility analysis report | D9: 技术部 | E9: 俞锋 | F9: =WEEKNUM(G9) -> 33 | G9: 2023/8/14 | H9: =WEEKNUM(I9) -> 33 | I9: =G9+1 -> 45153 | J9: =WEEKNUM(K9) -> 33 | K9: =M9 -> 45152 | L9: =WEEKNUM(M9) -> 33 | M9: =目录!H6 -> 45152
A11: 0.02 | B11: 新产品开发申请/立项报告（内部里程碑） New product development application/project approval report(Internal milestones） | D11: 技术部 | E11: 俞锋 | F11: =WEEKNUM(G11) -> 33 | G11: 2023/8/15 | H11: =WEEKNUM(I11) -> 33 | I11: =G11+1 -> 45154 | J11: =WEEKNUM(K11) -> 33 | K11: =M11 -> 45153 | L11: =WEEKNUM(M11) -> 33 | M11: =目录!H7 -> 45153
A13: 0.03 | B13: 新产品开发小组成员及职责表 New product development team members and responsibilities | D13: 技术部 | E13: 俞锋 | F13: =WEEKNUM(G13) -> 33 | G13: 2023/8/16 | H13: =WEEKNUM(I13) -> 33 | I13: =G13+1 -> 45155 | J13: =WEEKNUM(K13) -> 33 | K13: =M13 -> 45153 | L13: =WEEKNUM(M13) -> 33 | M13: =目录!H8 -> 45153
A15: 0.04 | B15: 新产品APQP开发计划（内部里程碑） New product APQP development plan(Internal milestones） | D15: 技术部 | E15: 俞锋 | F15: =WEEKNUM(G15) -> 33 | G15: 2023/8/17 | H15: =WEEKNUM(I15) -> 33 | I15: =G15+1 -> 45156 | J15: =WEEKNUM(K15) -> 33 | K15: =M15 -> 45153 | L15: =WEEKNUM(M15) -> 33 | M15: =目录!H9 -> 45153
A17: 0.05 | B17: 设计评审/验证/确认记录（设计开发输入） Design Review/validation/validation record (Design and development input) | D17: 项目小组 | E17: 俞锋 | F17: =WEEKNUM(G17) -> 33 | G17: 2023/8/18 | H17: =WEEKNUM(I17) -> 33 | I17: =G17+1 -> 45157 | J17: =WEEKNUM(K17) -> 33 | K17: =M17 -> 45154 | L17: =WEEKNUM(M17) -> 33 | M17: =目录!H10 -> 45154
A19: 1 | B19: 策划和定义项目 Plan and identify projects
A20: 1.01 | B20: 设计开发任务书 Design and development specification | D20: 技术部 | E20: 俞锋 | F20: =WEEKNUM(G20) -> 33 | G20: 2023/8/19 | H20: =WEEKNUM(I20) -> 34 | I20: =G20+1 -> 45158 | J20: =WEEKNUM(K20) -> 33 | K20: =M20 -> 45155 | L20: =WEEKNUM(M20) -> 33 | M20: =目录!H12 -> 45155
A22: 1.02 | B22: 初始材料清单 BOM Initial material list BOM | D22: 技术部 | E22: 俞锋 | F22: =WEEKNUM(G22) -> 34 | G22: 2023/8/20 | H22: =WEEKNUM(I22) -> 34 | I22: =G22+1 -> 45159 | J22: =WEEKNUM(K22) -> 33 | K22: =M22 -> 45156 | L22: =WEEKNUM(M22) -> 33 | M22: =目录!H13 -> 45156
A24: 1.03 | B24: 成本核算及报价表 Cost accounting and quotation sheet | D24: 项目小组 | E24: 俞锋 | F24: =WEEKNUM(G24) -> 34 | G24: 2023/8/21 | H24: =WEEKNUM(I24) -> 34 | I24: =G24+1 -> 45160 | J24: =WEEKNUM(K24) -> 33 | K24: =M24 -> 45156 | L24: =WEEKNUM(M24) -> 33 | M24: =目录!H14 -> 45156
A26: 1.04 | B26: 过程流程图（初始） Process flow Chart (initial) | D26: 技术部 | E26: 俞锋 | F26: =WEEKNUM(G26) -> 34 | G26: 2023/8/22 | H26: =WEEKNUM(I26) -> 34 | I26: =G26+1 -> 45161 | J26: =WEEKNUM(K26) -> 33 | K26: =M26 -> 45157 | L26: =WEEKNUM(M26) -> 33 | M26: =目录!H15 -> 45157
A28: 1.05 | B28: 特殊特性符合转化表 The special characteristics correspond to the transformation table | D28: 技术部 | E28: 俞锋 | F28: =WEEKNUM(G28) -> 34 | G28: 2023/8/23 | H28: =WEEKNUM(I28) -> 34 | I28: =G28+1 -> 45162 | J28: =WEEKNUM(K28) -> 34 | K28: =M28 -> 45158 | L28: =WEEKNUM(M28) -> 34 | M28: =目录!H16 -> 45158
A30: 1.06 | B30: 产品/过程特殊特性清单（初始） List of product/process special features (initial) | D30: 技术部 | E30: 俞锋 | F30: =WEEKNUM(G30) -> 34 | G30: 2023/8/24 | H30: =WEEKNUM(I30) -> 34 | I30: =G30+1 -> 45163 | J30: =WEEKNUM(K30) -> 34 | K30: =M30 -> 45158 | L30: =WEEKNUM(M30) -> 34 | M30: =目录!H17 -> 45158
A32: 1.07 | B32: 产品安全识别表 Product safety identification form | D32: 技术部 | E32: 俞锋 | F32: =WEEKNUM(G32) -> 34 | G32: 2023/8/25 | H32: =WEEKNUM(I32) -> 34 | I32: =G32+1 -> 45164 | J32: =WEEKNUM(K32) -> 34 | K32: =M32 -> 45159 | L32: =WEEKNUM(M32) -> 34 | M32: =目录!H18 -> 45159
A34: 1.08 | B34: 产品保证计划 Product Assurance Program | D34: 技术部 | E34: 俞锋 | F34: =WEEKNUM(G34) -> 34 | G34: 2023/8/26 | H34: =WEEKNUM(I34) -> 35 | I34: =G34+1 -> 45165 | J34: =WEEKNUM(K34) -> 34 | K34: =M34 -> 45159 | L34: =WEEKNUM(M34) -> 34 | M34: =目录!H19 -> 45159
A36: 1.09 | B36: 项目变更登记表 Project change registration form | D36: 技术部 | E36: 俞锋 | F36: =WEEKNUM(G36) -> 35 | G36: 2023/8/27 | H36: =WEEKNUM(I36) -> 35 | I36: =G36+1 -> 45166 | J36: =WEEKNUM(K36) -> 34 | K36: =M36 -> 45159 | L36: =WEEKNUM(M36) -> 34 | M36: =目录!H20 -> 45159
A38: 1.10 | B38: 风险评估和缓解计划 Risk assessment and mitigation planning | D38: 技术部 | E38: 俞锋 | F38: =WEEKNUM(G38) -> 35 | G38: 2023/8/28 | H38: =WEEKNUM(I38) -> 35 | I38: =G38+1 -> 45167 | J38: =WEEKNUM(K38) -> 34 | K38: =M38 -> 45159 | L38: =WEEKNUM(M38) -> 34 | M38: =目录!H21 -> 45159
A40: 1.11 | B40: 设计评审/验证/确认记录（产品设计输入） Design Review/validation/validation record (Product design input) | D40: 项目小组 | E40: 俞锋 | F40: =WEEKNUM(G40) -> 35 | G40: 2023/8/29 | H40: =WEEKNUM(I40) -> 35 | I40: =G40+1 -> 45168 | J40: =WEEKNUM(K40) -> 34 | K40: =M40 -> 45160 | L40: =WEEKNUM(M40) -> 34 | M40: =目录!H22 -> 45160
A42: 1.12 | B42: 阶段性总结和管理者支持 Periodic summary and manager support | D42: 项目小组 | E42: 俞锋 | F42: =WEEKNUM(G42) -> 35 | G42: 2023/8/30 | H42: =WEEKNUM(I42) -> 35 | I42: =G42+1 -> 45169 | J42: =WEEKNUM(K42) -> 34 | K42: =M42 -> 45160 | L42: =WEEKNUM(M42) -> 34 | M42: =目录!H23 -> 45160
A44: 2 | B44: 产品设计与开发 Product design and development
A45: 2.01 | B45: DFMEA | D45: 技术部 | E45: 俞锋 | F45: =WEEKNUM(G45) -> 35 | G45: 2023/9/1 | H45: =WEEKNUM(I45) -> 35 | I45: =G45+1 -> 45171 | J45: =WEEKNUM(K45) -> 34 | K45: =M45 -> 45160 | L45: =WEEKNUM(M45) -> 34 | M45: =目录!H25 -> 45160
A47: 2.02 | B47: DFMEA检查表 Checklist for DFMEA | D47: 技术部 | E47: 俞锋 | F47: =WEEKNUM(G47) -> 35 | G47: 2023/9/2 | H47: =WEEKNUM(I47) -> 36 | I47: =G47+1 -> 45172 | J47: =WEEKNUM(K47) -> 34 | K47: =M47 -> 45160 | L47: =WEEKNUM(M47) -> 34 | M47: =目录!H26 -> 45160
A49: 2.03 | B49: 产品技术规范 Product technical specification | D49: 技术部 | E49: 俞锋 | F49: =WEEKNUM(G49) -> 36 | G49: 2023/9/3 | H49: =WEEKNUM(I49) -> 36 | I49: =G49+1 -> 45173 | J49: =WEEKNUM(K49) -> 34 | K49: =M49 -> 45161 | L49: =WEEKNUM(M49) -> 34 | M49: =目录!H27 -> 45161
A51: 2.04 | B51: 设计评审/验证/确认记录 （可制造性评审） Design Review/Validation/validation Record (Manufacturability review) | D51: 项目小组 | E51: 俞锋 | F51: =WEEKNUM(G51) -> 36 | G51: 2023/9/4 | H51: =WEEKNUM(I51) -> 36 | I51: =G51+1 -> 45174 | J51: =WEEKNUM(K51) -> 34 | K51: =M51 -> 45161 | L51: =WEEKNUM(M51) -> 34 | M51: =目录!H28 -> 45161
A53: 2.05 | B53: 控制计划（样件） Control plan (Prototype) | D53: 技术部 | E53: 俞锋 | F53: =WEEKNUM(G53) -> 36 | G53: 2023/9/5 | H53: =WEEKNUM(I53) -> 36 | I53: =G53+1 -> 45175 | J53: =WEEKNUM(K53) -> 34 | K53: =M53 -> 45162 | L53: =WEEKNUM(M53) -> 34 | M53: =目录!H29 -> 45162
A55: 2.06 | B55: 控制计划检查表 Control plan checklist | D55: 项目小组 | E55: 俞锋 | F55: =WEEKNUM(G55) -> 36 | G55: 2023/9/6 | H55: =WEEKNUM(I55) -> 36 | I55: =G55+1 -> 45176 | J55: =WEEKNUM(K55) -> 34 | K55: =M55 -> 45162 | L55: =WEEKNUM(M55) -> 34 | M55: =目录!H30 -> 45162
A57: 2.07 | B57: 工艺标准（样件） Process standard (Prototype) | D57: 技术部 | E57: 俞锋 | F57: =WEEKNUM(G57) -> 36 | G57: 2023/9/7 | H57: =WEEKNUM(I57) -> 36 | I57: =G57+1 -> 45177 | J57: =WEEKNUM(K57) -> 34 | K57: =M57 -> 45163 | L57: =WEEKNUM(M57) -> 34 | M57: =目录!H31 -> 45163
A59: 2.08 | B59: 生产通知单（样件）（内部里程碑） Production order (Prototype)(Internal milestones） | D59: 生管部 | E59: 冯梦婷 | F59: =WEEKNUM(G59) -> 36 | G59: 2023/9/8 | H59: =WEEKNUM(I59) -> 36 | I59: =G59+1 -> 45178 | J59: =WEEKNUM(K59) -> 34 | K59: =M59 -> 45164 | L59: =WEEKNUM(M59) -> 34 | M59: =目录!H32 -> 45164
A61: 2.09 | B61: 设计验证报告 Design verification report | D61: 技术部 | E61: 俞锋 | F61: =WEEKNUM(G61) -> 36 | G61: 2023/9/9 | H61: =WEEKNUM(I61) -> 37 | I61: =G61+1 -> 45179 | J61: =WEEKNUM(K61) -> 35 | K61: =M61 -> 45166 | L61: =WEEKNUM(M61) -> 35 | M61: =目录!H33 -> 45166
A63: 2.10 | B63: 设计评审验证确认记录-产品设计输出评审 Design Review Validation Record - product design output review | D63: 项目小组 | E63: 俞锋 | F63: =WEEKNUM(G63) -> 37 | G63: 2023/9/10 | H63: =WEEKNUM(I63) -> 37 | I63: =G63+1 -> 45180 | J63: =WEEKNUM(K63) -> 35 | K63: =M63 -> 45167 | L63: =WEEKNUM(M63) -> 35 | M63: =目录!H34 -> 45167
A65: 2.11 | B65: 设计更改记录 Design change record | D65: 项目小组 | E65: 俞锋 | F65: =WEEKNUM(G65) -> 0 | J65: =WEEKNUM(K65) -> 51 | K65: =M65 -> 45282 | L65: =WEEKNUM(M65) -> 51 | M65: =目录!H35 -> 45282
A67: 2.12 | B67: 工程规范确认表 Engineering specification confirmation form | D67: 技术部 | E67: 俞锋 | F67: =WEEKNUM(G67) -> 37 | G67: 2023/9/11 | H67: =WEEKNUM(I67) -> 37 | I67: =G67+1 -> 45181 | J67: =WEEKNUM(K67) -> 35 | K67: =M67 -> 45168 | L67: =WEEKNUM(M67) -> 35 | M67: =目录!H36 -> 45168
A69: 2.13 | B69: 材料规范确认表 Material specification confirmation form | D69: 技术部 | E69: 俞锋 | F69: =WEEKNUM(G69) -> 37 | G69: 2023/9/12 | H69: =WEEKNUM(I69) -> 37 | I69: =G69+1 -> 45182 | J69: =WEEKNUM(K69) -> 35 | K69: =M69 -> 45169 | L69: =WEEKNUM(M69) -> 35 | M69: =目录!H37 -> 45169
A71: 2.14 | B71: 设备、工装和设施清单 List of equipment、 tooling and facilities | D71: 设备部 | E71: 马俞锋 | F71: =WEEKNUM(G71) -> 37 | G71: 2023/9/13 | H71: =WEEKNUM(I71) -> 37 | I71: =G71+1 -> 45183 | J71: =WEEKNUM(K71) -> 35 | K71: =M71 -> 45170 | L71: =WEEKNUM(M71) -> 35 | M71: =目录!H38 -> 45170
A73: 2.15 | B73: 量具/试验设备清单 List of measuring tool/ test equipment | D73: 质量部 | E73: 崔真真 | F73: =WEEKNUM(G73) -> 37 | G73: 2023/9/14 | H73: =WEEKNUM(I73) -> 37 | I73: =G73+1 -> 45184 | J73: =WEEKNUM(K73) -> 35 | K73: =M73 -> 45170 | L73: =WEEKNUM(M73) -> 35 | M73: =目录!H39 -> 45170
A75: 2.16 | B75: 产品/过程特殊特性清单 List of product/process special features | D75: 技术部 | E75: 俞锋 | F75: =WEEKNUM(G75) -> 37 | G75: 2023/9/15 | H75: =WEEKNUM(I75) -> 37 | I75: =G75+1 -> 45185 | J75: =WEEKNUM(K75) -> 35 | K75: =M75 -> 45171 | L75: =WEEKNUM(M75) -> 35 | M75: =目录!H40 -> 45171
A77: 2.17 | B77: 小组可行性承诺 Group Feasibility Commitment | D77: 项目小组 | E77: 俞锋 | F77: =WEEKNUM(G77) -> 37 | G77: 2023/9/16 | H77: =WEEKNUM(I77) -> 38 | I77: =G77+1 -> 45186 | J77: =WEEKNUM(K77) -> 36 | K77: =M77 -> 45172 | L77: =WEEKNUM(M77) -> 36 | M77: =目录!H41 -> 45172
A79: 2.18 | B79: 阶段性总结和管理者支持 Periodic summary and manager support | D79: 项目小组 | E79: 俞锋 | F79: =WEEKNUM(G79) -> 38 | G79: 2023/9/17 | H79: =WEEKNUM(I79) -> 38 | I79: =G79+1 -> 45187 | J79: =WEEKNUM(K79) -> 36 | K79: =M79 -> 45173 | L79: =WEEKNUM(M79) -> 36 | M79: =目录!H42 -> 45173
A81: 3 | B81: 过程设计与开发 Process design and development
A82: 3.01 | B82: 设计评审/验证/确认记（过程设计输入） Design Review/Validation/validation (Process design input) | D82: 项目小组 | E82: 俞锋 | F82: =WEEKNUM(G82) -> 34 | G82: 2024/8/18 | H82: =WEEKNUM(I82) -> 34 | I82: =G82+1 -> 45523 | J82: =WEEKNUM(K82) -> 22 | K82: =M82 -> 45440 | L82: =WEEKNUM(M82) -> 22 | M82: =目录!H44 -> 45440
A84: 3.02 | B84: 产品包装标准及规范 Product packaging standards and specifications | D84: 技术部 | E84: 俞锋 | F84: =WEEKNUM(G84) -> 34 | G84: 2024/8/19 | H84: =WEEKNUM(I84) -> 34 | I84: =G84+1 -> 45524 | J84: =WEEKNUM(K84) -> 22 | K84: =M84 -> 45440 | L84: =WEEKNUM(M84) -> 22 | M84: =目录!H45 -> 45440
A86: 3.03 | B86: 产品/过程质量体系检查表 Product/process quality system checklist | D86: 技术部 | E86: 俞锋 | F86: =WEEKNUM(G86) -> 34 | G86: 2024/8/20 | H86: =WEEKNUM(I86) -> 34 | I86: =G86+1 -> 45525 | J86: =WEEKNUM(K86) -> 22 | K86: =M86 -> 45441 | L86: =WEEKNUM(M86) -> 22 | M86: =目录!H46 -> 45441
A88: 3.04 | B88: 车间平面布置图 Floor plan of workshop | D88: 技术部 | E88: 俞锋 | F88: =WEEKNUM(G88) -> 34 | G88: 2024/8/21 | H88: =WEEKNUM(I88) -> 34 | I88: =G88+1 -> 45526 | J88: =WEEKNUM(K88) -> 22 | K88: =M88 -> 45441 | L88: =WEEKNUM(M88) -> 22 | M88: =目录!H47 -> 45441
A90: 3.05 | B90: 过程流程图（内部里程碑） Process flow chart(Internal milestones） | D90: 技术部 | E90: 俞锋 | F90: =WEEKNUM(G90) -> 34 | G90: 2024/8/22 | H90: =WEEKNUM(I90) -> 34 | I90: =G90+1 -> 45527 | J90: =WEEKNUM(K90) -> 22 | K90: =M90 -> 45442 | L90: =WEEKNUM(M90) -> 22 | M90: =目录!H48 -> 45442
A92: 3.06 | B92: 过程流程图检查表 Checklist for process flow chart | D92: 项目小组 | E92: 俞锋 | F92: =WEEKNUM(G92) -> 34 | G92: 2024/8/23 | H92: =WEEKNUM(I92) -> 34 | I92: =G92+1 -> 45528 | J92: =WEEKNUM(K92) -> 22 | K92: =M92 -> 45442 | L92: =WEEKNUM(M92) -> 22 | M92: =目录!H49 -> 45442
A94: 3.07 | B94: 特性矩阵图 Characteristic matrix diagram | D94: 技术部 | E94: 俞锋 | F94: =WEEKNUM(G94) -> 34 | G94: 2024/8/24 | H94: =WEEKNUM(I94) -> 35 | I94: =G94+1 -> 45529 | J94: =WEEKNUM(K94) -> 22 | K94: =M94 -> 45443 | L94: =WEEKNUM(M94) -> 22 | M94: =目录!H50 -> 45443
A96: 3.08 | B96: PFMEA（内部里程碑） PFMEA(Internal milestones） | D96: 技术部 | E96: 俞锋 | F96: =WEEKNUM(G96) -> 35 | G96: 2024/8/25 | H96: =WEEKNUM(I96) -> 35 | I96: =G96+1 -> 45530 | J96: =WEEKNUM(K96) -> 22 | K96: =M96 -> 45444 | L96: =WEEKNUM(M96) -> 22 | M96: =目录!H51 -> 45444
A98: 3.09 | B98: PFMEA检查表 PFMEA checklist | D98: 项目小组 | E98: 俞锋 | F98: =WEEKNUM(G98) -> 35 | G98: 2024/8/26 | H98: =WEEKNUM(I98) -> 35 | I98: =G98+1 -> 45531 | J98: =WEEKNUM(K98) -> 22 | K98: =M98 -> 45444 | L98: =WEEKNUM(M98) -> 22 | M98: =目录!H52 -> 45444
A100: 3.10 | B100: 控制计划（试生产） Control plan (Pre-launch) | D100: 技术部 | E100: 俞锋 | F100: =WEEKNUM(G100) -> 35 | G100: 2024/8/27 | H100: =WEEKNUM(I100) -> 35 | I100: =G100+1 -> 45532 | J100: =WEEKNUM(K100) -> 23 | K100: =M100 -> 45445 | L100: =WEEKNUM(M100) -> 23 | M100: =目录!H53 -> 45445
A102: 3.11 | B102: 控制计划检查表 Control plan checklist | D102: 项目小组 | E102: 俞锋 | F102: =WEEKNUM(G102) -> 35 | G102: 2024/8/28 | H102: =WEEKNUM(I102) -> 35 | I102: =G102+1 -> 45533 | J102: =WEEKNUM(K102) -> 23 | K102: =M102 -> 45445 | L102: =WEEKNUM(M102) -> 23 | M102: =目录!H54 -> 45445
A104: 3.12 | B104: 标准文件核查表 Standard documentation checklist | D104: 技术部 | E104: 俞锋 | F104: =WEEKNUM(G104) -> 35 | G104: 2024/8/29 | H104: =WEEKNUM(I104) -> 35 | I104: =G104+1 -> 45534 | J104: =WEEKNUM(K104) -> 23 | K104: =M104 -> 45446 | L104: =WEEKNUM(M104) -> 23 | M104: =目录!H55 -> 45446
A106: 3.13 | B106: 测量系统分析（MSA）计划 Measurement system Analysis (MSA) plan | D106: 质量部 | E106: 崔真真 | F106: =WEEKNUM(G106) -> 35 | G106: 2024/8/30 | H106: =WEEKNUM(I106) -> 35 | I106: =G106+1 -> 45535 | J106: =WEEKNUM(K106) -> 23 | K106: =M106 -> 45447 | L106: =WEEKNUM(M106) -> 23 | M106: =目录!H56 -> 45447
A108: 3.14 | B108: 初始过程能力研究计划 Initial process capability research plan | D108: 质量部 | E108: 崔真真 | F108: =WEEKNUM(G108) -> 35 | G108: 2024/8/31 | H108: =WEEKNUM(I108) -> 36 | I108: =G108+1 -> 45536 | J108: =WEEKNUM(K108) -> 23 | K108: =M108 -> 45447 | L108: =WEEKNUM(M108) -> 23 | M108: =目录!H57 -> 45447
A110: 3.15 | B110: 设备过程能力研究计划 Equipment process capability Research Program | D110: 质量部 | E110: 崔真真 | F110: =WEEKNUM(G110) -> 36 | G110: 2024/9/1 | H110: =WEEKNUM(I110) -> 36 | I110: =G110+1 -> 45537 | J110: =WEEKNUM(K110) -> 23 | K110: =M110 -> 45447 | L110: =WEEKNUM(M110) -> 23 | M110: =目录!H58 -> 45447
A112: 3.16 | B112: 防错装置清单 List of error prevention devices | D112: 技术部 | E112: 俞锋 | F112: =WEEKNUM(G112) -> 36 | G112: 2024/9/2 | H112: =WEEKNUM(I112) -> 36 | I112: =G112+1 -> 45538 | J112: =WEEKNUM(K112) -> 23 | K112: =M112 -> 45448 | L112: =WEEKNUM(M112) -> 23 | M112: =目录!H59 -> 45448
A114: 3.17 | B114: 设备维护保养计划 Equipment maintenance plan | D114: 设备部 | E114: 马俞锋 | F114: =WEEKNUM(G114) -> 36 | G114: 2024/9/3 | H114: =WEEKNUM(I114) -> 36 | I114: =G114+1 -> 45539 | J114: =WEEKNUM(K114) -> 23 | K114: =M114 -> 45448 | L114: =WEEKNUM(M114) -> 23 | M114: =目录!H60 -> 45448
A116: 3.18 | B116: 阶段性总结和管理者支持 Periodic summary and manager support | D116: 项目小组 | E116: 俞锋 | F116: =WEEKNUM(G116) -> 36 | G116: 2024/9/4 | H116: =WEEKNUM(I116) -> 36 | I116: =G116+1 -> 45540 | J116: =WEEKNUM(K116) -> 23 | K116: =M116 -> 45449 | L116: =WEEKNUM(M116) -> 23 | M116: =目录!H61 -> 45449
A118: 4 | B118: 产品和过程确认 Product and process validation
A119: 4.01 | B119: 工艺标准（试生产） Process standard (Pre-launch) | D119: 技术部 | E119: 俞锋 | F119: =WEEKNUM(G119) -> 45 | G119: 2024/11/5 | H119: =WEEKNUM(I119) -> 45 | I119: =G119+1 -> 45602 | J119: =WEEKNUM(K119) -> 23 | K119: =M119 -> 45449 | L119: =WEEKNUM(M119) -> 23 | M119: =目录!H63 -> 45449
A121: 4.02 | B121: 生产通知单（试生产）（内部里程碑） Production order (Pre-launch)(Internal milestones） | D121: 生管部 | E121: 冯梦婷 | F121: =WEEKNUM(G121) -> 45 | G121: 2024/11/6 | H121: =WEEKNUM(I121) -> 45 | I121: =G121+1 -> 45603 | J121: =WEEKNUM(K121) -> 23 | K121: =M121 -> 45450 | L121: =WEEKNUM(M121) -> 23 | M121: =目录!H64 -> 45450
A123: 4.03 | B123: 防错验证报告 Error proof verification report | D123: 技术部 | E123: 俞锋 | F123: =WEEKNUM(G123) -> 45 | G123: 2024/11/7 | H123: =WEEKNUM(I123) -> 45 | I123: =G123+1 -> 45604 | J123: =WEEKNUM(K123) -> 23 | K123: =M123 -> 45450 | L123: =WEEKNUM(M123) -> 23 | M123: =目录!H65 -> 45450
A125: 4.04 | B125: 测量系统分析报告（内部里程碑） Measurement system analysis report(Internal milestones） | D125: 质量部 | E125: 崔真真 | F125: =WEEKNUM(G125) -> 36 | G125: 2025/9/1 | H125: =WEEKNUM(I125) -> 40 | I125: 2025/9/30 | J125: =WEEKNUM(K125) -> 30 | K125: =M125 -> 45859 | L125: =WEEKNUM(M125) -> 30 | M125: =目录!H66 -> 45859
A127: 4.05 | B127: 初始过程能力、设备过程能力分析报告（内部里程碑） Initial process capability、Equipment process capability analysis report(Internal milestones） | D127: 质量部 | E127: 崔真真 | F127: =WEEKNUM(G127) -> 45 | G127: 2024/11/7 | H127: =WEEKNUM(I127) -> 49 | I127: =G127+30 -> 45633 | J127: =WEEKNUM(K127) -> 25 | K127: =M127 -> 45463 | L127: =WEEKNUM(M127) -> 25 | M127: =目录!H67 -> 45463
A129: 4.06 | B129: 设计验证报告 Design verification report | D129: 技术部 | E129: 俞锋 | F129: =WEEKNUM(G129) -> 49 | G129: 2024/12/7 | H129: =WEEKNUM(I129) -> 50 | I129: =G129+1 -> 45634 | J129: =WEEKNUM(K129) -> 25 | K129: =M129 -> 45465 | L129: =WEEKNUM(M129) -> 25 | M129: =目录!H68 -> 45465
A131: 4.07 | B131: 设计评审验证确认记录-过程设计输出评审 Design Review Validation Record - Process design output review | D131: 项目小组 | E131: 俞锋 | F131: =WEEKNUM(G131) -> 50 | G131: 2024/12/8 | H131: =WEEKNUM(I131) -> 50 | I131: =G131+1 -> 45635 | J131: =WEEKNUM(K131) -> 25 | K131: =M131 -> 45465 | L131: =WEEKNUM(M131) -> 25 | M131: =目录!H69 -> 45465
A133: 4.08 | B133: 设计更改记录 Design change record | D133: 项目小组 | E133: 俞锋 | F133: =WEEKNUM(G133) -> 0 | J133: =WEEKNUM(K133) -> 19 | K133: =M133 -> 45783 | L133: =WEEKNUM(M133) -> 19 | M133: =目录!H70 -> 45783
A135: 4.09 | B135: 包装评价报告 Package evaluation report | D135: 技术部 | E135: 俞锋 | F135: =WEEKNUM(G135) -> 15 | G135: 2025/4/12 | H135: =WEEKNUM(I135) -> 16 | I135: =G135+1 -> 45760 | J135: =WEEKNUM(K135) -> 11 | K135: =M135 -> 45731 | L135: =WEEKNUM(M135) -> 11 | M135: =目录!H71 -> 45731
A137: 4.10 | B137: 控制计划（量产）（内部里程碑） Control plan (Mass production)(Internal milestones） | D137: 技术部 | E137: 俞锋 | F137: =WEEKNUM(G137) -> 17 | G137: 2025/4/23 | H137: =WEEKNUM(I137) -> 17 | I137: =G137+1 -> 45771 | J137: =WEEKNUM(K137) -> 12 | K137: =M137 -> 45736 | L137: =WEEKNUM(M137) -> 12 | M137: =目录!H72 -> 45736
A139: 4.11 | B139: 控制计划检查表 Control plan checklist | D139: 项目小组 | E139: 俞锋 | F139: =WEEKNUM(G139) -> 17 | G139: 2025/4/24 | H139: =WEEKNUM(I139) -> 17 | I139: =G139+1 -> 45772 | J139: =WEEKNUM(K139) -> 12 | K139: =M139 -> 45737 | L139: =WEEKNUM(M139) -> 12 | M139: =目录!H73 -> 45737
A141: 4.12 | B141: 零件提交保证书（PSW）（内部里程碑） Parts Submission Guarantee (PSW)(Internal milestones） | D141: 质量部 | E141: 崔真真 | F141: =WEEKNUM(G141) -> 17 | G141: 2025/4/25 | H141: =WEEKNUM(I141) -> 17 | I141: =G141+1 -> 45773 | J141: =WEEKNUM(K141) -> 17 | K141: =M141 -> 45771 | L141: =WEEKNUM(M141) -> 17 | M141: =目录!H74 -> 45771
A143: 4.13 | B143: 控制计划（安全投产）（内部里程碑） Control plan (Safe operation)(Internal milestones） | D143: 技术部 | E143: 俞锋 | F143: =WEEKNUM(G143) -> 25 | G143: 2025/6/15 | H143: =WEEKNUM(I143) -> 25 | I143: =G143+1 -> 45824 | J143: =WEEKNUM(K143) -> 18 | K143: =M143 -> 45776 | L143: =WEEKNUM(M143) -> 18 | M143: =目录!H75 -> 45776
A145: 4.14 | B145: 控制计划检查表 Control plan checklist | D145: 项目小组 | E145: 俞锋 | F145: =WEEKNUM(G145) -> 25 | G145: 2025/6/16 | H145: =WEEKNUM(I145) -> 25 | I145: =G145+1 -> 45825 | J145: =WEEKNUM(K145) -> 18 | K145: =M145 -> 45777 | L145: =WEEKNUM(M145) -> 18 | M145: =目录!H76 -> 45777
A147: 4.15 | B147: 工艺标准（安全投产） Process standard (Safe operation) | D147: 技术部 | E147: 俞锋 | F147: =WEEKNUM(G147) -> 25 | G147: 2025/6/17 | H147: =WEEKNUM(I147) -> 25 | I147: =G147+1 -> 45826 | J147: =WEEKNUM(K147) -> 19 | K147: =M147 -> 45783 | L147: =WEEKNUM(M147) -> 19 | M147: =目录!H77 -> 45783
A149: 4.16 | B149: 生产通知单（安全投产）（内部里程碑） Production order(Safe operation)(Internal milestones） | D149: 生管部 | E149: 冯梦婷 | F149: =WEEKNUM(G149) -> 25 | G149: 2025/6/18 | H149: =WEEKNUM(I149) -> 25 | I149: =G149+1 -> 45827 | J149: =WEEKNUM(K149) -> 19 | K149: =M149 -> 45784 | L149: =WEEKNUM(M149) -> 19 | M149: =目录!H78 -> 45784
A151: 4.17 | B151: 设计验证报告 Design verification report | D151: 技术部 | E151: 俞锋 | F151: =WEEKNUM(G151) -> 38 | G151: 2025/9/19 | H151: =WEEKNUM(I151) -> 38 | I151: =G151+1 -> 45920 | J151: =WEEKNUM(K151) -> 30 | K151: =M151 -> 45864 | L151: =WEEKNUM(M151) -> 30 | M151: =目录!H79 -> 45864
A153: 4.18 | B153: 包装评价报告 Package evaluation report | D153: 项目小组 | E153: 俞锋 | F153: =WEEKNUM(G153) -> 38 | G153: 2025/9/20 | H153: =WEEKNUM(I153) -> 39 | I153: =G153+1 -> 45921 | J153: =WEEKNUM(K153) -> 30 | K153: =M153 -> 45864 | L153: =WEEKNUM(M153) -> 30 | M153: =目录!H80 -> 45864
A155: 4.19 | B155: 设计评审/验证/确认记（安全投产评审） Design review/Validation/validation (Safety commissioning review) | D155: 项目小组 | E155: 俞锋 | F155: =WEEKNUM(G155) -> 39 | G155: 2025/9/21 | H155: =WEEKNUM(I155) -> 39 | I155: =G155+1 -> 45922 | J155: =WEEKNUM(K155) -> 30 | K155: =M155 -> 45864 | L155: =WEEKNUM(M155) -> 30 | M155: =目录!H81 -> 45864
A157: 4.20 | B157: 设计更改记录 Design change record | D157: 项目小组 | E157: 俞锋 | J157: =WEEKNUM(K157) -> 0 | L157: =WEEKNUM(M157) -> 0
A159: 4.21 | B159: 产品质量策划总结和认定报告 Product quality planning summary and approval report | D159: 项目小组 | E159: 俞锋 | F159: =WEEKNUM(G159) -> 39 | G159: 2025/9/22 | H159: =WEEKNUM(I159) -> 39 | I159: =G159+1 -> 45923 | J159: =WEEKNUM(K159) -> 30 | K159: =M159 -> 45864 | L159: =WEEKNUM(M159) -> 30 | M159: =目录!H83 -> 45864
A161: 4.22 | B161: 阶段性总结和管理者支持 Periodic summary and manager support | D161: 项目小组 | E161: 俞锋 | F161: =WEEKNUM(G161) -> 39 | G161: 2025/9/23 | H161: =WEEKNUM(I161) -> 39 | I161: =G161+1 -> 45924 | J161: =WEEKNUM(K161) -> 30 | K161: =M161 -> 45864 | L161: =WEEKNUM(M161) -> 30 | M161: =目录!H84 -> 45864
A163: 5 | B163: 反馈、评定和纠正措施（持续改进） Feedback、Assessment and corrective action (CONTINUOUS improvement)
A164: 5.01 | B164: 项目移交清单（内部里程碑） Project handover list(Internal milestones） | D164: 技术部 | E164: 俞锋 | F164: =WEEKNUM(G164) -> 50 | G164: =I161+80 -> 46004 | H164: =WEEKNUM(I164) -> 51 | I164: =G164+1 -> 46005 | J164: =WEEKNUM(K164) -> 30 | K164: =M164 -> 45864 | L164: =WEEKNUM(M164) -> 30 | M164: =目录!H86 -> 45864
A166: 5.02 | B166: 设计评审/验证/确认记（量产评审） Design review/Validation/validation (Mass production review) | D166: 项目小组 | E166: 俞锋 | F166: =WEEKNUM(G166) -> 51 | G166: =I164+1 -> 46006 | H166: =WEEKNUM(I166) -> 51 | I166: =G166+1 -> 46007 | J166: =WEEKNUM(K166) -> 35 | K166: =M166 -> 45895 | L166: =WEEKNUM(M166) -> 35 | M166: =目录!H87 -> 45895
A168: 编制/日期： Compilation/Date: | N168: 批准/日期： Approval/Date:
A169: 说明：1.Description:计划时间 Plan time ; 实际时间 The actual time 。
A170: 2.关键路径的计划时间 :立项报告--->设计开发输入评审--->产品设计输入评审--->阶段评审--->材料规范--->可制造性评审--->试样--->产品设计输出评审--->阶段评审--->过程设计输入评审--->试生产控制计划--->阶段评审 --->试生产--->过程设计输出评审--->量产控制计划--->PSW--->安全投产--->安全投产评审--->阶段评审--->量产评审。
A171: 表单编号：HLD/CF-04-041-007 Form No：HLD/CF-04-041-007 | BI171: 格式版次：第一版，第2次修改 Format edition: first edition, 2 revision

Sheet 0.05
F1: 密级：秘密★★，未经允许不可查看；保存期限：长期
A2: 设计评审/验证/确认记录 Design review/validation/validation records
J3: 序号NO.： | K3: 0.05
A4: 新产品名称 The name of the new product | C4: ='0.01'!C4:E5 -> 大块金用工业长丝-帘子布事业部PH25657 Nylon 66 tire cord fabric industrial yarn-Tire cord fabric Department PH25657 | G4: 新产品规格/型号Batch number and specification of new products | H4: ='0.01'!H4:K4 -> PH25657-2800dtex/432f
A5: 顾 客 名 称 The customer name | C5: ='0.01'!H5 -> 帘子布事业部 | G5: 日期 Date | H5: =目录!G10 -> 2023年8月16日
A6: 评审项目 Review project | C6: □设计开发输入 █产品设计输入 □ 可制造性 □ 产品设计输出 □ 过程设计输入 □ 过程设计输出 □安全投产输出 □ 量产输出
A8: 评审内容及记录Review contents and records | C8: 评审项目 | G8: 评审内容 | J8: 评审结论
C9: 产品性能要求 | E9: 详见《新产品开发申请立项报告》 | G9: 是否充分？ 是否适宜？ 要求是否完整？ 要求是否清楚？ 所有要求是否没有相矛盾？ | J9: □通过 □存在问题 □通过 □存在问题 □通过 □存在问题 □通过 □存在问题 □通过 □存在问题
C10: 可利用的类似产品信息 | E10: 涤纶高模低缩产品设计经验、尼龙工业长丝同类产品设计经验 | G10: 是否充分？ 是否适宜？ 要求是否完整？ 要求是否清楚？ 所有要求是否没有相矛盾？ | J10: □通过 □存在问题 □通过 □存在问题 □通过 □存在问题 □通过 □存在问题 □通过 □存在问题
C11: 适用于产品的法律、法规要求 | E11: 符合GB/T30512、ROHS、REACH | G11: 是否充分？ 是否适宜？ 要求是否完整？ 要求是否清楚？ 所有要求是否没有相矛盾？ | J11: □通过 □存在问题 □通过 □存在问题 □通过 □存在问题 □通过 □存在问题 □通过 □存在问题
C12: 适用于产品的标准和行业规范 | E12: 产品满足行标FZ∕T 54013锦纶66工业用长丝标准要求 | G12: 是否充分？ 是否适宜？ 要求是否完整？ 要求是否清楚？ 所有要求是否没有相矛盾？ | J12: □通过 □存在问题 □通过 □存在问题 □通过 □存在问题 □通过 □存在问题 □通过 □存在问题
C13: 由产品性质所导致的潜在失效后果的管控 | E13: 线密度在标准范围内尽可能保持稳定，降低线密度变异系数 | G13: 是否充分？ 是否适宜？ 要求是否完整？ 要求是否清楚？ 所有要求是否没有相矛盾？ | J13: □通过 □存在问题 □通过 □存在问题 □通过 □存在问题 □通过 □存在问题 □通过 □存在问题
E14: 断裂强度对成品帘子布的强力影响较大，生产过程中必须保证不低于标准强度
E15: 干热收缩率对帘子布的尺寸稳定性影响较大，生产过程中必须保证干热收缩率在标准范围内
E16: 其余性能指标按照现有的生产技术能力，可以满足客户的要求
A17: 评审结果 The results of the | C17: 设计开发输入完整、清楚，满足设计和开发的目的，评审通过。
A18: 评审人员会签 The judges will countersign
A19: 编制/日期Compilation/Date | G19: 审批/日期 Approval/Date
A20: 表单编号：HLD/CF-04-041-008 Form No：HLD/CF-04-041-008 | H20: 格式版次：第一版，第 2次修改 Format edition: first edition, 2 revision
D87: 评审结果前加客户反馈情况、交付满足情况、经验借鉴情况，可点链接

Sheet 0.05修改版
F1: 密级：秘密★★，未经允许不可查看；保存期限：长期
A2: 设计评审/验证/确认记录 Design review/validation/validation records
J3: 序号NO.： | K3: 0.05
A4: 新产品名称 The name of the new product | C4: ='0.01'!C4:E5 -> 大块金用工业长丝-帘子布事业部PH25657 Nylon 66 tire cord fabric industrial yarn-Tire cord fabric Department PH25657 | G4: 新产品规格/型号Batch number and specification of new products | H4: ='0.01'!H4:K4 -> PH25657-2800dtex/432f
A5: 顾 客 名 称 The customer name | C5: ='0.01'!H5 -> 帘子布事业部 | G5: 日期 Date | H5: =目录!G10 -> 2023年8月16日
A6: 评审阶段 | C6: □设计开发输入 █产品设计输入 □ 可制造性 □ 产品设计输出 □ 过程设计输入 □ 过程设计输出 □安全投产输出 □ 量产输出
A8: 评审内容及记录Review contents and records | C8: 评审项目 | G8: 评审内容 | J8: 评审结论
C9: 产品性能要求 | E9: 详见《新产品开发申请立项报告》 | G9: 是否充分？ 是否适宜？ 要求是否完整？ 要求是否清楚？ 所有要求是否没有相矛盾？ | J9: □通过 □存在问题 □通过 □存在问题 □通过 □存在问题 □通过 □存在问题 □通过 □存在问题
C10: 评审项目改成了评审阶段，点链接查看修改版 | E10: 涤纶高模低缩产品设计经验、尼龙工业长丝同类产品设计经验 | G10: 是否充分？ 是否适宜？ 要求是否完整？ 要求是否清楚？ 所有要求是否没有相矛盾？ | J10: □通过 □存在问题 □通过 □存在问题 □通过 □存在问题 □通过 □存在问题 □通过 □存在问题
C11: 适用于产品的法律、法规要求 | E11: 符合GB/T30512、ROHS、REACH | G11: 是否充分？ 是否适宜？ 要求是否完整？ 要求是否清楚？ 所有要求是否没有相矛盾？ | J11: □通过 □存在问题 □通过 □存在问题 □通过 □存在问题 □通过 □存在问题 □通过 □存在问题
C12: 适用于产品的标准和行业规范 | E12: 产品满足行标FZ∕T 54013锦纶66工业用长丝标准要求 | G12: 是否充分？ 是否适宜？ 要求是否完整？ 要求是否清楚？ 所有要求是否没有相矛盾？ | J12: □通过 □存在问题 □通过 □存在问题 □通过 □存在问题 □通过 □存在问题 □通过 □存在问题
C13: 由产品性质所导致的潜在失效后果的管控 | E13: 线密度在标准范围内尽可能保持稳定，降低线密度变异系数 | G13: 是否充分？ 是否适宜？ 要求是否完整？ 要求是否清楚？ 所有要求是否没有相矛盾？ | J13: □通过 □存在问题 □通过 □存在问题 □通过 □存在问题 □通过 □存在问题 □通过 □存在问题
E14: 断裂强度对成品帘子布的强力影响较大，生产过程中必须保证不低于标准强度
E15: 干热收缩率对帘子布的尺寸稳定性影响较大，生产过程中必须保证干热收缩率在标准范围内
E16: 其余性能指标按照现有的生产技术能力，可以满足客户的要求
A17: 评审结果 The results of the | C17: 设计开发输入完整、清楚，满足设计和开发的目的，评审通过。
A18: 评审人员会签 The judges will countersign
A19: 编制/日期Compilation/Date | G19: 审批/日期 Approval/Date
A20: 表单编号：HLD/CF-04-041-008 Form No：HLD/CF-04-041-008 | H20: 格式版次：第一版，第 2次修改 Format edition: first edition, 2 revision
D87: 评审结果前加客户反馈情况、交付满足情况、经验借鉴情况，可点链接

Sheet 1.01
E1: 密级：秘密★★，未经允许不可查看；保存期限：长期
A2: 设计开发任务书 Design and development specification
I3: 序号NO.： | J3: 1.01
A4: 新产品名称 The name of the new product | C4: ='0.01'!C4:E5 -> 大块金用工业长丝-帘子布事业部PH25657 Nylon 66 tire cord fabric industrial yarn-Tire cord fabric Department PH25657 | F4: 新产品批号和规格Batch number and specification of new products | H4: ='0.01'!H4:K4 -> PH25657-2800dtex/432f
A5: 顾客名称 The customer name | C5: ='0.01'!H5 -> 帘子布事业部 | F5: 日期 Date | H5: =目录!G12 -> 2023年8月17日
A6: 一、依据的标准、法律法规及技术协议的主要内容：Standards, laws and regulations and main contents of the technical agreement: 1、以海利得尼龙工业长丝企业标准和尼龙工业长丝外观定等标准为基础。 2、设计要求符合IATF16949质量管理体系标准和ISO14001:2015环境管理体系标准。 3、与传统工业丝一样，没有添加任何新化学原料，符合化学品管理条例。
A7: 二、设计内容：Design content : 1、原料切片粘度的选择---神马尼龙切片，粘度IV：3.**±0.10 2、纺丝生产机型的选择----尼龙生产线
A8: 三、设计目标（包括过程能力、生产率、成本等）：Design objectives (including process capability, productivity, cost, etc.)
A9: 项目目标 project objective | C9: 指标 target | F9: 责任人 person liable | G9: 责任人 | H9: 统计时间 statistical time
A10: 1.日程安排 | C10: 2023年8月完成试样 | F10: APQP团队 | G10: APQP团队 | H10: 第二阶段结束
A11: 2.过程能力 | C11: CC/SC项PPK≥1.67或CPK≥1.67 （当数据符合正态分布且稳定时看CPK，当数据不符合正态分布或不稳定时看PPK） | F11: APQP团队 | G11: APQP团队 | H11: 第二阶段、第四阶段结束
A12: 3.开发成本 | C12: 成本控制与其他尼龙66工业长丝产品类似 | F12: APQP团队 | G12: APQP团队 | H12: 第四阶段结束
A13: 4.生产率 | C13: ≥0.9吨/天/位 | F13: APQP团队 | G13: APQP团队 | H13: 第四阶段结束
A14: 5.产品符合性（CC/SC项，其余一般特性见《立项报告》）： | C14: ='0.02'!B11 -> 线密度 Linear Density | D14: ='0.02'!G11 -> 2880±30 | E14: ='0.02'!E11:F11 -> dtex | F14: APQP团队 | G14: APQP团队 | H14: 第二阶段、第四阶段结束
C15: ='0.02'!B13 -> 断裂强力 Breaking Strength | D15: ='0.02'!G13 -> ≥245.0 | E15: ='0.02'!E13:F13 -> N | F15: APQP团队 | G15: APQP团队 | H15: 第二阶段、第四阶段结束
C16: ='0.02'!B16 -> 断裂伸长率 Breaking Elongation Ratio | D16: ='0.02'!G16 -> 20.0±3.0 | E16: ='0.02'!E16:F16 -> % | F16: APQP团队 | G16: APQP团队 | H16: 第二阶段、第四阶段结束
C17: ='0.02'!B19 -> 干热收缩率（177℃×2min×0.05cN/dtex) Shrinkage in Hot Air | D17: ='0.02'!G19 -> 6.2±1.5 | E17: ='0.02'!E19 -> % | F17: APQP团队 | G17: APQP团队 | H17: 第二阶段、第四阶段结束
A18: 6.可靠性及质量目标 | C18: 优等率≥90% | F18: APQP团队 | G18: APQP团队 | H18: 第四阶段结束
A19: 7.APQP指标 | C19: 见项目计划 | F19: APQP团队 | G19: APQP团队 | H19: 每个阶段结束时
A20: 顾客的特殊要求： □有 □无
A21: 详细要求：客户其他要求均能满足要求，详见客户要求清单。
A22: 项目团队会签 Team members will countersign
A23: 编制/日期 Compilation/Date | F23: 审批/日期Approval/Date
A24: 表单编号：HLD/CF-04-041-009 Form No : HLD/CF-04-041-009 | G24: 格式版次：第一版，第2次修改 Format edition: first edition, 2 revision

Sheet 1.02
D1: 密级：秘密★★，未经允许不可查看；保存期限：长期
A2: 初始材料清单（BOM） Initial material list (BOM)
H3: 序号NO.： | I3: 1.02
A4: 新产品名称 The name of the new product | C4: ='0.01'!C4:E5 -> 大块金用工业长丝-帘子布事业部PH25657 Nylon 66 tire cord fabric industrial yarn-Tire cord fabric Department PH25657 | F4: 顾客名称 The customer name | G4: ='0.01'!H5 -> 帘子布事业部
A5: 新产品规格/型号 Batch number and specification of new products | C5: ='0.01'!H4 -> PH25657-2800dtex/432f | F5: 制定日期 Set the date | G5: =目录!G13 -> 2023年8月18日
A6: 制定部门 Develop department | C6: 技术部 | F6: 修订日期 The revision date | G6: =目录!G70 -> 2025年5月6日
A7: 序号STT | B7: 材料名称 The name of the material | D7: 规格/型号Specification/Model | E7: 供应商名称 Supplier name | F7: 是否已准入 Whether it has been approved | G7: 准入计划 Admission Plan | I7: 实际完成时间 actual finish time
A8: 1 | B8: 尼龙66切片 | D8: FYR32KD | E8: 021156 | F8: √ | G8: / | H8: / | I8: /
A9: 2 | B9: 纺丝油剂 | D9: SLT-B-100E | E9: 02821 | F9: √
A10: 3 | B10: 纸管 | D10: 94*106*300mm | E10: 恒旺 | F10: √ | G10: / | H10: / | I10: /
A11: 4 | B11: 木托盘 | D11: 110*110CM（墩子） | E11: 宏旺 | F11: √
A12: 5 | B12: 塑料袋 | D12: 54*72mm黑色 | E12: 正欣 | F12: √ | G12: / | H12: / | I12: /
A13: 6 | B13: 护角 | D13: 8cm | E13: 好运 | F13: √
A14: 7 | B14: 缠绕膜 | D14: 500*0.025 | E14: 鸿鹰 | F14: √ | G14: / | H14: / | I14: /
A15: 8 | B15: PP打包带 | D15: 12*0.9,10kg | E15: 天恩 | F15: √
A16: 9 | B16: 蜂窝板 | D16: 1120*1120*50mm 1120*1120*25mm | E16: 永基 | F16: √ | G16: / | H16: / | I16: /
A17: 10 | B17: 纸箱 | D17: 3A/112*112圆角下盖 | E17: 先锋 | F17: √
A18: 备 注
A19: 编制/日期Compilation/Date | F19: 审批/日期Approval/Date
A21: 表单编号：HLD/CF-04-041-011 Form No : HLD/CF-04-041-011 | F21: 格式版次：第一版，第1次修改 Format edition: first edition, 1 revision

Sheet 1.03
E1: 密级：秘密★★，未经允许不可查看；保存期限：长期
A2: 成本核算及报价表 Cost accounting and quotation sheet
M3: 序号NO.： | N3: 1.03
A4: 新产品名称 The name of the new product | D4: ='0.01'!C4 -> 大块金用工业长丝-帘子布事业部PH25657 Nylon 66 tire cord fabric industrial yarn-Tire cord fabric Department PH25657 | H4: 新产品规格/型号 Batch number and specification of new products | L4: ='0.01'!H4 -> PH25657-2800dtex/432f
A5: 顾 客 名 称 The customer name | D5: ='0.01'!H5 -> 帘子布事业部 | H5: 日期 Date | L5: =目录!G14 -> 2023年8月18日
A6: 资金来源 Source of funds | E6: 拨 款 grant | G6: 贷 款 The loans | I6: 自 筹 Since the raise | L6: 其 它 other | M6: 合 计 total
A7: 经费（万元）
A8: 经费明细表 A breakdown of expenses 单位： 元
A9: 序号STT | B9: 项 目 分 类 Project classification | H9: 核算费用Cost accounting | J9: （工作量） | L9: （核算标准） | N9: 小 计subtotal
A10: 1 | B10: 直 接direct | C10: 聚酯切片 | H10: 7500 | N10: =SUM(H10:I12) -> 8650
B11: 材料费material fee | C11: 油剂 | H11: 600
C12: 包装材料 | H12: 550
A13: 2 | B13: 化验分析费Laboratory analysis fee | C13: 切片IV测试 | H13: 150 | N13: =SUM(H13:I17) -> 350
C14: 含油丝IV测试 | H14: 150
C15: 含油率测试 | H15: 50
A18: 3 | B18: 燃料动力消耗费 Fuel power consumption fee | H18: 800 | N18: =SUM(H18) -> 800
A19: 4 | B19: 设备购置费（设备名称及型号）Equipment purchase fee (equipment name and model) | H19: 0 | N19: 0
A20: 5 | B20: 小型样机试制费（样机名称）Small prototype trial production fee (name of prototype) | H20: 0 | N20: 0
A21: 6 | B21: 现场试验费 Field test fee | H21: 0 | N21: 0
A22: 7 | B22: 其 他Other | C22: 外协费 Outsourcing fee | H22: 0 | N22: =SUM(H22:I26,H27) -> 3500
C23: 调研费 Research fee | H23: 0
C24: 培训费 training fee | H24: 0
C25: 会议评审费 Conference review fee | H25: 0
C26: 运输费 Shipping fee | H26: 3500
A27: 8 | B27: 不可预见费 Unforeseen expenses | H27: 0
A28: 9 | B28: 设备、房屋Equipment, housing | D28: （设备名称）Device name | H28: 0 | N28: 0
B29: 占用费Occupancy fee | D29: （房屋用途）Housing purposes | H29: 0
A30: 10 | B30: 直接人员费用（按全工时人数）Direct staff costs (based on the number of people working in full hours) | H30: 600
A31: 总 计 Total | H31: 1*900元/吨
A32: 编制/日期 Compilation/Date | H32: 审批/日期Approval/Date
A33: 表单编号：HLD/CF-04-041-004 Form No：HLD/CF-04-041-004 | K33: 格式版次：第一版，第1次修改 Format edition: first edition, 1 revision

Sheet 1.03修改版
E1: 密级：秘密★★，未经允许不可查看；保存期限：长期
A2: 成本核算及报价表 Cost accounting and quotation sheet
M3: 序号NO.： | N3: 1.03
A4: 新产品名称 The name of the new product | D4: ='0.01'!C4 -> 大块金用工业长丝-帘子布事业部PH25657 Nylon 66 tire cord fabric industrial yarn-Tire cord fabric Department PH25657 | H4: 新产品规格/型号 Batch number and specification of new products | L4: ='0.01'!H4 -> PH25657-2800dtex/432f
A5: 顾 客 名 称 The customer name | D5: ='0.01'!H5 -> 帘子布事业部 | H5: 日期 Date | L5: =目录!G14 -> 2023年8月18日
A6: 资金来源 Source of funds | E6: 拨 款 grant | G6: 贷 款 The loans | I6: 自 筹 Since the raise | L6: 其 它 other | M6: 合 计 total
A7: 经费（万元）
A8: 经费明细表 A breakdown of expenses 单位： 元
A9: 序号STT | B9: 项 目 分 类 Project classification | H9: 核算费用Cost accounting | J9: （工作量） | L9: （核算标准） | N9: 小 计subtotal
A10: 1 | B10: 直 接direct | C10: 聚酯切片 | H10: 7500 | N10: =SUM(H10:I12) -> 8650
B11: 材料费material fee | C11: 油剂 | H11: 600
C12: 包装材料 | H12: 550
A13: 2 | B13: 化验分析费Laboratory analysis fee | C13: 切片IV测试 | H13: 150 | N13: =SUM(H13:I17) -> 350
C14: 含油丝IV测试 | H14: 150
C15: 含油率测试 | H15: 50
A18: 3 | B18: 燃料动力消耗费 Fuel power consumption fee | H18: 800 | N18: =SUM(H18) -> 800
B19: 能耗费用（水电） | O19: 发给体系老师看下
A20: 4 | B20: 设备购置费（设备名称及型号）Equipment purchase fee (equipment name and model) | H20: 0 | N20: 0
A21: 5 | B21: 小型样机试制费（样机名称）Small prototype trial production fee (name of prototype) | H21: 0 | N21: 0
A22: 6 | B22: 现场试验费 Field test fee | H22: 0 | N22: 0
A23: 7 | B23: 其 他Other | C23: 外协费 Outsourcing fee | H23: 0 | N23: =SUM(H23:I27,H28) -> 3500
C24: 调研费 Research fee | H24: 0
C25: 培训费 training fee | H25: 0
C26: 会议评审费 Conference review fee | H26: 0
C27: 运输费 Shipping fee | H27: 3500
A28: 8 | B28: 不可预见费 Unforeseen expenses | H28: 0
A29: 9 | B29: 设备、房屋Equipment, housing | D29: （设备名称）Device name | H29: 0 | N29: 0
B30: 占用费Occupancy fee | D30: （房屋用途）Housing purposes | H30: 0
A31: 10 | B31: 直接人员费用（按全工时人数）Direct staff costs (based on the number of people working in full hours) | H31: 600
A32: 总 计 Total | H32: 1*900元/吨
A33: 编制/日期 Compilation/Date | H33: 审批/日期Approval/Date
A34: 表单编号：HLD/CF-04-041-004 Form No：HLD/CF-04-041-004 | K34: 格式版次：第一版，第1次修改 Format edition: first edition, 1 revision

Sheet 1.04
E1: 密级：秘密★★，未经允许不可查看；保存期限：长期
A2: 过程流程图（初始） Process flow Chart (initial)
M3: 序号NO.：1.04
A4: 新产品名称 The name of the new product | C4: ='0.01'!C4:E5 -> 大块金用工业长丝-帘子布事业部PH25657 Nylon 66 tire cord fabric industrial yarn-Tire cord fabric Department PH25657 | H4: 新产品批号和规格 Batch number and specification of new products | I4: ='0.01'!H4 -> PH25657-2800dtex/432f | J4: 顾 客 名 称 The customer name | L4: ='0.01'!H5 -> 帘子布事业部
A6: 编制 Preparde by | C6: 于淼 Yu Miao | H6: 批准 Appoved by | I6: 顾锋 Gu Feng | J6: 日期(初稿) Date(First Draft) | L6: =目录!G15 -> 2023年8月19日
A7: 生产线 production line | C7: F、H | G7: 产品类别：尼龙66工业长丝 Part Category：Nylon 66 industrial yarn
A8: 工位名称 Process Name | B8: 步骤 Step | C8: 制造 manufacture | D8: 移动 Moving | E8: 放置 Placing | F8: 检查 Checking | G8: 操作说明 Illumination of Operation | J8: 产品特殊特性 Key Product Characteristics | L8: 过程特殊特性 Key Control Characteristics
J9: 项目Projects | K9: 级别Levels | L9: 项目Projects | M9: 级别levels
A10: 投料 Feeding | B10: PA661100 | G10: 将从仓库领取的尼龙66切片投料至大料仓 Feed the nylon 66 chips collected from the warehouse into the large silo
A11: 切片输送 PET chip transport | B11: PA661200 | G11: 使用氮气将尼龙66切片从大料仓输送至纺丝料仓 The nylon 66 chips are conveyed from the buffer silo to the spinning silo using nitrogen
A12: 切片存储 Storage of Nylon 66 chips | B12: PA661300 | G12: 尼龙66切片在纺丝料仓中存储 Nylon 66 chips are stored in the chip spinning silo
A13: 螺杆熔融 Melton by screw | B13: PA661400 | G13: 纺丝料斗中的高粘度切片，在重力作用下进入螺杆熔融挤出 The viscosified chips will be fed into the scew for melting.
A14: 熔体计量 Melt metering | B14: PA661500 | G14: 螺杆挤出后的熔体经过熔体分配管通过计量泵精确计量 The melt of polymer extruded by srew, then be measured and transported by the metering pump | J14: 线密度 Linear density | K14: SC | L14: 计量泵转速 Rotating speed of Metering pump | M14: SC
A15: 喷丝 spinning | B15: PA661600 | G15: 计量后的熔体通过组件喷出丝束 The measured melt will be extruded into the spinining pack and form into the fresh born yarn.
A16: 冷却成型 cooling and molding | B16: PA661700 | G16: 熔体丝束通过加热罩、缓冷装置和冷却风，固化成初生丝束 The yarn go through the heating hood and quenching air to modify the initial properties of new born yarn. | J16: 断裂伸长 Breaking elongation ratio | K16: CC | L16: 加热罩温度 Heating hood temperature 侧吹风温度 Lateral air temperature | M16: CC
A17: 上油 Adding oil | B17: PA661800 | G17: 通过上油轮将纺丝油剂吸附至丝束表面上 Apply the spin finish onto the surface of yarn by kiss roller.
A18: 拉伸定型 stretching and sizing | B18: PA661900 | G18: 上油后的丝束经罗拉多级拉伸和热定型，以达到设计物性性能 The oiled yarn will be stretched and sized by serveral pairs of roller, to make the yarn get the certain physical properties. | J18: 断裂强力 Breaking strength | K18: CC | L18: 罗拉速度 Speed of roller | M18: CC
J19: 干热收缩率 Shrinkage in Hot Air | K19: SC | L19: 罗拉温度 Temperature of roller | M19: SC
A20: 上网络 Adding intermingle | B20: PA662000 | G20: 拉伸和定型后的丝束，经网络器和压空的作用获得网络节点 The streched and sized yarn will be insert into the air-jet device for making the entanglement.
A21: 毛丝检测 Detection of the broken filament | B21: PA662100 | G21: 丝束经过毛丝检测仪在线记录毛丝个数 Use the online broken filament detector to examine the quantity of broken filament of the bobbin.
A22: 卷绕 Winding | B22: PA662200 | G22: 用规定颜色的纸管将丝束通过卷绕机卷绕成一定卷重的丝筒 The winder will take up yarn onto the paper core which has specific color requirement.
A23: 落丝 Doffing | B23: PA662300 | G23: 把卷绕完成的丝筒根据不同毛丝等级按规定摆放到相应丝车上，并贴好小标签Separate the finished bobbins according to the criterion of broken filament, label the bobbin according accordingly, then load the bobbins onto the different trolley respectively.
A24: 剥丝 Stripping | B24: PA662400 | G24: 抽吸丝饼表层丝，剥丝完成后打结 Peel off the surface yarn which may has quality risk, and tie a knot.
A25: 检验 Inspection | B25: PA662500 | G25: 对丝筒物性抽检，外观全检，并根据检验结果定等 Make the physical properties inspection and apperance inspection for the finished bobbins, then grading these finished bobbins according to the specific quality criterion. | J25: 线密度 Linear density | K25: SC
J26: 断裂伸长 Breaking elongation ratio | K26: CC
J27: 断裂强力 Breaking strength | K27: CC
J28: 干热收缩率 Shrinkage in Hot Air | K28: SC
A29: 包装 Packing | B29: PA662600 | G29: 根据生产通知单和包装标准进行丝饼二维码扫描、丝饼装箱打包并称重Scan QR code of bobbin and pack up the bobbin according to the packing standard and produciton order, then weight them.
A30: 入库 Warehousing | B30: PA662700 | G30: 将包装好的产品用叉车运送至仓库指定区域 Transport the packaged goods to the designated area of the warehouse.
A31: 交付 Deliver | B31: PA662800 | G31: 根据销售订单对已入库产品进行装车交付 According to the sales order, load and deliver the warehousing products
A32: 注：CC代表关键特性，SC代表重要特性。 Noted:CC represent critcal characters,SC represent significant characters.

Sheet 1.05
E1: 密级：秘密★★，未经允许不可查看；保存期限：长期
A2: 特殊特性符号转化表 Special properties symbol conversion table
F3: 序号NO.：1.05
A4: 新产品名称 The name of the new product | C4: ='0.01'!C4 -> 大块金用工业长丝-帘子布事业部PH25657 Nylon 66 tire cord fabric industrial yarn-Tire cord fabric Department PH25657 | F4: 日期 Date | H4: =目录!G16 -> 2023年8月20日
B5: 顾客名称The customer name | C5: ='0.01'!H5 -> 帘子布事业部 | F5: HALEAD （内部）
A6: 特殊特性Special features | F6: 定义 | H6: 符号
A7: 安全/法规Safety/Regulations | C7: —— | F7: S≥9 | H7: CC
A8: 关键特性 The key features | C8: ★ | F8: S≥9 | H8: CC
A9: 重要特性 Important features | C9: ◇ | F9: 5≤S≤8且O≥5 | H9: SC
A10: 一般特性 General features | C10: —— | F10: —— | H10: ——
A12: 备注：根据顾客要求、类似经验等，确定产品的特殊特性，包括关键特性、重要特性、一般特性。
A13: 编制/日期Compilation/Date | E13: 审批/日期 Approval/Date
A14: 表单编号：HLD/CF-04-041-025 Form No. : HLD/CF-04-041-025 | F14: 格式版次：第一版，第2次修改 Format edition: first edition, 2 revision

Sheet 1.06
E1: 密级：秘密★★，未经允许不可查看；保存期限：长期
A2: 产品/过程特殊特性清单 List of product/process special features
F4: 序号NO.：1.06
A5: 新产品名称 The name of the new product | C5: ='0.01'!C4 -> 大块金用工业长丝-帘子布事业部PH25657 Nylon 66 tire cord fabric industrial yarn-Tire cord fabric Department PH25657 | E5: 新产品规格/型号 Batch number and specification of new products | G5: ='0.01'!H4 -> PH25657-2800dtex/432f
A6: 顾 客 名 称 The customer name | C6: ='0.01'!H5 -> 帘子布事业部 | E6: 日期 Date | G6: =目录!G17 -> 2023年8月20日
A7: 序号 STT | B7: 产品特性 Key Produc Characteristic | D7: 过程特性 Key Control Characteristic | F7: 控制手段 Control method | G7: 责任部门 The responsibility department | H7: 备注
B8: 描述Describe | C8: 符号Symbol | D8: 描述Describe | E8: 符号Symbol
A9: 1 | B9: 线密度 Linear density | C9: SC | F9: SPC管控图 | G9: 化纤事业部
A10: 2 | B10: 断裂强力 Tenacity at break | C10: CC | F10: SPC管控图 | G10: 化纤事业部
A11: 3 | B11: 断裂伸长 Elongation at break | C11: CC | F11: SPC管控图 | G11: 化纤事业部
A12: 4 | B12: 干热收缩率 Shinkage in hot air | C12: SC | F12: SPC管控图 | G12: 化纤事业部
A13: 5 | D13: 计量泵转速 speed of metering pump | E13: SC | F13: 100%实时监控 | G13: 化纤事业部
A14: 6 | D14: 加热罩温度 Heating hood temperature | E14: CC | F14: 100%实时监控 | G14: 化纤事业部
A15: 7 | D15: 侧吹风温度 Quenching air temperature | E15: CC | F15: 100%实时监控 | G15: 化纤事业部
A16: 8 | D16: 罗拉温度 temperature of roller | E16: SC | F16: 100%实时监控 | G16: 化纤事业部
A17: 9 | D17: 罗拉速度 speed of roller | E17: CC | F17: 100%实时监控 | G17: 化纤事业部
A18: 备注：CC表示关键特性,SC表示重要特性。
A19: 编制/日期Compilation/Date | E19: 审批/日期Approval/Date
A20: 表单编号：HLD/CF-04-041-012 Form No ：HLD/CF-04-041-012 | F20: 格式版次：第一版，第1次修改 Format edition: first edition, 1 revision

Sheet 1.07
E1: 密级：秘密★★，未经允许不可查看；保存期限：长期
A2: 产品安全识别表 Product safety identification form
A3: 序号NO.：1.07
A4: 新产品名称 The name of the new product | C4: ='0.01'!C4 -> 大块金用工业长丝-帘子布事业部PH25657 Nylon 66 tire cord fabric industrial yarn-Tire cord fabric Department PH25657 | F4: 新产品批号和规格Batch number and specification of new products | H4: ='0.01'!H4 -> PH25657-2800dtex/432f
A5: 顾 客 名 称 The customer name | C5: ='0.01'!H5 -> 帘子布事业部 | F5: 日期 Date | H5: =目录!G18 -> 2023年8月21日
A6: 项目 project | C6: 产品安全要求 Product safety requirements | F6: 风险评估 risk assessment | G6: 责任人 | H6: 控制方法 control method
A7: 1 | B7: 产品安全方面的相关法规 | C7: 该产品不涉及安全方面的法规 | F7: NA | H7: NA
A8: 2 | B8: 安全相关特殊特性 | C8: ='1.01'!C15 -> 断裂强力 Breaking Strength | D8: ='1.01'!D15 -> ≥245.0 | E8: ='1.01'!E15 -> N | F8: 在DFMEA及PFMEA中分析 | H8: 1、在控制计划中规定控制方法及反应计划 2、在FMEA、控制计划、作业指导书等文件中标识符合
A9: 3 | B9: 安全相关特殊特性 | C9: ='1.01'!C16 -> 断裂伸长率 Breaking Elongation Ratio | D9: ='1.01'!D16 -> 20.0±3.0 | E9: ='1.01'!E16 -> % | F9: 在DFMEA及PFMEA中分析 | H9: 1、在控制计划中规定控制方法及反应计划 2、在FMEA、控制计划、作业指导书等文件中标识符合
A10: 4
A11: 5
A12: 6
A13: 7
A14: 编制/日期 Compilation/Date | F14: 审批/日期 Approval/Date
A15: 表单编号：HLD/CF-04-041-047 Form No：HLD/CF-04-041-047 | H15: 格式版次：第一版，第0次修改 Format edition: first edition, 0 revision

Sheet 1.07修改版
E1: 密级：秘密★★，未经允许不可查看；保存期限：长期
A2: 产品安全识别表 Product safety identification form
A3: 序号NO.：1.07
A4: 新产品名称 The name of the new product | C4: ='0.01'!C4 -> 大块金用工业长丝-帘子布事业部PH25657 Nylon 66 tire cord fabric industrial yarn-Tire cord fabric Department PH25657 | F4: 新产品批号和规格Batch number and specification of new products | H4: ='0.01'!H4 -> PH25657-2800dtex/432f
A5: 顾 客 名 称 The customer name | C5: ='0.01'!H5 -> 帘子布事业部 | F5: 日期 Date | H5: =目录!G18 -> 2023年8月21日
A6: 项目 project | C6: 产品安全要求 Product safety requirements | F6: 风险评估 risk assessment | G6: 责任人 | H6: 控制方法 control method
A7: 1 | B7: 产品安全方面的相关法规 | C7: 该产品不涉及安全方面的法规 | F7: NA | H7: NA
A8: 2 | B8: 安全相关特殊特性 | C8: ='1.01'!C15 -> 断裂强力 Breaking Strength | D8: ='1.01'!D15 -> ≥245.0 | E8: ='1.01'!E15 -> N | F8: 在DFMEA及PFMEA中分析 | H8: 1、在控制计划中规定控制方法及反应计划 2、在FMEA、控制计划、作业指导书等文件中标识符合
A9: 3 | B9: 安全相关特殊特性 | C9: ='1.01'!C16 -> 断裂伸长率 Breaking Elongation Ratio | D9: ='1.01'!D16 -> 20.0±3.0 | E9: ='1.01'!E16 -> % | F9: 在DFMEA及PFMEA中分析 | H9: 1、在控制计划中规定控制方法及反应计划 2、在FMEA、控制计划、作业指导书等文件中标识符合
A10: 4 | B10: 有害物质 | C10: 满足要求
A11: 5
A12: 6
A13: 7
A14: 编制/日期 Compilation/Date | F14: 审批/日期 Approval/Date
A15: 表单编号：HLD/CF-04-041-047 Form No：HLD/CF-04-041-047 | H15: 格式版次：第一版，第0次修改 Format edition: first edition, 0 revision

Sheet 1.08
E1: 密级：秘密★★，未经允许不可查看；保存期限：长期
A2: 产品保证计划 Product Assurance Program
A3: 序号NO.：1.08
A4: 新产品名称 The name of the new product | C4: ='0.01'!C4 -> 大块金用工业长丝-帘子布事业部PH25657 Nylon 66 tire cord fabric industrial yarn-Tire cord fabric Department PH25657 | F4: 新产品批号和规格Batch number and specification of new products | H4: ='0.01'!H4 -> PH25657-2800dtex/432f
F5: 顾 客 名 称 The customer name | H5: ='0.01'!H5 -> 帘子布事业部
A6: 制定部门 Designated department | C6: 技术部 | F6: 制定日期 Fixed date | H6: =目录!G19 -> 2023年8月21日
A7: 一、项目要求概述（简要的说明新产品项目开发的各项要求 Brief description of the requirements of the new product project development
A8: 顾客对新产品开发项目的质量和技术要求及其它基本要求： Customer's quality and technical requirements and other basic requirements for new product development projects:
A9: 顾客对新产品开发项目的质量和技术要求及其它基本要求：规格为2800dtex/432f ，断裂强度≥8.50cN/dtex.
A10: 二、产品可靠性，耐久性和分配目标的要求Requirements for product reliability, durability and distribution targets
A11: 见产品规范
A13: 三、风险分析/评估：Risk Analysis/Assessment:
A14: 序号 STT | B14: 项 目 Item | C14: 可能带来的风险 Possible risks | F14: 解 决 方 法 Solution | J14: 备 注 Remarks
A15: 1 | B15: 新技术 | C15: 无 | F15: 无
A16: 2 | B16: 毛丝 | C16: 毛丝多会造成布外观毛 | F16: 总结以往类似尼龙工业长丝毛丝控制的经验
A17: 3 | B17: 包 装 | C17: 打包不规范.包装不牢固，运输过程中造成破损 | F17: 员工培训
A18: 4 | B18: 服 务 | C18: 产品投诉 | F18: 及时接受和持续做分析.纠正预防
A19: 5 | B19: 制 造 | C19: 生产过程出现工作失误 | F19: 作业指导书和生产控制计划
A20: 6 | B20: 其 它 | C20: 无 | F20: 无
A21: 四、初始工程标准：Initial engineering standards:
A22: A、原材料（进货检验和试验）部分：A. Raw materials (incoming inspection and testing):
A23: 序号 STT | B23: 原材料名称 Raw material name | D23: 初 始 质 量 要 求 Initial quality requirements | G23: 控 制 方 法 Control Method | J23: 备 注 Remarks
A24: 1 | B24: 尼龙66切片 | D24: 见《化纤部原辅材料质量标准》 | G24: 进货检验
A25: 2 | B25: 纺丝油剂 | D25: 见《化纤部原辅材料质量标准》 | G25: 进货检验
A26: B、过程（工序检验和试验）部分：B. Process (process inspection and test) part:
A27: 序号 STT | B27: 工序检验项目 Process inspection items | D27: 初 始 质 量 要 求 Initial quality requirements | G27: 控 制 方 法 Control Method | J27: 备 注 Remarks
A28: 1 | B28: 切片粘度IV | D28: 3.**±0.10 | G28: SPC
A29: C、成品（最终检验和试验）部分：C. Finished product (final inspection and test):
A30: 序号 STT | B30: 成品检验项目Finished product inspection items | F30: 初 始 质 量 要 求 Initial quality requirements | H30: 控 制 方 法 Control Method | J30: 备 注 Remarks
A31: 1 | B31: 线密度Linear Density | F31: ='0.02'!G11 -> 2880±30 | G31: ='0.02'!E11 -> dtex | H31: SPC | J31: ='0.02'!I11 -> GB/T14343
A32: 2 | B32: 线密度变异系数CV of Linear Density | F32: ='0.02'!G12 -> ≤1.60 | G32: ='0.02'!E12 -> % | H32: / | J32: ='0.02'!I12 -> GB/T14343
A33: 3 | B33: 断裂强力Breaking Strength | F33: ='0.02'!G13 -> ≥245.0 | G33: ='0.02'!E13 -> N | H33: SPC | J33: ='0.02'!I13 -> GB/T14344
A34: 4 | B34: 断裂强度Tenacity | F34: ='0.02'!G14 -> ≥8.50 | G34: ='0.02'!E14 -> cN/dtex | H34: SPC | J34: ='0.02'!I14 -> GB/T14344
A35: 5 | B35: 强度变异系数CVCV of Tenacity | F35: ='0.02'!G15 -> ≤3.00 | G35: ='0.02'!E15 -> % | H35: / | J35: ='0.02'!I15 -> GB/T14344
A36: 6 | B36: 断裂伸长率Breaking Elongation Ratio | F36: ='0.02'!G16 -> 20.0±3.0 | G36: ='0.02'!E16 -> % | H36: SPC | J36: ='0.02'!I16 -> GB/T14344
A37: 7 | B37: 伸长变异系数CVCV of Elongation | F37: ='0.02'!G17 -> ≤5.00 | G37: ='0.02'!E17 -> % | H37: / | J37: ='0.02'!I17 -> GB/T14344
A38: 8 | B38: 中间伸长4.7cN/dtex E.@4.7CN/dtex Load | F38: ='0.02'!G18 -> 11.0±1.5 | G38: ='0.02'!E18 -> % | H38: SPC | J38: ='0.02'!I18 -> GB/T14344
A39: 9 | B39: 干热收缩率（177℃×2min×0.05cN/dtex) Shrinkage in Hot Air | F39: ='0.02'!G19 -> 6.2±1.5 | G39: ='0.02'!E19 -> % | H39: SPC | J39: ='0.02'!I19 -> HLD method
A40: 10 | B40: 网络度（钩针法）Intermingles（Needle） | F40: ='0.02'!G20 -> 6.0±3.0 | G40: ='0.02'!E20 -> nodes/m | H40: SPC | J40: ='0.02'!I20 -> HLD method
A41: 11 | B41: 含油率Spin Finish Oil | F41: ='0.02'!G21 -> 0.90±0.30 | G41: ='0.02'!E21 -> % | H41: SPC | J41: ='0.02'!I21 -> GB/T6504-NMR
A42: 12 | B42: 强力保持率（180℃×4h）Strength retention rate | F42: ='0.02'!G22 -> ≥90 | G42: ='0.02'!E22 -> % | H42: SPC | J42: ='0.02'!I22 -> HLD method
A43: D、包装要求： D. Packaging requirements:
A44: 序号 STT | B44: 包装检验Packaging inspection items | D44: 初 始 质 量 要 求 Initial quality requirements | G44: 控 制 方 法 Control Method | J44: 备 注 Remarks
A45: 1 | B45: 装箱 | D45: 不混装丝饼 | G45: 作业指导书
A46: 2 | B46: 包装 | D46: 外箱规整，标签张贴正确 | G46: 作业指导书
A47: 3 | B47: 运送 | D47: 不损坏包装及产品 | G47: 作业指导书
A48: E、其它标准要求：E. Other standard requirements:
A49: 无
A50: 备 注Remarks
A51: 编制/日期Compilation/Date | F51: 审批/日期Approval/Date
A53: 表单编号：HLD/CF-04-041-010 Form No ：HLD/CF-04-041-010 | H53: 格式版次：第一版，第1次修改 Format edition: first edition, 1 revision

Sheet 1.09
E1: 密级：秘密★★，未经允许不可查看；保存期限：长期
A3: 项目变更登记汇总表 Summary of project change registration
A4: 序号NO.：1.09
A5: 新产品名称 The name of the new product | E5: ='0.01'!C4 -> 大块金用工业长丝-帘子布事业部PH25657 Nylon 66 tire cord fabric industrial yarn-Tire cord fabric Department PH25657 | I5: 新产品批号和规格 Batch number and specification of new products | N5: ='0.01'!H4 -> PH25657-2800dtex/432f
A6: 顾 客 名 称 The customer name | E6: ='0.01'!H5 -> 帘子布事业部 | I6: 日期 Date | N6: =目录!G20 -> 2023年8月21日
A7: 序号 | C7: 日期 | D7: 产品 | E7: 变更原因 | F7: 变更内容 | G7: 项目小组评审 | I7: 责任人 | J7: 顾客沟通 | K7: 责任人 | L7: 供方沟通 | M7: 责任人 | N7: 对应措施 | O7: 责任人 | P7: 要求切换/实施日期 | Q7: 变更前产品处理意见 | R7: 变更关闭情况
G8: 风险及影响 | H8: 结果
A12: 表单编号：HLD/CF-04-041-048 Form No：HLD/CF-04-041-048 | N12: 格式版次：第一版，第0次修改 Format edition: first edition, 0 revision
B21: 风险评估和缓解计划

Sheet 1.10
E1: 密级：秘密★★，未经允许不可查看；保存期限：长期
A2: 风险评估和缓解计划 Risk assessment and mitigation planning
A3: 序号NO.：1.10
A4: 新产品名称 The name of the new product | C4: ='0.01'!C4 -> 大块金用工业长丝-帘子布事业部PH25657 Nylon 66 tire cord fabric industrial yarn-Tire cord fabric Department PH25657 | F4: 新产品批号和规格 Batch number and specification of new products | H4: ='0.01'!H4 -> PH25657-2800dtex/432f
A5: 顾 客 名 称 The customer name | C5: ='0.01'!H5 -> 帘子布事业部 | F5: 日期 Date | H5: =目录!G21 -> 2023年8月21日
A6: No. | B6: 可能的风险 | C6: 可能的机遇 | D6: 风险或机遇评价 | G6: 应对风险的措施 | I6: 有效性评价
D7: S | E7: O | F7: 初始R | I7: S | J7: O | K7: 剩余风险R
A8: 1 | B8: 项目要求识别不全，顾客要求能不满足 | D8: 4 | E8: 3 | F8: U | G8: 建立《顾客要求的确定与评审控制程序》明确规定合同要求的识别并评审，通过合同评审识别顾客要求是否能满足，以降低合同要求识别有遗漏的风险 | I8: 3 | J8: 2 | K8: R
A9: 2 | B9: 产品风险没有识别，接订单后没有可制造性，无法生产或风险太高 | D9: 3 | E9: 3 | F9: R
A10: 3 | B10: 项目市场需求增加或变化，订单突然增加或取消 | D10: 3 | E10: 3 | F10: R
A11: 4 | B11: 没有经过项目要求评审就签合同，订单要求可能无法满足 | D11: 4 | E11: 3 | F11: U | G11: 建立《顾客要求的确定与评审控制程序》明确规定签订合同前必须通过合同评审方可签订。 | I11: 3 | J11: 2 | K11: R
A12: 5 | B12: 图纸评审不认真，产品设计开发中图纸设计错误 | D12: 3 | E12: 2 | F12: R | K12: =IF(I12="","",I12*J12*#REF!)
A13: 6 | B13: 对设计开发进度监控不足，设计开发进度延迟 | D13: 1 | E13: 2 | F13: A | K13: =IF(I13="","",I13*J13*#REF!)
A14: 7 | C14: 项目经验丰富，项目团队技能优秀 | D14: 1 | E14: 2 | F14: A
A15: 8 | B15: 过程开发错误，产品无法满足使用要求 | D15: 3 | E15: 4 | F15: U | G15: 编制PFMEA，运作DFMEA工具对过程风险进行分析，并针对高风险的项目采取措施，生产中落实该措施，以降低风险 | I15: 3 | J15: 2 | K15: R
A16: 9 | B16: 项目生产中不合格，增加返工成本、报废 | D16: 3 | E16: 4 | F16: U | G16: 编制PFMEA，运作PFMEA工具对过程风险进行分析，并针对高风险的项目采取措施，生产中落实该措施，以降低风险 | I16: 3 | J16: 2 | K16: R
A17: 10 | B17: 员工有感染流行病等聚集传播性疾病，导致全厂隔离，影响生产 | D17: 4 | E17: 3 | F17: U | G17: 制定《流行病爆发、流行时应急计划》，以应对各种紧急情况，确保生产不受影响 | I17: 3 | J17: 2 | K17: R
A18: 11 | C18: 生产经验丰富、生产技能熟练 | D18: 2 | E18: 1 | F18: A
A19: 12 | B19: 项目生产过程环境条件失控，温湿度异常，影响生产环境 | D19: 2 | E19: 2 | F19: R
A20: 13 | B20: 突发事件发生，影响项目交付 | D20: 4 | E20: 3 | F20: U | G20: 制定《应急计划》，以应对各种紧急情况，确定顾客要求不受影响 | I20: 3 | J20: 2 | K20: R
A21: 14 | B21: 项目交付不准时，顾客不满意 | D21: 3 | E21: 2 | F21: R | K21: =IF(I21="","",I21*J21*#REF!)
A22: 15 | B22: 已交付项目不合格，顾客不满意 | D22: 4 | E22: 3 | F22: U | G22: 落实成品检验制度，严格把好检验关 | I22: 3 | J22: 2 | K22: R
A23: 16 | C23: 项目在同行业中成本低，价格相对合格，质价比高，顾客乐意采购 | D23: 2 | E23: 2 | F23: R
A24: 17 | B24: 供应商交付不准时，原材料供应短缺，影响项目进度 | D24: 4 | E24: 4 | F24: U | G24: 建立《供应商管理程序》规定供方选择评价准则，规定供方定期评估的方法并实施 | I24: 3 | J24: 2 | K24: R
A25: 18 | C25: 公司每年采购量大，集中采购，供应商乐意配合 | D25: 2 | E25: 2 | F25: A | K25: =IF(I25="","",I25*J25*#REF!)
A26: 19 | B26: 供应商交付不合格，影响项目进度 | D26: 4 | E26: 4 | F26: U | G26: 建立《供应商管理程序》规定供方选择评价准则，规定供方定期评估的方法并实施 | I26: 2 | J26: 2 | K26: A
A27: 20 | B27: 供方送货或其它来访人员有感染流行病等聚集传播性疾病，导致公司全体被隔离 | D27: 4 | E27: 3 | F27: U | G27: 制定《流行病爆发、流行时应急计划》，以应对各种紧急情况，确保生产不受影响 | I27: 3 | J27: 2 | K27: R
A28: 21 | C28: 公司付款周期短，30天准时交款，供应商乐意配合 | D28: 2 | E28: 2 | F28: A | K28: =IF(I28="","",I28*J28*#REF!)
A29: 22 | B29: 项目质量管理中，漏检不合格品，导致不合格流转或放行 | D29: 3 | E29: 2 | F29: R | K29: =IF(I29="","",I29*J29*#REF!)
A30: 23 | B30: 量具不准，测量数据不可靠 | D30: 3 | E30: 2 | F30: R | K30: =IF(I30="","",I30*J30*#REF!)
A31: 24 | B31: 项目质量管理中，检验技能不够，把良品判为不良品，导致不必要的返工与调整 | D31: 3 | E31: 4 | F31: U | G31: 建立上岗培训考核制度，确保人员检测技能 | I31: 2 | J31: 2 | K31: A
A32: 25 | C32: 公司检验人员工作经验丰富，学习能力强 | D32: 2 | E32: 2 | F32: R | K32: =IF(I32="","",I32*J32*#REF!)
A33: 26 | B33: 不合格品缺少标识，没有隔离，导致不良品有外流的风险 | D33: 3 | E33: 2 | F33: R
A34: 27 | B34: 劳动力短缺，影响项目生产进度 | D34: 4 | E34: 3 | F34: U | G34: 制定《劳动力短缺应急计划》，以应对各种紧急情况，确保顾客要求不受影响 | I34: 3 | J34: 2 | K34: R
A35: 28 | B35: 全球受流行病等影响，员工有感染的风险，导致全厂隔离 | D35: 4 | E35: 3 | F35: U | G35: 制定《流行病爆发、流行时应急计划》，以应对各种紧急情况，确保生产不受影响 | I35: 3 | J35: 2 | K35: R
A36: 29 | C36: 今年应届大学毕生数量明显多于往年 | D36: 3 | E36: 4 | F36: U | G36: 多招应届毕业生，提升公司员工整体学历水平，提升员工整体水平，增加公司竞争力 | I36: 2 | J36: 2 | K36: A
A37: 30 | B37: 人员培训不到位，导致产品不良发生，影响项目交付 | D37: 2 | E37: 2 | F37: A | K37: =IF(I37="","",I37*J37*#REF!)
A38: 编制/日期 Compilation/Date | F38: 审批/日期 Approval/Date
A39: 表单编号：HLD/CF-04-041-049 Form No ：HLD/CF-04-041-049 | H39: 格式版次：第一版，第0次修改 Format edition: first edition, 0 revision

Sheet 1.11
F1: 密级：秘密★★，未经允许不可查看；保存期限：长期
A2: 设计评审/验证/确认记录 Design review/validation/validation records
H3: 序号NO.：1.11
A4: 新产品名称 The name of the new product | C4: ='0.01'!C4 -> 大块金用工业长丝-帘子布事业部PH25657 Nylon 66 tire cord fabric industrial yarn-Tire cord fabric Department PH25657 | G4: 新产品规格/型号Batch number and specification of new products | H4: ='0.01'!H4 -> PH25657-2800dtex/432f
A5: 顾 客 名 称 The customer name | C5: ='0.01'!H5 -> 帘子布事业部 | G5: 日期 Date | H5: =目录!G22 -> 2023年8月22日
A6: 评审项目 Review project | C6: □设计开发输入 █产品设计输入 □ 可制造性 □ 产品设计输出 □ 过程设计输入 □ 过程设计输出 □安全投产输出 □ 量产输出
A8: 评审内容及记录Review contents and records | C8: 评审项目 | G8: 评审内容 | J8: 评审结论
C9: 特殊特性等产品规范 | E9: 客户有特殊特性及标识要求，已转化为内部通用尼龙工业长丝特殊特性及标识，产品指标要求见立项报告 | G9: 是否充分？ 是否适宜？ 要求是否完整？ 要求是否清楚？ 所有要求是否没有相矛盾？ | J9: □通过 □存在问题 □通过 □存在问题 □通过 □存在问题 □通过 □存在问题 □通过 □存在问题
C10: 边界和对接要求 | E10: 可容纳丝筒外径≤230mm | G10: 是否充分？ 是否适宜？ 要求是否完整？ 要求是否清楚？ 所有要求是否没有相矛盾？ | J10: □通过 □存在问题 □通过 □存在问题 □通过 □存在问题 □通过 □存在问题 □通过 □存在问题
C11: 包装，标识与可追溯性的要求 | E11: 包装无特殊要求，目前现有包装规范能够满足要求；二维码标签 | G11: 是否充分？ 是否适宜？ 要求是否完整？ 要求是否清楚？ 所有要求是否没有相矛盾？ | J11: □通过 □存在问题 □通过 □存在问题 □通过 □存在问题 □通过 □存在问题 □通过 □存在问题
C12: 替代方案 | E12: 越南尼龙生产线可做F、H线的替代生产线 | G12: 是否充分？ 是否适宜？ 要求是否完整？ 要求是否清楚？ 所有要求是否没有相矛盾？ | J12: □通过 □存在问题 □通过 □存在问题 □通过 □存在问题 □通过 □存在问题 □通过 □存在问题
C13: 输入要求的风险评估，以及缓解管理风险 | E13: 详见《风险评估和缓解计划》 | G13: 是否充分？ 是否适宜？ 要求是否完整？ 要求是否清楚？ 所有要求是否没有相矛盾？ | J13: □通过 □存在问题 □通过 □存在问题 □通过 □存在问题 □通过 □存在问题 □通过 □存在问题
C14: 开发目标 | E14: 详见《设计开发任务书》 | G14: 是否充分？ 是否适宜？ 要求是否完整？ 要求是否清楚？ 所有要求是否没有相矛盾？ | J14: □通过 □存在问题 □通过 □存在问题 □通过 □存在问题 □通过 □存在问题 □通过 □存在问题
C15: 客户确定的目的国（如有提供）的适用法规要求 | E15: ='0.05'!E11:F11 -> 符合GB/T30512、ROHS、REACH | G15: 是否充分？ 是否适宜？ 要求是否完整？ 要求是否清楚？ 所有要求是否没有相矛盾？ | J15: □通过 □存在问题 □通过 □存在问题 □通过 □存在问题 □通过 □存在问题 □通过 □存在问题
C16: 嵌入工软件的要求 | E16: 不需要 | G16: 是否充分？ 是否适宜？ 要求是否完整？ 要求是否清楚？ 所有要求是否没有相矛盾？ | J16: □通过 □存在问题 □通过 □存在问题 □通过 □存在问题 □通过 □存在问题 □通过 □存在问题
A17: 评审结果 The results of the | C17: 产品设计输入完整、清楚，满足产品设计的目的，评审通过。
A18: 评审人员会签 The judges will countersign
A19: 编制/日期Compilation/Date | G19: 审批/日期 Approval/Date
A20: 表单编号：HLD/CF-04-041-008 Form No：HLD/CF-04-041-008 | H20: 格式版次：第一版，第2次修改 Format edition: first edition, 2 revision

Sheet 1.12
B1: 密级：秘密★★，未经允许不可查看；保存期限：长期
A2: 阶段性总结和管理者支持 Periodic summary and manager support
J3: 序号NO.：1.12
A4: 新产品名称 The name of the new product | D4: ='0.01'!C4 -> 大块金用工业长丝-帘子布事业部PH25657 Nylon 66 tire cord fabric industrial yarn-Tire cord fabric Department PH25657 | G4: 新产品规格/型号 Batch number and specification of new products | I4: ='0.01'!H4 -> PH25657-2800dtex/432f
A5: 顾客名称 The customer name | D5: ='0.01'!H5 -> 帘子布事业部 | G5: 日期 Date | I5: =目录!G23 -> 2023年8月22日
A6: 一、产品质量先期策划实施和执行阶段： Product quality planning, implementation and Execution stage:
A7: ■ 第一阶段：策划和定义项目 □ 第二阶段：产品设计与开发 □ 第三阶段：过程设计与开发 □ 第四阶段：产品和过程确认
A12: 二、产品质量先期策划实施和执行工作状况（包括每一阶段的质量风险、开发成本、准备时间/前置期、关键路径等内容）：Work status of product quality planning, implementation and execution in advance (including quality risk, development cost, preparation time/lead time, critical path, etc.)
A13: 1、新产品制造可行性分析报告已完成； The new product manufacturing feasibility analysis report has been completed; 2、多方论证小组成员及职责表已完成； The members of the multi-party demonstration team and the list of responsibilities have been completed; 3、新产品项目APQP开发计划已完成； The APQP development plan for the new product project has been completed; 4、新产品开发申请、立项报告、设计开发任务书均已完成； New product development applications, project approval reports, and design and development tasks have all been completed; 5、新产品开发设计目标已完成； The new product development and design goals have been completed; 6、材料清单已完成； The list of materials has been completed; 7、过程流程图已完成； The process flow chart has been completed; 8、特殊特性清单已完成。 The list of special features has been completed.
A22: 三、公司高阶管理层对产品质量先期策划实施和执行工作的总结和支持：Summary and support of the company's senior management for the early planning, implementation and execution of product quality:
A23: 第一阶段均已完成 ，可进行下阶段的工作.
A25: 备 注
A27: 编制/日期Compilation/Date | G27: 审批/日期Approval/Date
A29: 表单编号：HLD/CF-04-041-013 Form No ：HLD/CF-04-041-013 | H29: 格式版次：第一版，第1次修改 Format edition: first edition, 1 revision

Sheet 1.12修改版
B1: 密级：秘密★★，未经允许不可查看；保存期限：长期
A2: 阶段性总结和管理者支持 Periodic summary and manager support
J3: 序号NO.：1.12
A4: 新产品名称 The name of the new product | D4: ='0.01'!C4 -> 大块金用工业长丝-帘子布事业部PH25657 Nylon 66 tire cord fabric industrial yarn-Tire cord fabric Department PH25657 | G4: 新产品规格/型号 Batch number and specification of new products | I4: ='0.01'!H4 -> PH25657-2800dtex/432f
A5: 顾客名称 The customer name | D5: ='0.01'!H5 -> 帘子布事业部 | G5: 日期 Date | I5: =目录!G23 -> 2023年8月22日
A6: 一、产品质量先期策划实施和执行阶段： Product quality planning, implementation and Execution stage:
A7: ■ 第一阶段：策划和定义项目 □ 第二阶段：产品设计与开发 □ 第三阶段：过程设计与开发 □ 第四阶段：产品和过程确认
A12: 二、产品质量先期策划实施和执行工作状况（包括每一阶段的质量风险、开发成本、准备时间/前置期、关键路径等内容）：Work status of product quality planning, implementation and execution in advance (including quality risk, development cost, preparation time/lead time, critical path, etc.) | K12: 评审内容链接 （可点击跳转查看） | O12: 是否OK | Q12: 改进行动 | U12: 全星增加项
A13: 1、新产品制造可行性分析报告已完成； The new product manufacturing feasibility analysis report has been completed; 2、多方论证小组成员及职责表已完成； The members of the multi-party demonstration team and the list of responsibilities have been completed; 3、新产品项目APQP开发计划已完成； The APQP development plan for the new product project has been completed; 4、新产品开发申请、立项报告、设计开发任务书均已完成； New product development applications, project approval reports, and design and development tasks have all been completed; 5、新产品开发设计目标已完成； The new product development and design goals have been completed; 6、材料清单已完成； The list of materials has been completed; 7、过程流程图已完成； The process flow chart has been completed; 8、特殊特性清单已完成。 The list of special features has been completed. | K13: 设计开发任务书 | O13: OK /NG /NA
K14: 初始材料清单（BOM） | L14: 初始材料清单（BOM） | M14: 初始材料清单（BOM） | N14: 初始材料清单（BOM） | O14: OK /NG /NA
K15: 成本核算及报价表 | L15: 成本核算及报价表 | M15: 成本核算及报价表 | N15: 成本核算及报价表 | O15: OK /NG /NA
K16: 过程流程图（初始） | L16: 过程流程图（初始） | M16: 过程流程图（初始） | N16: 过程流程图（初始） | O16: OK /NG /NA
K17: 特殊特性符合转化表 | L17: 特殊特性符合转化表 | M17: 特殊特性符合转化表 | N17: 特殊特性符合转化表 | O17: OK /NG /NA
K18: 产品/过程特殊特性清单（初始） | L18: 产品/过程特殊特性清单（初始） | M18: 产品/过程特殊特性清单（初始） | N18: 产品/过程特殊特性清单（初始） | O18: OK /NG /NA
K19: 产品安全识别表 | L19: 产品安全识别表 | M19: 产品安全识别表 | N19: 产品安全识别表 | O19: OK /NG /NA
K20: 产品保证计划 | L20: 产品保证计划 | M20: 产品保证计划 | N20: 产品保证计划 | O20: OK /NG /NA
K21: 项目变更登记表 | L21: 项目变更登记表 | M21: 项目变更登记表 | N21: 项目变更登记表 | O21: OK /NG /NA
A22: 三、公司高阶管理层对产品质量先期策划实施和执行工作的总结和支持：Summary and support of the company's senior management for the early planning, implementation and execution of product quality: | K22: 风险评估和缓解计划 | L22: 风险评估和缓解计划 | M22: 风险评估和缓解计划 | N22: 风险评估和缓解计划 | O22: OK /NG /NA
A23: 第一阶段均已完成 ，可进行下阶段的工作. | K23: 设计评审/验证/确认记录（产品设计输入） | L23: 设计评审/验证/确认记录（产品设计输入） | M23: 设计评审/验证/确认记录（产品设计输入） | N23: 设计评审/验证/确认记录（产品设计输入） | O23: OK /NG /NA
A25: 备 注
A27: 编制/日期Compilation/Date | G27: 审批/日期Approval/Date
A29: 表单编号：HLD/CF-04-041-013 Form No ：HLD/CF-04-041-013 | H29: 格式版次：第一版，第1次修改 Format edition: first edition, 1 revision
A31: 序 | B31: 发布日期 | E31: 问题描述 | H31: 责任人 | I31: 措施 | J31: 预计完成日期 | K31: 上传证据 | L31: 实际完成日期 | M31: 状态 | N31: 备注 | O31: 全星增加项

Sheet 2.01
P1: 密级：秘密★★，未经允许不可查看；保存期限：长期
A2: DFMEA
A3: 序号NO.：2.01
A4: 步骤1：策划与准备 Step 1: Plan and prepare
A5: 公司名称： Company name: | F5: 浙江海利得新材料股份有限公司 Zhejiang Hailide New Material Co.,Ltd. | K5: 项目： Project: | N5: ='0.01'!C4 -> 大块金用工业长丝-帘子布事业部PH25657 Nylon 66 tire cord fabric industrial yarn-Tire cord fabric Department PH25657 | S5: DFMEA ID 编号： DFMEA ID No.: | X5: /
A6: 制造地址： Manufacturing address: | F6: 浙江省海宁市经编产业园18号 18 Warp Knitting Industrial Park, Haining City, Zhejiang Province | K6: DFMEA开始时间： DFMEA start time: | N6: =目录!G25 -> 2023年8月22日 | S6: 版次： Edition: | X6: 第 一 版，第 0 次修改 Edition 1, revision 0
A7: 顾客名称： Customer Name: | F7: ='0.01'!H5 -> 帘子布事业部 | K7: DFMEA修订时间： DFMEA revision time: | N7: / | S7: 过程责任人： Process owner: | X7: 顾锋 Gu Feng
A8: 车型/项目： Model/Project: | F8: 尼龙66工业长丝 Nylon 66 industrial yarn | K8: 跨职能团队： Cross-functional team: | N8: =目录!B92 -> 顾锋、顾钰炜、谢明智、俞锋、宋琴、熊初珍、叶莉莎、冯梦婷、崔真真、蒋佳贤、马俞锋、谢陈龙、朱翌熹
B9: 持续改善 | C9: 步骤2：结构分析 Step 2: Structural analysis | F9: 步骤3：功能分析 Step 3: Functional analysis | I9: 步骤4：失效分析 Step 4: Failure analysis | M9: 步骤5：风险分析 Step 5: Risk analysis | S9: 步骤6：优化 Step 6: Optimize
A10: 问题# Problem# | B10: 历史/ 变更授权(适用时) | C10: 1.上一较高级别 | D10: 2. 关注要素 | E10: 3. 下一较低级别或特性类型 | F10: 1.上一较高级别功能及要求 | G10: 2.关注要素功能及要求 | H10: 3.下一较低级别功能要求或特性 | I10: 1.对上一较高级别要素和/或最终用户的失效影响（FE） | J10: 失效影响(FE)的严重度(S) | K10: 2.关注要素的失效模式 (FM) | L10: 3.下一较低级别要素或特性的失效起因（FC) | M10: 当前的对失效原因的预防控制（PC） | N10: 失效起因/失效模式的频度(O) | O10: 当前的失效原因或失效模式的探测措施(DC) | P10: 失效起因/失效模式的探测度(D) | Q10: DFMEA措施优先级(AP) | R10: 特殊特性 | S10: 预防措施 | T10: 探测措施 | U10: 负责人姓名 | V10: 目标完成日期 | W10: 状态 | X10: 采取基于证据的措施 | Y10: 完成日期 | Z10: 严重度（S) | AA10: 频度（O) | AB10: 探测度（D) | AC10: DFMEA措施优先级(AP) | AD10: 特殊特性 | AE10: 备注
C11: 尼龙66安全气囊工业长丝 | D11: 油剂 | E11: 油剂动粘度 | F11: 毛丝少、性能稳定、织造性能好 | G11: 给丝上油，增加纤维的集束性、抗静电性、平滑性 | H11: 油剂动粘度：23±3mm2/s | I11: 法律法规（GB/T 30512-2014、REACH、ROHS等）：无影响；下工序：油剂在管路系统内的流动阻力就越大，纺丝上油就越困难；下工厂：产品含油率偏低；最终用户：影响产品外观。 | J11: 5 | K11: 油剂浓度＞26mm2/s | L11: 油剂有效成分配比设计不合理 | M11: 尼龙66工业长丝 同类产品设计经验 | N11: 4 | O11: 参照海利得方法HLD/CF-03-131-043《纺丝油剂、油剂添加剂检测作业指导书》进行油剂动粘度检测 | P11: 5 | Q11: L
I12: 法律法规（GB/T 30512-2014、REACH、ROHS等）：无影响；下工序：油剂会由于附着力下降而出现飞溅的现象；下工厂：产品含油率偏低；最终用户：影响产品外观。 | K12: 油剂浓度＜20mm2/s
D13: 原丝 | E13: 线密度 | G13: 具有特定尺寸、物性、长度的外观无脏污、成型正常的卷装 | H13: 产品线密度：2880±30dtex | I13: 法律法规（GB/T 30512-2014、REACH、ROHS等）：无影响；下工序：丝线密度大；下工厂：产品克重偏重；最终用户：无影响。 | J13: 7 | K13: 线密度＞2910dtex | L13: 计量泵有效泵供量设计不合理 | M13: 尼龙66工业长丝 同类产品设计经验并 参考行业标准FZ∕T 54013-2019 《锦纶66工业用长丝》 | N13: 5 | O13: 参照国标GB/T14343《化学纤维:长丝线密度试验方法》进行纤度检测 | P13: 5 | Q13: M | R13: SC
I14: 法律法规（GB/T 30512-2014、REACH、ROHS等）：无影响；下工序：丝线密度小，强力降低；下工厂：产品克重偏轻、安全气囊撕裂强力降低；最终用户：影响使用寿命。 | K14: 线密度＜2850dtex
E15: 断裂强力 | H15: 产品断裂强力：≥245N | I15: 法律法规（GB/T 30512-2014、REACH、ROHS等）：无影响；下工序：产品强力不能达标；下工厂：安全气囊充气时破裂；最终用户：影响顾客安全。 | J15: 10 | K15: 断裂强力＜245N | L15: 拉伸倍率设计不合理 | M15: 尼龙66工业长丝 同类产品设计经验并 参考行业标准FZ∕T 54013-2019 《锦纶66工业用长丝》 | N15: 4 | O15: 参照国标GB/T14344《合成纤维长丝拉伸性能试验方法》进行断裂强力检测 | P15: 5 | Q15: H | R15: CC | S15: / | T15: 全尺寸测试 | U15: 质量经理 | V15: =目录!H33 -> 45166 | W15: 已完成 | X15: 全尺寸测试 | Y15: =V15 -> 45166 | Z15: 10 | AA15: 3 | AB15: 5 | AC15: M | AD15: CC
L16: 增粘切片粘度设计不合理
E17: 断裂伸长率 | H17: 产品断裂伸长率 ：20.0±3.0% | I17: 法律法规（GB/T 30512-2014、REACH、ROHS等）：无影响；下工序：产品断裂伸长不能达标；下工厂：安全气囊受力情况下形变大；最终用户：影响顾客安全。 | J17: 10 | K17: 断裂伸长率＞23% | L17: 拉伸倍率设计不合理 | M17: 尼龙66工业长丝 同类产品设计经验并 参考行业标准FZ∕T 54013-2019 《锦纶66工业用长丝》 | N17: 4 | O17: 参照国标GB/T14344《合成纤维长丝拉伸性能试验方法》进行断裂伸长率检测 | P17: 5 | Q17: H | R17: CC | S17: / | T17: 全尺寸测试 | U17: 质量经理 | V17: =V15 -> 45166 | W17: 已完成 | X17: 全尺寸测试 | Y17: =V15 -> 45166 | Z17: 10 | AA17: 3 | AB17: 5 | AC17: M | AD17: CC
L18: 松弛率设计不合理
L19: 加热罩温度设计不合理
L20: 侧吹风温度设计不合理
L21: 增粘切片粘度设计不合理
I22: 法律法规（GB/T 30512-2014、REACH、ROHS等）：无影响；下工序：产品断裂伸长不能达标；下工厂：安全气囊的断裂功小，在受力情况下提前断裂；最终用户：影响顾客安全。 | K22: 断裂伸长率＜17% | L22: 拉伸倍率设计不合理 | M22: 尼龙66工业长丝 同类产品设计经验并 参考行业标准FZ∕T 54013-2019 《锦纶66工业用长丝》 | N22: 4 | O22: 参照国标GB/T14344《合成纤维长丝拉伸性能试验方法》进行断裂伸长率检测 | P22: 5
L23: 松弛率设计不合理
L24: 加热罩温度设计不合理
L25: 侧吹风温度设计不合理
L26: 增粘切片粘度设计不合理
E27: 干热收缩率 | H27: 产品干热收缩率：6.20±1.50% | I27: 法律法规（GB/T 30512-2014、REACH、ROHS等）：无影响；下工序：产品干热收缩率不能达标；下工厂：气囊外观不平整；最终用户：气囊布平整度差。 | J27: 7 | K27: 干热收缩率＞7.70% | L27: 松弛率设计不合理 | M27: 尼龙66工业长丝 同类产品设计经验并 参考行业标准FZ∕T 54013-2019 《锦纶66工业用长丝》 | N27: 5 | O27: 参照海利得方法HLDCF-03-131-015 《TST2型干热收缩仪作业指导书》进行干热收缩率检测 | P27: 5 | Q27: M | R27: SC
L28: 定型温度设计不合理
L29: 增粘切片粘度设计不合理
I30: 法律法规（GB/T 30512-2014、REACH、ROHS等）：无影响；下工序：产品干热收缩率不能达标；下工厂：气囊外观不平整；最终用户：气囊布平整度差。 | K30: 干热收缩率＜4.70% | L30: 松弛率设计不合理 | M30: 尼龙66工业长丝 同类产品设计经验并 参考行业标准FZ∕T 54013-2019 《锦纶66工业用长丝》 | N30: 5 | O30: 参照海利得方法HLDCF-03-131-015 《TST2型干热收缩仪作业指导书》进行干热收缩率检测 | P30: 5
L31: 定型温度设计不合理
L32: 增粘切片粘度设计不合理
E33: 网络度 | H33: 产品网络度 ：6.0±3.0nodes/m | I33: 法律法规（GB/T 30512-2014、REACH、ROHS等）：无影响；下工序：纺丝断头多、毛丝多；下工厂：气囊布外观毛；最终用户：产品外观毛丝。 | J33: 5 | K33: 网络度＞9.0nodes/m | L33: 网络器选型不合理 | M33: 尼龙66工业长丝 同类产品设计经验并 参考行业标准FZ∕T 54013-2019 《锦纶66工业用长丝》 | N33: 4 | O33: 参照海利得方法HLDCF-03-131-020 《网络度检测作业指导书》进行网络度检测 | P33: 5 | Q33: L
L34: 网络压空设计不合理
I35: 法律法规（GB/T 30512-2014、REACH、ROHS等）：无影响；下工序：丝束松散；下工厂：气囊布织造性能差，布面松散丝多；最终用户：产品外观毛丝。 | K35: 网络度＜3.0nodes/m | L35: 网络器选型不合理 | M35: 尼龙66工业长丝 同类产品设计经验并 参考行业标准FZ∕T 54013-2019 《锦纶66工业用长丝》 | N35: 4 | O35: 参照海利得方法HLDCF-03-131-020 《网络度检测作业指导书》进行网络度检测 | P35: 5
L36: 网络压空设计不合理
E37: 含油率 | H37: 产品含油率：0.90±0.30% | I37: 法律法规（GB/T 30512-2014、REACH、ROHS等）：无影响；下工序：丝含油高、增加成本；下工厂：安全气囊布粘合力低；最终用户：影响使用寿命。 | J37: 5 | K37: 含油率＞1.20% | L37: 含油率设计不合理 | M37: 尼龙66工业长丝 同类产品设计经验并 参考行业标准FZ∕T 54013-2019 《锦纶66工业用长丝》 | N37: 4 | O37: 参照国标GB/T 6504《化学纤维 含油率测试方法》中NMR方法进行含油率检测 | P37: 5 | Q37: L
L38: 油轮转速设计不合理
I39: 法律法规（GB/T 30512-2014、REACH、ROHS等）：无影响；下工序：丝含油低、纺丝断头、毛丝；下工厂：安全气囊面毛、织造性能差；最终用户：产品外观毛丝。 | K39: 含油率＜0.60% | L39: 含油率设计不合理 | M39: 尼龙66工业长丝 同类产品设计经验并 参考行业标准FZ∕T 54013-2019 《锦纶66工业用长丝》 | N39: 4 | O39: 参照国标GB/T 6504《化学纤维 含油率测试方法》中NMR方法进行含油率检测 | P39: 5
L40: 油轮转速设计不合理
E41: 强力保持率 | H41: 产品强力保持率：≥90% | I41: 法律法规（GB/T 30512-2014、REACH、ROHS等）：无影响；下工序：受热后，强力降低；下工厂：安全气囊撕裂强力降低；最终用户：影响使用寿命。 | J41: 5 | K41: 强力保持率＜90% | L41: 拉伸倍率设计不合理 | M41: 尼龙66工业长丝 同类产品设计经验并 参考行业标准FZ∕T 54013-2019 《锦纶66工业用长丝》 | N41: 5 | O41: 参考行业标准FZ∕T 54013-2019 《锦纶66工业用长丝》进行强力保持率检测 | P41: 5 | Q41: L
L42: 松弛率设计不合理
L43: 定型温度设计不合理
E44: 外观 | H44: 产品外观无脏污 | I44: 法律法规（GB/T 30512-2014、REACH、ROHS等）：无影响；下工序：无影响；下工厂：气囊布油污；最终用户：产品外观污染。 | J44: 4 | K44: 脏污 | L44: 罗拉清洗周期设计不合理 | M44: 尼龙66工业长丝 同类产品设计经验并 参考行业标准FZ∕T 54013-2019 《锦纶66工业用长丝》 | N44: 4 | O44: 参照海利得标准HLDCF-03-041-251《化纤事业部尼龙工业长丝外观定等标准》进行外观检验 | P44: 6 | Q44: L
H45: 产品外观无成型不良 | I45: 法律法规（GB/T 30512-2014、REACH、ROHS等）：无影响；下工序：无影响；下工厂：影响退卷；最终用户：无影响。 | J45: 4 | K45: 成型不良 | L45: 卷绕方式设计不合理
E46: 重量 | H46: 产品重量：4.87±0.15kg | I46: 法律法规（GB/T 30512-2014、REACH、ROHS等）：无影响；下工序：无影响； 下工厂：影响客户原材料消耗，影响织造效率； 最终用户：无影响。 | J46: 5 | K46: 重量＜4.72kg或＞5.02kg | L46: 重量设计不合理 | M46: 尼龙66工业长丝 同类产品设计经验 | N46: 4 | O46: 称重检验 | P46: 5 | Q46: L
A47: 编制/日期 | L47: 批准/日期
A49: 注：CC代表关键特性，SC代表重要特性。 Noted:CC represent critcal characters,SC represent significant characters.

Sheet 2.02
E1: 密级：秘密★★，未经允许不可查看；保存期限：长期
A2: DFMEA检查表
P3: 序号NO.：2.02
A4: 新产品名称 The name of the new product | E4: ='0.01'!C4 -> 大块金用工业长丝-帘子布事业部PH25657 Nylon 66 tire cord fabric industrial yarn-Tire cord fabric Department PH25657 | J4: 新产品批号和规格Batch number and specification of new products | M4: ='0.01'!H4 -> PH25657-2800dtex/432f
A5: 顾 客 名 称 The customer name | E5: ='0.01'!H5 -> 帘子布事业部 | J5: 日期 Date | M5: =目录!G26 -> 2023年8月22日
A6: 问 题 | G6: 是 | H6: 否 | I6: 所要求的意见/措施 | M6: 负责人 | P6: 完成日期
A7: 1 | B7: DFMEA是根据顾客的当前要求编制的吗？
A8: 2 | B8: 是否评审了历史活动和保修数据？
A9: 3 | B9: 是否考虑了从类似零件DFMEA中汲取的最佳实践和经验教训？
A10: 4 | B10: 是否在所有适用地点的最佳实践、经验教训评审和横向展开使用了公司数据库？
A11: 5 | B11: DFMEA是否识别所有特殊和关键特性，包括失效模式？
A12: 6 | B12: 是否已与受影响的供应商一起识别并评审了传递特性(术语表),以确保FMEA达成共识以及在供应商端的适当控制？
A13: 7 | B13: 是否与受影响的供应商一起评审了顾客或组织指定的特殊特性，以确保FMEA一致？
A14: 8 | B14: 是否已确定影响高风险优先失效模式的设计特性？
A15: 9 | B15: 是否已为高风险优先级编号分配了适当的纠正措施？
A16: 10 | B16: 是否已为高严重度编号分配了适当的纠正措施？
A17: 11 | B17: 是否与跨职能团队一起评审了适当的纠正措施？
A18: 12 | B18: 当纠正措施完成并验证后，风险优先级是否已修改？
A19: 13 | B19: 如果顾客工程要求，FMEA是否经过评审和批准？
A20: 编制/日期 | I20: 审批/日期
A21: 表单编号：HLD/CF-04-041-035 Form No：HLD/CF-04-041-035 | O21: 格式版次：第一版，第1次修改 Format edition: first edition, 1 revision

Sheet 2.03
E1: 密级：秘密★★，未经允许不可查看；保存期限：长期
A2: 产品技术规范 Product technical specification
A3: 序号NO.：2.03
A4: 新产品名称The name of the new product | C4: ='0.01'!C4 -> 大块金用工业长丝-帘子布事业部PH25657 Nylon 66 tire cord fabric industrial yarn-Tire cord fabric Department PH25657 | G4: 新产品批号和规格Batch number and specification of new products | I4: ='0.01'!H4 -> PH25657-2800dtex/432f
A5: 顾客名称 The customer name | C5: ='0.01'!H5 -> 帘子布事业部 | G5: 日期 Date | I5: =目录!G27 -> 2023年8月23日
A6: NO. | B6: 项目Item | E6: 单位Unit | G6: 标准Standard | I6: 测试方法 Method of testing | K6: CC/SC
A7: 1 | B7: ='0.02'!B11:D11 -> 线密度 Linear Density | E7: ='0.02'!E11:F11 -> dtex | G7: ='0.02'!G11:H11 -> 2880±30 | I7: ='0.02'!I11:J11 -> GB/T14343 | K7: SC
A8: 2 | B8: ='0.02'!B12:D12 -> 线密度变异系数 CV of Linear Density | E8: ='0.02'!E12:F12 -> % | G8: ='0.02'!G12:H12 -> ≤1.60 | I8: ='0.02'!I12:J12 -> GB/T14343 | K8: —
A9: 3 | B9: ='0.02'!B13:D13 -> 断裂强力 Breaking Strength | E9: ='0.02'!E13:F13 -> N | G9: ='0.02'!G13:H13 -> ≥245.0 | I9: ='0.02'!I13:J13 -> GB/T14344 | K9: CC
A10: 4 | B10: ='0.02'!B14:D14 -> 断裂强度 Tenacity | E10: ='0.02'!E14:F14 -> cN/dtex | G10: ='0.02'!G14:H14 -> ≥8.50 | I10: ='0.02'!I14:J14 -> GB/T14344 | K10: —
A11: 5 | B11: ='0.02'!B15:D15 -> 强度变异系数CV CV of Tenacity | E11: ='0.02'!E15:F15 -> % | G11: ='0.02'!G15:H15 -> ≤3.00 | I11: ='0.02'!I15:J15 -> GB/T14344 | K11: —
A12: 6 | B12: ='0.02'!B16:D16 -> 断裂伸长率 Breaking Elongation Ratio | E12: ='0.02'!E16:F16 -> % | G12: ='0.02'!G16:H16 -> 20.0±3.0 | I12: ='0.02'!I16:J16 -> GB/T14344 | K12: CC
A13: 7 | B13: ='0.02'!B17:D17 -> 伸长变异系数CV CV of Elongation | E13: ='0.02'!E17:F17 -> % | G13: ='0.02'!G17:H17 -> ≤5.00 | I13: ='0.02'!I17:J17 -> GB/T14344 | K13: —
A14: 8 | B14: ='0.02'!B18:D18 -> 中间伸长4.7cN/dtex E.@4.7CN/dtex Load | E14: ='0.02'!E18:F18 -> % | G14: ='0.02'!G18:H18 -> 11.0±1.5 | I14: ='0.02'!I18:J18 -> GB/T14344 | K14: —
A15: 9 | B15: ='0.02'!B19:D19 -> 干热收缩率（177℃×2min×0.05cN/dtex) Shrinkage in Hot Air | E15: ='0.02'!E19:F19 -> % | G15: ='0.02'!G19:H19 -> 6.2±1.5 | I15: ='0.02'!I19:J19 -> HLD method | K15: SC
A16: 10 | B16: ='0.02'!B20:D20 -> 网络度（钩针法） Intermingles（Needle） | E16: ='0.02'!E20:F20 -> nodes/m | G16: ='0.02'!G20:H20 -> 6.0±3.0 | I16: ='0.02'!I20:J20 -> HLD method | K16: —
A17: 11 | B17: ='0.02'!B21:D21 -> 含油率 Spin Finish Oil | E17: ='0.02'!E21:F21 -> % | G17: ='0.02'!G21:H21 -> 0.90±0.30 | I17: ='0.02'!I21:J21 -> GB/T6504-NMR | K17: —
A18: 12 | B18: ='0.02'!B22:D22 -> 强力保持率（180℃×4h） Strength retention rate | E18: ='0.02'!E22:F22 -> % | G18: ='0.02'!G22:H22 -> ≥90 | I18: ='0.02'!I22:J22 -> HLD method | K18: —
A19: 编制/日期Compilation/Date | G19: 审批/日期Approval/Date
A20: 表单编号：HLD/CF-04-041-014 Form No：HLD/CF-04-041-014 | H20: 格式版次：第一版，第1次修改 Format edition: first edition, 1 revision

Sheet 2.03 (变更1)
E1: 密级：秘密★★，未经允许不可查看；保存期限：长期
A2: 产品技术规范 Product technical specification
A3: 序号NO.：2.03
A4: 新产品名称The name of the new product | C4: ='0.01'!C4 -> 大块金用工业长丝-帘子布事业部PH25657 Nylon 66 tire cord fabric industrial yarn-Tire cord fabric Department PH25657 | G4: 新产品批号和规格Batch number and specification of new products | I4: ='0.01'!H4 -> PH25657-2800dtex/432f
A5: 顾客名称 The customer name | C5: ='0.01'!H5 -> 帘子布事业部 | G5: 日期 Date | I5: =目录!G35 -> 2023年12月22日
A6: NO. | B6: 项目Item | E6: 单位Unit | G6: 标准Standard | I6: 测试方法 Method of testing | K6: CC/SC
A7: 1 | B7: ='0.02'!B11:D11 -> 线密度 Linear Density | E7: ='0.02'!E11:F11 -> dtex | G7: ='0.02'!G11:H11 -> 2880±30 | I7: ='0.02'!I11:J11 -> GB/T14343 | K7: SC
A8: 2 | B8: ='0.02'!B12:D12 -> 线密度变异系数 CV of Linear Density | E8: ='0.02'!E12:F12 -> % | G8: ='0.02'!G12:H12 -> ≤1.60 | I8: ='0.02'!I12:J12 -> GB/T14343 | K8: —
A9: 3 | B9: ='0.02'!B13:D13 -> 断裂强力 Breaking Strength | E9: ='0.02'!E13:F13 -> N | G9: ='0.02'!G13:H13 -> ≥245.0 | I9: ='0.02'!I13:J13 -> GB/T14344 | K9: CC
A10: 4 | B10: ='0.02'!B14:D14 -> 断裂强度 Tenacity | E10: ='0.02'!E14:F14 -> cN/dtex | G10: ='0.02'!G14:H14 -> ≥8.50 | I10: ='0.02'!I14:J14 -> GB/T14344 | K10: —
A11: 5 | B11: ='0.02'!B15:D15 -> 强度变异系数CV CV of Tenacity | E11: ='0.02'!E15:F15 -> % | G11: ='0.02'!G15:H15 -> ≤3.00 | I11: ='0.02'!I15:J15 -> GB/T14344 | K11: —
A12: 6 | B12: ='0.02'!B16:D16 -> 断裂伸长率 Breaking Elongation Ratio | E12: ='0.02'!E16:F16 -> % | G12: ='0.02'!G16:H16 -> 20.0±3.0 | I12: ='0.02'!I16:J16 -> GB/T14344 | K12: CC
A13: 7 | B13: ='0.02'!B17:D17 -> 伸长变异系数CV CV of Elongation | E13: ='0.02'!E17:F17 -> % | G13: ='0.02'!G17:H17 -> ≤5.00 | I13: ='0.02'!I17:J17 -> GB/T14344 | K13: —
A14: 8 | B14: ='0.02'!B18:D18 -> 中间伸长4.7cN/dtex E.@4.7CN/dtex Load | E14: ='0.02'!E18:F18 -> % | G14: ='0.02'!G18:H18 -> 11.0±1.5 | I14: ='0.02'!I18:J18 -> GB/T14344 | K14: —
A15: 9 | B15: ='0.02'!B19:D19 -> 干热收缩率（177℃×2min×0.05cN/dtex) Shrinkage in Hot Air | E15: ='0.02'!E19:F19 -> % | G15: ='0.02'!G19:H19 -> 6.2±1.5 | I15: ='0.02'!I19:J19 -> HLD method | K15: SC
A16: 10 | B16: ='0.02'!B20:D20 -> 网络度（钩针法） Intermingles（Needle） | E16: ='0.02'!E20:F20 -> nodes/m | G16: ='0.02'!G20:H20 -> 6.0±3.0 | I16: ='0.02'!I20:J20 -> HLD method | K16: —
A17: 11 | B17: ='0.02'!B21:D21 -> 含油率 Spin Finish Oil | E17: ='0.02'!E21:F21 -> % | G17: ='0.02'!G21:H21 -> 0.90±0.30 | I17: ='0.02'!I21:J21 -> GB/T6504-NMR | K17: —
A18: 编制/日期Compilation/Date | G18: 审批/日期Approval/Date
A19: 表单编号：HLD/CF-04-041-014 Form No：HLD/CF-04-041-014 | H19: 格式版次：第一版，第1次修改 Format edition: first edition, 1 revision

Sheet 2.03 (变更2)
E1: 密级：秘密★★，未经允许不可查看；保存期限：长期
A2: 产品技术规范 Product technical specification
A3: 序号NO.：2.03
A4: 新产品名称The name of the new product | C4: ='0.01'!C4 -> 大块金用工业长丝-帘子布事业部PH25657 Nylon 66 tire cord fabric industrial yarn-Tire cord fabric Department PH25657 | G4: 新产品批号和规格Batch number and specification of new products | I4: ='0.01'!H4 -> PH25657-2800dtex/432f
A5: 顾客名称 The customer name | C5: ='0.01'!H5 -> 帘子布事业部 | G5: 日期 Date | I5: =目录!I35 -> 2024年6月4日
A6: NO. | B6: 项目Item | E6: 单位Unit | G6: 标准Standard | I6: 测试方法 Method of testing | K6: CC/SC
A7: 1 | B7: ='0.02 (变更2)'!B11:D11 -> 线密度 Linear Density | E7: ='0.02 (变更2)'!E11:F11 -> dtex | G7: ='0.02 (变更2)'!G11:H11 -> 2880±30 | I7: ='0.02 (变更2)'!I11:J11 -> GB/T14343 | K7: SC
A8: 2 | B8: ='0.02 (变更2)'!B12:D12 -> 线密度变异系数 CV of Linear Density | E8: ='0.02 (变更2)'!E12:F12 -> % | G8: ='0.02 (变更2)'!G12:H12 -> ≤1.60 | I8: ='0.02 (变更2)'!I12:J12 -> GB/T14343 | K8: —
A9: 3 | B9: ='0.02 (变更2)'!B13:D13 -> 断裂强力 Breaking Strength | E9: ='0.02 (变更2)'!E13:F13 -> N | G9: ='0.02 (变更2)'!G13:H13 -> ≥245.0 | I9: ='0.02 (变更2)'!I13:J13 -> GB/T14344 | K9: CC
A10: 4 | B10: ='0.02 (变更2)'!B14:D14 -> 断裂强度 Tenacity | E10: ='0.02 (变更2)'!E14:F14 -> cN/dtex | G10: ='0.02 (变更2)'!G14:H14 -> ≥8.50 | I10: ='0.02 (变更2)'!I14:J14 -> GB/T14344 | K10: —
A11: 5 | B11: ='0.02 (变更2)'!B15:D15 -> 强度变异系数CV CV of Tenacity | E11: ='0.02 (变更2)'!E15:F15 -> % | G11: ='0.02 (变更2)'!G15:H15 -> ≤3.00 | I11: ='0.02 (变更2)'!I15:J15 -> GB/T14344 | K11: —
A12: 6 | B12: ='0.02 (变更2)'!B16:D16 -> 断裂伸长率 Breaking Elongation Ratio | E12: ='0.02 (变更2)'!E16:F16 -> % | G12: ='0.02 (变更2)'!G16:H16 -> 20.0±3.0 | I12: ='0.02 (变更2)'!I16:J16 -> GB/T14344 | K12: CC
A13: 7 | B13: ='0.02 (变更2)'!B17:D17 -> 伸长变异系数CV CV of Elongation | E13: ='0.02 (变更2)'!E17:F17 -> % | G13: ='0.02 (变更2)'!G17:H17 -> ≤5.00 | I13: ='0.02 (变更2)'!I17:J17 -> GB/T14344 | K13: —
A14: 8 | B14: ='0.02 (变更2)'!B18:D18 -> 中间伸长4.7cN/dtex E.@4.7CN/dtex Load | E14: ='0.02 (变更2)'!E18:F18 -> % | G14: ='0.02 (变更2)'!G18:H18 -> 11.0±1.5 | I14: ='0.02 (变更2)'!I18:J18 -> GB/T14344 | K14: —
A15: 9 | B15: ='0.02 (变更2)'!B19:D19 -> 干热收缩率（177℃×2min×0.05cN/dtex) Shrinkage in Hot Air | E15: ='0.02 (变更2)'!E19:F19 -> % | G15: ='0.02 (变更2)'!G19:H19 -> 5.2±1.5 | I15: ='0.02 (变更2)'!I19:J19 -> HLD method | K15: SC
A16: 10 | B16: ='0.02 (变更2)'!B20:D20 -> 网络度（钩针法） Intermingles（Needle） | E16: ='0.02 (变更2)'!E20:F20 -> nodes/m | G16: ='0.02 (变更2)'!G20:H20 -> 6.0±3.0 | I16: ='0.02 (变更2)'!I20:J20 -> HLD method | K16: —
A17: 11 | B17: ='0.02 (变更2)'!B21:D21 -> 含油率 Spin Finish Oil | E17: ='0.02 (变更2)'!E21:F21 -> % | G17: ='0.02 (变更2)'!G21:H21 -> 0.90±0.30 | I17: ='0.02 (变更2)'!I21:J21 -> GB/T6504-NMR | K17: SC
A18: 编制/日期Compilation/Date | G18: 审批/日期Approval/Date
A19: 表单编号：HLD/CF-04-041-014 Form No：HLD/CF-04-041-014 | H19: 格式版次：第一版，第1次修改 Format edition: first edition, 1 revision

Sheet 2.04
F1: 密级：秘密★★，未经允许不可查看；保存期限：长期
A2: 设计评审/验证/确认记录 Design review/validation/validation records
H3: 序号NO.：2.04
A4: 新产品名称 The name of the new product | C4: ='0.01'!C4 -> 大块金用工业长丝-帘子布事业部PH25657 Nylon 66 tire cord fabric industrial yarn-Tire cord fabric Department PH25657 | G4: 新产品规格/型号Batch number and specification of new products | H4: ='0.01'!H4 -> PH25657-2800dtex/432f
A5: 顾 客 名 称 The customer name | C5: ='0.01'!H5 -> 帘子布事业部 | G5: 日期 Date | H5: =目录!G28 -> 2023年8月23日
A6: 评审项目 Review project | C6: □设计开发输入 □产品设计输入 █ 可制造性 □ 产品设计输出 □ 过程设计输入 □ 过程设计输出 □安全投产输出 □ 量产输出
A8: 评审内容及记录Review contents and records | C8: 评审项目 | G8: 评审内容 | J8: 评审结论
C9: 特殊特性等产品规范 | E9: 详见《产品技术规范》 | G9: 是否充分？ 是否适宜？ 要求是否完整？ 要求是否清楚？ 所有要求是否没有相矛盾？ | J9: □通过 □存在问题 □通过 □存在问题 □通过 □存在问题 □通过 □存在问题 □通过 □存在问题
C10: 开发目标 | E10: 详见《设计开发任务书》 | G10: 是否充分？ 是否适宜？ 要求是否完整？ 要求是否清楚？ 所有要求是否没有相矛盾？ | J10: □通过 □存在问题 □通过 □存在问题 □通过 □存在问题 □通过 □存在问题 □通过 □存在问题
C11: 替代方案 | E11: ='1.11'!E12:F12 -> 越南尼龙生产线可做F、H线的替代生产线 | G11: 是否充分？ 是否适宜？ 要求是否完整？ 要求是否清楚？ 所有要求是否没有相矛盾？ | J11: □通过 □存在问题 □通过 □存在问题 □通过 □存在问题 □通过 □存在问题 □通过 □存在问题
C12: 顾客要求或其它设计要求 | E12: 客户无特殊要求，具体性能要求见立项报告 | G12: 是否充分？ 是否适宜？ 要求是否完整？ 要求是否清楚？ 所有要求是否没有相矛盾？ | J12: □通过 □存在问题 □通过 □存在问题 □通过 □存在问题 □通过 □存在问题 □通过 □存在问题
C13: 以往的开发经验 | E13: ='0.05'!E10:F10 -> 涤纶高模低缩产品设计经验、尼龙工业长丝同类产品设计经验 | G13: 是否充分？ 是否适宜？ 要求是否完整？ 要求是否清楚？ 所有要求是否没有相矛盾？ | J13: □通过 □存在问题 □通过 □存在问题 □通过 □存在问题 □通过 □存在问题 □通过 □存在问题
C14: 新材料 | E14: 无 | G14: 是否充分？ 是否适宜？ 要求是否完整？ 要求是否清楚？ 所有要求是否没有相矛盾？ | J14: □通过 □存在问题 □通过 □存在问题 □通过 □存在问题 □通过 □存在问题 □通过 □存在问题
C15: 产品搬运及人体工学的要求 | E15: 成品搬运叉车搬运，包装方式设计时需要托盘 | G15: 是否充分？ 是否适宜？ 要求是否完整？ 要求是否清楚？ 所有要求是否没有相矛盾？ | J15: □通过 □存在问题 □通过 □存在问题 □通过 □存在问题 □通过 □存在问题 □通过 □存在问题
C16: 制造与装配设计 | E16: 可制造性：产品毛丝按照尼龙工业长丝标准管控；可装配性：丝筒外径≤230mm | G16: 是否充分？ 是否适宜？ 要求是否完整？ 要求是否清楚？ 所有要求是否没有相矛盾？ | J16: □通过 □存在问题 □通过 □存在问题 □通过 □存在问题 □通过 □存在问题 □通过 □存在问题
C17: 防错 | E17: 毛丝检测设计毛丝检测仪，防止毛丝多的产品流出 | G17: 是否充分？ 是否适宜？ 要求是否完整？ 要求是否清楚？ 所有要求是否没有相矛盾？ | J17: □通过 □存在问题 □通过 □存在问题 □通过 □存在问题 □通过 □存在问题 □通过 □存在问题
E18: 包装设计扫描枪，防止产品混装
A19: 评审结果 The results of the | C19: 可制造性设计输入完整、清楚，满足产品可制造性的要求，评审通过。
A20: 评审人员会签 The judges will countersign
A21: 编制/日期Compilation/Date | G21: 审批/日期 Approval/Date
A22: 表单编号：HLD/CF-04-041-008 Form No：HLD/CF-04-041-008 | H22: 格式版次：第一版，第2次修改 Format edition: first edition, 2 revision

Sheet 2.05
F1: 密级：秘密★★，未经允许不可查看；保存期限：长期
A2: 控制计划——尼龙66工业长丝
A3: Control plan --Nylon 66 industrial yarn | O3: 序号NO.：2.05
A4: ■样件Prototype | C4: □试生产Pre-launch | E4: □量产Production | G4: □ 安全投产Safe operation
A5: 文件编号： File Number： | C5: HLD/CF-03-041-254 | G5: 主要联系人/电话 Primary Contact /TEL: | I5: 顾锋/0573-87985287 Gu Feng 0573-87985287 | K5: 日期(编制)：Date(compile) | L5: =目录!G29 -> 2023年8月24日 | M5: 日期(修订)： Date(revise) | O5: /
A6: 版次： Edition: | C6: 第一版，第 0 次修改 First edition, revision 0 | G6: 产品名称 Product Name | I6: ='0.01'!C4 -> 大块金用工业长丝-帘子布事业部PH25657 Nylon 66 tire cord fabric industrial yarn-Tire cord fabric Department PH25657 | K6: 产品规格/型号 Product Specification | L6: ='0.01'!H4 -> PH25657-2800dtex/432f | M6: 顾客工程批准/日期（如需要） Customer Engineering Approval/Date(If Req'd) | O6: /
A7: 组织/工厂 Organization/Plant | C7: 浙江海利得新材料股份有限公司 Zhejiang Hailide New Material Co.,Ltd. | G7: 公司/工厂批准/日期 Organization/Plant Approval/Date | K7: 其它批准/日期 Other Approval/Date | L7: / | M7: 顾客质量批准/日期（如需要） Customer Quality Approval/Date(If Req'd) | O7: /
A8: 组织代码 Organization Code | C8: / | G8: 核心小组 Core team | I8: =目录!B92 -> 顾锋、顾钰炜、谢明智、俞锋、宋琴、熊初珍、叶莉莎、冯梦婷、崔真真、蒋佳贤、马俞锋、谢陈龙、朱翌熹 | M8: 其它批准/日期（如需要） Other Approval/Date (If Req'd) | O8: /
A9: 零件/过程编号 Parts/process No. | B9: 过程名称/操作 描述 Process name/operation description | C9: 机器,装置,夹具,工装 Machine, fixture,jig, tooling | D9: 特性 Characteristics | G9: 特殊特性分类Special characteristic shiftification | H9: 方法 Method | J9: 样本 Sample | L9: 控制方法 Control Method | M9: 执行人员 Responsible | N9: 反应计划 Reaction plan
D10: 编号 No. | E10: 产品 Production | F10: 过程 Process | H10: 产品/过程规范/公差Product/Process Specification /Tolerance | I10: 评价/测量技术 Evaluation/measurement techniques | J10: 容量 Capacity | K10: 频率 Frequency | N10: 措施 Measure | O10: 执行人员 Responsible
A11: PA661100 | B11: 投料 Feeding | C11: 行车 Hoisting equipment | D11: 1101 | F11: 送料 Feeding | H11: HLD/CF-03-051-151《尼龙66投料输送作业指导书》 Nylon 66 Feeding and Conveying Operation Instruction Manual | I11: 料位仪 Material level meter | J11: 按需求量 According to demand | K11: 连续 Continuous | L11: 投料并记录在HLD/CF-04-051-1+L11:L1676《投料记录表》 Feeding and make record in log sheet《 SSP feeding record form》 | M11: 投料工 Feed operator | N11: 按照HLD/CF-03-051-151《尼龙66投料输送作业指导书》要求，发现异常，立即通知上级 If any abnormality is detected, inform your superior immediately | O11: 投料工 Feed operator
A12: PA661200 | B12: 切片输送 PET chip transport | C12: 罗茨风机 Roots blower | D12: 1201 | F12: 压力 Pressure | H12: 1~15KPa | I12: 压力表 Pressure meter | J12: 100% | K12: 连续 Continuous | L12: 按照HLD/CF-03-051-151《尼龙66投料输送作业指导书》要求，进行DCS实时监控 Public works DCS real-time monitoring. | M12: 中控操作工 Center control operator | N12: 按HLD/CF-02-111《化纤事业部设备管理程序》进行设备或电气维修 repaire equipment, electric appliances | O12: 设备人员 Equipment Operators
C13: 回转喂料器 Rotary feeder rotary | D13: 1202 | F13: 回转喂料器回转速度 Rotary feeder rotary speed | H13: 12rpm | I13: 转速控制器 Rotating speed controller | J13: 100% | K13: 连续 Continuous | L13: 按照HLD/CF-03-051-151《尼龙66投料输送作业指导书》要求，进行DCS实时监控 Public works DCS real-time monitoring. | M13: 中控操作工 Center control operator
C14: N2系统 N2 system | D14: 1203 | F14: N2循环系统氧含量 N2 oxygen content | H14: HLD/CF-03-111-021《化纤部公用工程工艺参数》 Public works process standard | I14: O2分析仪 O2 analyser | J14: 100% | K14: 连续 Continuous | L14: 按照HLD/CF-03-111-028《公用工程工艺管理规定》要求，进行DCS实时监控 Public works DCS real-time monitoring. | M14: 设备人员 Equipment Operators | N14: 按照HLD/CF-03-111-028《公用工程工艺管理规定》要求，工艺调整或者设备电气维修 adjust production process and repaire equipment, electric appliances | O14: 设备人员 Equipment Operators
J15: 1个 One | K15: 1次/2h 1time/2h | L15: 按照HLD/CF-03-111-078《化纤事业部设备动力部设备巡检作业规程》要求，巡检并记录在领值系统 Regular check and make record in EAMic | M15: 设备人员 Equipment Operators
D16: 1204 | F16: N2 循环系统露点 N2dew point | H16: HLD/CF-03-111-021《化纤部公用工程工艺参数》 Public works process standard | I16: 露点分析仪 Dew point analyser | J16: 100% | K16: 连续 Continuous | L16: 按照HLD/CF-03-111-028《公用工程工艺管理规定》要求，进行DCS实时监控 Public works DCS real-time monitoring. | M16: 设备人员 Equipment Operators | N16: 按照HLD/CF-03-111-028《公用工程工艺管理规定》要求，工艺调整或者设备电气维修 adjust production process and repaire equipment, electric appliances | O16: 设备人员 Equipment Operators
J17: 1个 One | K17: 1次/2h 1time/2h | L17: 按照HLD/CF-03-111-078《化纤事业部设备动力部设备巡检作业规程》要求，巡检并记录在领值系统 Regular check and make record in EAMic | M17: 设备人员 Equipment Operators
A18: PA661300 | B18: 高粘度切片存储Storage of viscosified chips | C18: 料仓 Chip silo | D18: 1301 | F18: 料位 Material level | H18: 1.8~4.5t | I18: 料位仪 Material level meter | J18: 1 | K18: 连续 Continuous | L18: 按照HLD/CF-03-051-151《尼龙66投料输送作业指导书》要求，进行DCS实时监控 Public works DCS real-time monitoring. | M18: 中控操作工 Center control operator | N18: 按照HLD/CF-03-051-151《尼龙66投料输送作业指导书》要求，发现异常，立即通知上级 If any abnormality is detected, inform your superior immediately | O18: 中控操作工 Center control operator
D19: 1302 | F19: N2压力 N2 pressure | H19: 1~10KPa | I19: 压力表 Pressure gauge | J19: 1 | K19: 连续 Continuous | L19: 按照HLD/CF-03-051-151《尼龙66投料输送作业指导书》要求，进行DCS实时监控 Public works DCS real-time monitoring. | M19: 中控操作工 Center control operator
J20: 所有料仓 All chip silos | K20: 1次/8小时 1time/8h | L20: 巡检N2压力并记录在HLD/CF-04-051-112《SSP巡回检查记录表 》 Route inspection N2 pressure and make record in SSP check list | M20: 中控操作工 Center control operator
D21: 1303 | E21: 毛丝根数 The number of broken filament | H21: HLD/CF-03-041-001《DSD工艺标准》 Standard of spinning process | I21: 毛丝检测仪 Broken filament detector | J21: 1 | K21: 连续 Continuous | L21: 在1900毛丝检测过程，在线实时监控毛丝情况，并按HLD/CF-03-051-019《化纤事业部卷绕岗位作业指导书-挑灯作业指导书》分选丝饼 In 1900 detection of broken filament process，Online real-time monitoring，Sorting the bobbin according to the color of the light | M21: 卷绕工 Winding worker | N21: 按HLD/CF-03-051-019《化纤事业部卷绕岗位作业指导书-挑灯作业指导书》要求进行异常处理 Handle exceptions as required | O21: 卷绕工 Winding worker
A22: PA661400 | B22: 螺杆熔融 Melting by screw | C22: 螺杆挤压机Screw extruder | D22: 1401 | F22: 熔体压力 Melt pressure | H22: HLD/CF-03-041-001《DSD工艺标准》 Standard of spinning process | I22: 压力变送器 Pressure transmitte | J22: 1 | K22: 连续 Continuous | L22: 按照HLD/CF-03-051-101《化纤事业部DSD工艺管理规定》要求实时监控工艺参数 DCS real-time monitoring | M22: 工艺工程师 Spinning technician | N22: 1.按照HLD/CF-03-051-101《化纤事业部DSD工艺管理规定》要求进行工艺调整 Technological adjustment 2.按HLD/CF-02-111《化纤事业部设备管理程序》进行设备或电气维修 repaire equipment, electric appliances 3.按照HLD/CF-03-051-126《纺丝车间异常管理规定》的要求进行反馈 give feedback on issues | O22: 1.工艺工程师 Spinning technician 2.设备人员 Equipment Operators 3.卷绕工 Winding worker
J23: 所有螺杆 All screws | K23: 1次 / 更换品种 1 time / Change varieties | L23: HLD/CF-04-041-038《DSD工艺单》编制、审核 Compilation and review《DSD technology log sheet》 | M23: 工艺工程师、工艺主管 Spinning technician、Head of spinning technician
J24: 所有螺杆 All screws | K24: 1次/1个大检修周期 1 time /1 overhaul cycle | L24: 压力变送器自检 ，记录在HLD/CF-04-132-018《压力传感器期间核查记录表》 Self-check of Pressure transmitter, make record in Pressure sensor check list | M24: 设备人员 Equipment Operators
J25: 所有螺杆 All screws | K25: 1次/2h 1 time/2h | L25: 巡检并记录是否有报警，记录在HLD/CF-04-051-211《纺丝巡检记录表》 Route inspect and make record,make record in Spinning check list | M25: 卷绕工 Winding worker
I26: 转速控制器 Rotating speed controller | J26: 1 | K26: 连续 Continuous | L26: 按照HLD/CF-03-051-101《化纤事业部DSD工艺管理规定》要求实时监控工艺参数 DCS real-time monitoring | M26: 工艺工程师 Spinning technician | N26: 1.按照HLD/CF-03-051-101《化纤事业部DSD工艺管理规定》要求进行工艺调整 Technological adjustment 2.按HLD/CF-02-111《化纤事业部设备管理程序》进行设备或电气维修 repaire equipment, electric appliances | O26: 1.工艺工程师 Spinning technician 2.设备人员 Equipment Operators
J27: 1 | K27: 1次/2年 1 time/ 2 year | L27: 螺杆减速器换油并记录在HLD/CF-04-111-121《设备润滑表》 Change the oil of the reducer and make record in log sheet | M27: 设备人员 Equipment Operators
E28: 线密度 Linear density | G28: SC | H28: HLD/CF-03-041-244《锦纶66工业丝标准》 Product specification | I28: 缕纱测长仪+电子天平 Measuring reel+Electronic scale | J28: 全锭位 All spindles | K28: 1次/12h 1 time/12h | L28: 在2100落丝后按照HLD/CF-03-123-007《化纤事业部成品抽检取样规定》取样，在2300检验过程中检测 Sampling after 2100 Doffing，Detected during 2300 inspection | M28: 卷绕工 Winding worker | N28: 1.按照HLD/CF-03-123-007《化纤事业部成品抽检取样规定》重新取样 Resampling 2.按照HLD/CF-03-051-101《化纤事业部DSD工艺管理规定》要求，分析原因、调整、跟踪 Analyze the cause, adjust and track | O28: 1.卷绕工、工艺工程师 Winding worker、Spinning technician 2.工艺工程师 Spinning technician
J29: 全锭位 All spindles | K29: 1次 / 更换品种 1 time / Change varieties | L29: 在2100落丝后按照HLD/CF-03-123-007《化纤事业部成品抽检取样规定》首件取样，在2300检验过程中检测 First piece sampling after 2100 Doffing，Detected during 2300 inspection | M29: 工艺工程师 Spinning technician
J30: 2个数据点 2 data point | K30: 1次/天 1 time/ day | L30: 按照HLD/CF-03-051-101《化纤事业部DSD工艺管理规定》要求，绘制SPC Xbar-R控制图 SPC Xbar-R management | M30: 工艺工程师 Spinning technician
D31: 1402 | F31: 螺杆温度 Screw temperature | H31: HLD/CF-03-041-001《DSD工艺标准》 Standard of spinning process | I31: 温度传感器 Temperature sensor | J31: 1 | K31: 连续 Continuous | L31: 按照HLD/CF-03-051-101《化纤事业部DSD工艺管理规定》要求实时监控工艺参数 DCS real-time monitoring | M31: 工艺工程师 Spinning technician | N31: 1.按照HLD/CF-03-051-101《化纤事业部DSD工艺管理规定》要求进行工艺调整 Technological adjustment 2.按HLD/CF-02-111《化纤事业部设备管理程序》进行设备或电气维修 repaire equipment, electric appliances 3.按照HLD/CF-03-051-126《纺丝车间异常管理规定》的要求进行反馈 give feedback on issues | O31: 1.工艺工程师 Spinning technician 2.设备人员 Equipment Operators 3.卷绕工 Winding worker
J32: 所有螺杆 All screws | K32: 1次 / 更换品种 1 time / Change varieties | L32: HLD/CF-04-041-038《DSD工艺单》编制、审核 Compilation and review《DSD technology log sheet》 | M32: 工艺工程师、工艺主管 Spinning technician、Head of spinning technician
F33: 螺杆温度 Screw temperature | I33: 温度传感器 Temperature sensor | J33: 所有螺杆 All screws | K33: 1次/1个大检修周期 1 time /1 overhaul cycle | L33: 冷却风扇清扫，记录在HLD/CF-04-111-021《化纤事业部设备报/检修记录表》 Cooling fan clean,make record in log sheet | M33: 设备人员 Equipment Operators
J34: 所有螺杆 All screws | K34: 1次/1个大检修周期 1 time /1 overhaul cycle | L34: 温度传感器对比校验，记录在HLD/CF-04-132-012《化纤事业部热电阻比对记录表》 Regularly contrast check for temperature sensor,make record in thermal resistance comparison check list | M34: 设备人员 Equipment Operators
J35: 所有螺杆 All screws | K35: 1次/2h 1 time/2h | L35: 巡检并记录是否有报警，记录在HLD/CF-04-051-211《纺丝巡检记录表》 Route inspect and make record,make record in Spinning check list | M35: 卷绕工 Winding worker
A36: PA661400 | B36: 螺杆熔融 Melting by screw | C36: 螺杆挤压机Screw extruder | D36: 1403 | F36: 联苯温度 Diphyl temperature | H36: HLD/CF-03-041-001《DSD工艺标准》 Standard of spinning process | I36: 温度传感器 Temperature sensor | J36: 1 | K36: 连续 Continuous | L36: 按照HLD/CF-03-051-101《化纤事业部DSD工艺管理规定》要求实时监控工艺参数 DCS real-time monitoring | M36: 工艺工程师 Spinning technician | N36: 1.按照HLD/CF-03-051-101《化纤事业部DSD工艺管理规定》要求进行工艺调整 Technological adjustment 2.按HLD/CF-02-111《化纤事业部设备管理程序》进行设备或电气维修 repaire equipment, electric appliances 3.按照HLD/CF-03-051-126《纺丝车间异常管理规定》的要求进行反馈 give feedback on issues | O36: 1.工艺工程师 Spinning technician 2.设备人员 Equipment Operators 3.卷绕工 Winding worker
J37: 所有联苯炉 All biphenyl kettles | K37: 1次 / 更换品种 1 time / Change varieties | L37: HLD/CF-04-041-038《DSD工艺单》编制、审核 Compilation and review《DSD technology log sheet》 | M37: 工艺工程师、工艺主管 Spinning technician、Head of spinning technician
J38: 所有联苯炉 All biphenyl kettles | K38: 1次/1年 1 time/ 1 year | L38: 温度传感器校验，记录在HLD/CF-04-132-020《化纤事业部B类监视测量设备台账》 Calibration of temperature sensor,make record in log sheet | M38: 设备人员 Equipment Operators
J39: 所有联苯炉 All biphenyl kettles | K39: 1次/2h 1 time/2h | L39: 巡检并记录是否有报警，记录在HLD/CF-04-051-211《纺丝巡检记录表》 Route inspect and make record,make record in Spinning check list | M39: 卷绕工 Winding worker
D40: 1404 | E40: 毛丝根数 The number of broken filament | H40: HLD/CF-03-041-001《DSD工艺标准》 Standard of spinning process | I40: 毛丝检测仪 Broken filament detector | J40: 1 | K40: 连续 Continuous | L40: 在1900毛丝检测过程，按照HLD/CF-03-051-019《化纤事业部卷绕岗位作业指导书-挑灯作业指导书》要求，按亮灯情况分选丝饼及在线实时监控 In 1900 detection of broken filament process，Sorting the bobbin according to the color of the light and Online real-time monitoring | M40: 卷绕工 Winding worker | N40: 按照HLD/CF-03-051-019《化纤事业部卷绕岗位作业指导书-挑灯作业指导书》要求，进行异常处理 Handle exceptions as required | O40: 卷绕工 Winding worker
A41: PA661500 | B41: 熔体计量 Metering of melt | C41: 计量泵 Metering pump | D41: 1501 | F41: 计量泵转速 Rotating speed of Metering pump | G41: SC | H41: HLD/CF-03-041-001《DSD工艺标准》 Standard of spinning process | I41: 转速控制器 Rotating speed controller | J41: 100% | K41: 连续 Continuous | L41: 按照HLD/CF-03-051-101《化纤事业部DSD工艺管理规定》要求实时监控工艺参数 DCS real-time monitoring | M41: 工艺工程师 Spinning technician | N41: 1.按照HLD/CF-03-051-101《化纤事业部DSD工艺管理规定》要求进行工艺调整 Technological adjustment 2.按HLD/CF-02-111《化纤事业部设备管理程序》进行设备或电气维修 repaire equipment, electric appliances 3.按照HLD/CF-03-051-126《纺丝车间异常管理规定》的要求进行反馈 give feedback on issues | O41: 1.工艺工程师 Spinning technician 2.设备人员 Equipment Operators 3.卷绕工 Winding worker
J42: 所有计量泵 All metering pump | K42: 1次 / 更换品种 1 time / Change varieties | L42: HLD/CF-04-041-038《DSD工艺单》编制、审核 Compilation and review《DSD technology log sheet》 | M42: 工艺工程师、工艺主管 Spinning technician、Head of spinning technician
J43: 所有计量泵 All metering pump | K43: 1次/2h 1 time/2h | L43: 巡检并记录是否有报警，记录在HLD/CF-04-051-211《纺丝巡检记录表》 Route inspect and make record,make record in Spinning check list | M43: 卷绕工 Winding worker
J44: 所有计量泵 All metering pump | K44: 1次/≤12 月 1 time/ ≤ 12month | L44: 校验转速并记录在HLD/CF-04-111-157《计量泵速度比对记录表》 Check speed and make record in log sheet | M44: 设备人员 Equipment Operators
J45: 所有计量泵 All metering pump | K45: 1次/2年 1 time/ 2 year | L45: 减速器换油并记录在HLD/CF-04-111-121《设备润滑表》 Change the oil of the reducer and make record in log sheet | M45: 设备人员 Equipment Operators
D46: 1502 | E46: 线密度 Linear density | G46: SC | H46: HLD/CF-03-041-244《锦纶66工业丝标准》 Product specification | I46: 缕纱测长仪+电子天平 Measuring reel+Electronic scale | J46: 全锭位 All spindles | K46: 1次/12h 1 time/12h | L46: 在2100落丝后按照HLD/CF-03-123-007《化纤事业部成品抽检取样规定》取样，在2300检验过程中检测 Sampling after 2100 Doffing，Detected during 2300 inspection | M46: 卷绕工 Winding worker | N46: 1.按照HLD/CF-03-123-007《化纤事业部成品抽检取样规定》重新取样 Resampling 2.按照HLD/CF-03-051-101《化纤事业部DSD工艺管理规定》要求，分析原因、调整、跟踪 Analyze the cause, adjust and track | O46: 1.卷绕工、工艺工程师 Winding worker、Spinning technician 2.工艺工程师 Spinning technician
J47: 全锭位 All spindles | K47: 1次 / 更换品种 1 time / Change varieties | L47: 在2100落丝后按照HLD/CF-03-123-007《化纤事业部成品抽检取样规定》首件取样，在2300检验过程中检测 First piece sampling after 2100 Doffing，Detected during 2300 inspection | M47: 工艺工程师 Spinning technician
J48: 2个数据点 2 data point | K48: 1次/天 1 time/ day | L48: 按照HLD/CF-03-051-101《化纤事业部DSD工艺管理规定》要求，绘制SPC Xbar-R控制图 SPC Xbar-R management | M48: 工艺工程师 Spinning technician
A49: PA661600 | B49: 喷丝 Spinning | C49: 喷丝板 Spinneret plate | D49: 1601 | F49: 喷丝孔长径比 Length - Diameter ratio of spinneret | H49: HLD/CF-03-041-001《DSD工艺标准》 Standard of spinning process | I49: 目测 Visual inspection | J49: 全锭位 All spindles | K49: 1次 / 更换品种 1 time / Change varieties | L49: HLD/CF-04-041-038《DSD工艺单》编制、审核 Compilation and review《DSD technology log sheet》 | M49: 工艺工程师、工艺主管 Spinning technician、Head of spinning technician | N49: 按照HLD/CF-03-051-009《化纤事业部组件组装作业指导书》要求，反馈组长 Feedback Team Leader | O49: 泵板工 Pumb plate worker
J50: 一块板 A piece of board | K50: 1次/1次组件组装 1 time/1 spin pack assemble | L50: 组件组装并记录在HLD/CF-04-051-014《组件组装记录表》 Spinning pack assemble and record in log sheet | M50: 泵板工 pumb plate worker
D51: 1602 | F51: 喷丝板孔数 Number of spinneret holes | H51: HLD/CF-03-041-001《DSD工艺标准》 Standard of spinning process | I51: 目测 Visual inspection | J51: 全锭位 All spindles | K51: 1次 / 更换品种 1 time / Change varieties | L51: HLD/CF-04-041-038《DSD工艺单》编制、审核 Compilation and review《DSD technology log sheet》 | M51: 工艺工程师、工艺主管 Spinning technician、Head of spinning technician
J52: 一块板 A piece of board | K52: 1次/1次组件组装 1 time/1 spin pack assemble | L52: 组件组装并记录在HLD/CF-04-051-014《组件组装记录表》 Spinning pack assemble and record in log sheet | M52: 泵板工 pumb plate worker
C53: 喷丝板 Spinneret plate | D53: 1603 | F53: 污垢值 Dirt amount of spinneret plate | H53: HLD/CF-03-041-007《化纤事业部泵板岗位技术标准》 Technical standard of post | I53: 自动镜检仪 Automatic Optical Instrument | J53: 所有孔 Spinneret orifice | K53: 1次/1次喷丝板检验 1 time/1 spinneret piece inspect | L53: 检查并记录在HLD/CF-04-113-001《镜检台账》 Check and record in Make record for optical inspection of spinneret plate | M53: 镜检员 Inspector | N53: 按照HLD/CF-02-113《化纤事业部工装管理程序》要求，重新清洗喷丝板并镜检 Rinse the spinneret and inspect | O53: 泵板工、镜检员 pumb plate worker、Inspector
J54: 所有镜检仪 Automatic Optical Instruments | K54: 1次/月 1 time / Month | L54: 对镜检仪自校，记录在HLD/CF-04-113-011《全自动镜检仪维护记录表》 Calibration for automatic optical instruments ,make record in Automatic Optical Instruments check list | M54: 镜检员 Inspector
C55: 组件 Spinning pack | D55: 1604 | F55: 滤网孔径 Diameter of filter | H55: HLD/CF-03-041-001《DSD工艺标准》 Standard of spinning process | I55: 目测 Visual inspection | J55: 全锭位 All spindles | K55: 1次 / 更换品种 1 time / Change varieties | L55: HLD/CF-04-041-038《DSD工艺单》编制、审核 Compilation and review《DSD technology log sheet》 | M55: 工艺工程师、工艺主管 Spinning technician、Head of spinning technician | N55: 按照HLD/CF-03-051-009《化纤事业部组件组装作业指导书》要求，反馈组长 Feedback Team Leader | O55: 泵板工 pumb plate worker
J56: 一个滤网 1 strainer | K56: 1次/1次组件组装 1 time/1 spin pack assemble | L56: 组件组装并记录在HLD/CF-04-051-014《组件组装记录表》 Spinning pack assemble and record in log sheet | M56: 泵板工 pumb plate worker
J57: 1 | K57: 连续 Continuous | L57: 按照HLD/CF-03-051-101《化纤事业部DSD工艺管理规定》要求，对组件压力实时监控Presure real-time monitoring for spinning pack | M57: 工艺工程师 Spinning technician
D58: 1605 | F58: 组件预热时间 pack warm-up time | H58: HLD/CF-03-041-007《化纤事业部泵板岗位技术标准》 Technical standard of post | I58: 钟表 clock | J58: 所有组件 All spinning pack | K58: 1次/1次组件组装 1 time/1 spin pack assemble | L58: 上机前确认，记录在HLD/CF-04-051-015《化纤事业部组件预热确认表》 Confirm before boarding,record in log sheet | M58: 泵板工 pump plate worker | N58: 按照HLD/CF-03-041-007《化纤事业部泵板岗位技术标准》要求，重新预热组件 Reheat the spinning pack | O58: 泵板工 pumb plate worker
D59: 1606 | F59: 组件预热温度 Preheating temperature of spinning pack | H59: HLD/CF-03-041-007《化纤事业部泵板岗位技术标准》 Technical standard of post | I59: 温度计 Thermometer | J59: 所有组件 All spinning pack | K59: 1次/组件安装 1 Time/Spinning pack loading | L59: 上机前确认，记录在HLD/CF-04-051-015《化纤事业部组件预热确认表》 Confirm before boarding,record in log sheet | M59: 泵板工 pumb plate worker
D60: 1607 | F60: 铲板周期 Cleanning cyle time | H60: HLD/CF-03-041-001《DSD工艺标准》 Standard of spinning process | I60: 钟表 Timer | J60: 全锭位 All spindles | K60: 1次 / 更换品种 1 time / Change varieties | L60: HLD/CF-04-041-038《DSD工艺单》编制、审核 Compilation and review《DSD technology log sheet》 | M60: 工艺工程师、工艺主管 Spinning technician、Head of spinning technician | N60: 1.按照HLD/CF-03-051-021《板面修正作业指导书》要求，重新铲板 Cleanning of spinneret plate again 2.按照HLD/CF-03-051-021《板面修正作业指导书》要求，更换组件 Replacement of the spinning pack | O60: 1.清洗工 Cleaner 2.泵板工 pumb plate worker
J61: 全锭位 All spindles | K61: 1次/1个铲板周期 1 time/1 shovel plate period | L61: 板面修正，记录在QR/HLD-04-12-01或HLD/CF-04-051-026/028/184/192《卷绕落筒记录表》 Cleanning the spinneret,record in log sheet | M61: 清洗工 Cleaner
A62: PA661600 | B62: 喷丝 Spinning | C62: 组件 Spinning pack | D62: 1608 | F62: 使用周期 Usage period | H62: HLD/CF-03-041-007《化纤事业部泵板岗位技术标准》 Technical standard of post | I62: 日历 Calendar | J62: 全锭位 All spindles | K62: 1次/1个使用周期 1 time/1 use period | L62: 组件更换，记录在HLD/CF-04-051-013《组件周期更换表》 Change Spin pack,record in log sheet | M62: 生产主管 Workshop supervisor | N62: 按照HLD/CF-03-041-007《化纤事业部泵板岗位技术标准》要求，立即更换组件 Replacement of the spinning pack | O62: 泵板工 pumb plate worker
D63: 1609 | E63: 毛丝根数 The number of broken filament | H63: HLD/CF-03-041-001《DSD工艺标准》 Standard of spinning process | I63: 毛丝检测仪 Broken filament detector | J63: 1 | K63: 连续 Continuous | L63: 在1900毛丝检测过程，按照HLD/CF-03-051-019《化纤事业部卷绕岗位作业指导书-挑灯作业指导书》要求，按亮灯情况分选丝饼及在线实时监控 In 1900 detection of broken filament process，Sorting the bobbin according to the color of the light and Online real-time monitoring | M63: 卷绕工 Winding worker | N63: 按照HLD/CF-03-051-019《化纤事业部卷绕岗位作业指导书-挑灯作业指导书》要求，进行异常处理 Handle exceptions as required | O63: 卷绕工 Winding worker
A64: PA661700 | B64: 冷却成型 Cooling and molding | C64: 加热罩 Heating hood | D64: 1701 | F64: 加热罩温度 Heating hood temperature | G64: CC | H64: HLD/CF-03-041-001《DSD工艺标准》 Standard of spinning process | I64: 温度传感器 Temperature sensor | J64: 1 | K64: 连续 Continuous | L64: 按照HLD/CF-03-051-101《化纤事业部DSD工艺管理规定》要求实时监控工艺参数 DCS real-time monitoring | M64: 工艺工程师 Spinning technician | N64: 1.按照HLD/CF-03-051-101《化纤事业部DSD工艺管理规定》要求进行工艺调整 Technological adjustment 2.按HLD/CF-02-111《化纤事业部设备管理程序》进行设备或电气维修 repaire equipment, electric appliances 3.按照HLD/CF-03-051-126《纺丝车间异常管理规定》的要求进行反馈 give feedback on issues | O64: 1.工艺工程师 Spinning technician 2.设备人员 Equipment Operators 3.卷绕工 Winding worker
J65: 所有纺位 All spinning positions | K65: 1次 / 更换品种 1 time / Change varieties | L65: HLD/CF-04-041-038《DSD工艺单》编制、审核 Compilation and review《DSD technology log sheet》 | M65: 工艺工程师、工艺主管 Spinning technician、Head of spinning technician
J66: 所有纺位 All spinning positions | K66: 1次/1个大检修周期 1 time /1 overhaul cycle | L66: 温度传感器对比校验，记录在HLD/CF-04-132-012《化纤事业部热电阻比对记录表》 Regularly contrast check for temperature sensor,make record in thermal resistance comparison check list | M66: 设备人员 Equipment Operators
J67: 所有纺位 All spinning positions | K67: 1次/2h 1 time/2h | L67: 巡检并记录是否有报警，记录在HLD/CF-04-051-211《纺丝巡检记录表》 Route inspect and make record,make record in Spinning check list | M67: 卷绕工 Winding worker
E68: 断裂伸长 Breaking elongation ratio | G68: CC | H68: HLD/CF-03-041-244《锦纶66工业丝标准》 Product specification | I68: 强伸仪 Tensile tester | J68: 全锭位 All spindles | K68: 1次/12h 1 time/12h | L68: 在2100落丝后按照HLD/CF-03-123-007《化纤事业部成品抽检取样规定》取样，在2300检验过程中检测 Sampling after 2100 Doffing，Detected during 2300 inspection | M68: 卷绕工 Winding worker | N68: 1.按照HLD/CF-03-123-007《化纤事业部成品抽检取样规定》重新取样 Resampling 2.按照HLD/CF-03-051-101《化纤事业部DSD工艺管理规定》要求，分析原因、调整、跟踪 Analyze the cause, adjust and track | O68: 1.卷绕工、工艺工程师 Winding worker、Spinning technician 2.工艺工程师 Spinning technician
J69: 全锭位 All spindles | K69: 1次 / 更换品种 1 time / Change varieties | L69: 在2100落丝后按照HLD/CF-03-123-007《化纤事业部成品抽检取样规定》首件取样，在2300检验过程中检测 First piece sampling after 2100 Doffing，Detected during 2300 inspection | M69: 工艺工程师 Spinning technician
J70: 2个数据点 2 data point | K70: 1次/天 1 time/ day | L70: 按照HLD/CF-03-051-101《化纤事业部DSD工艺管理规定》要求，绘制SPC Xbar-R控制图 SPC Xbar-R management | M70: 工艺工程师 Spinning technician
C71: N2系统 N2 system | D71: 1702 | F71: N2温度 N2 temperature | H71: HLD/CF-03-041-001《DSD工艺标准》 Standard of spinning process | I71: 温度传感器 Temerature sensor | J71: 每个 Each | K71: 1次/4h 1time/4h | L71: 巡检并记录温度在HLDCF-04-051-247《尼龙产线氮气巡检记录表》 Check and record the temperature | M71: 卷绕工 Winding worker | N71: 按照HLD/CF-03-051-126《纺丝车间异常管理规定》的要求进行反馈 give feedback on issues | O71: 卷绕工 Winding worker
D72: 1703 | F72: N2风量 N2 air volume | H72: HLD/CF-03-041-001《DSD工艺标准》 Standard of spinning process | I72: 流量计 Flowmeter | J72: 每个 Each | K72: 1次/4h 1time/4h | L72: 巡检并记录风量在HLDCF-04-051-247《尼龙产线氮气巡检记录表》 Check and record the air volume | M72: 卷绕工 Winding worker
D73: 1704 | F73: N2循环系统氧含量 N2 oxygen content | H73: HLD/CF-03-111-021《化纤部公用工程工艺参数》 Public works process standard | I73: O2分析仪 O2 analyser | J73: 100% | K73: 连续 Continuous | L73: 按照HLD/CF-03-111-028《公用工程工艺管理规定》要求，进行DCS实时监控 Public works DCS real-time monitoring. | M73: 设备人员 Equipment Operators | N73: 按照HLD/CF-03-111-028《公用工程工艺管理规定》要求，工艺调整或者设备电气维修 adjust production process and repaire equipment, electric appliances | O73: 设备人员 Equipment Operators
J74: 1个 One | K74: 1次/2h 1time/2h | L74: 按照HLD/CF-03-111-078《化纤事业部设备动力部设备巡检作业规程》要求，巡检并记录在领值系统 Regular check and make record in EAMic | M74: 设备人员 Equipment Operators
A75: PA661700 | B75: 冷却成型 Cooling and molding | C75: N2系统 N2 system | D75: 1705 | F75: N2 循环系统露点 N2dew point | H75: HLD/CF-03-111-021《化纤部公用工程工艺参数》 Public works process standard | I75: 露点分析仪 Dew point analyser | J75: 100% | K75: 连续 Continuous | L75: 按照HLD/CF-03-111-028《公用工程工艺管理规定》要求，进行DCS实时监控 Public works DCS real-time monitoring. | M75: 设备人员 Equipment Operators | N75: 按照HLD/CF-03-111-028《公用工程工艺管理规定》要求，工艺调整或者设备电气维修 adjust production process and repaire equipment, electric appliances | O75: 设备人员 Equipment Operators
J76: 1个 One | K76: 1次/2h 1time/2h | L76: 按照HLD/CF-03-111-078《化纤事业部设备动力部设备巡检作业规程》要求，巡检并记录在领值系统 Regular check and make record in EAMic | M76: 设备人员 Equipment Operators
C77: 抽吸装置 Aspirator | D77: 1706 | F77: 风量 Air Volume | H77: HLD/CF-03-041-001《DSD工艺标准》 Standard of spinning process | I77: 压力表 Pressure meter | J77: 每个 Each | K77: 1次/2天 1time/2Day | L77: 清理滤网并记录在HLDCF-04-051-248《尼龙产线抽吸滤网清理记录表》 Clean the filter screen and record it | M77: 卷绕工 Winding worker | N77: 按HLD/CF-02-111《化纤事业部设备管理程序》进行设备或电气维修 repaire equipment, electric appliances | O77: 设备人员 Equipment Operators
J78: 1个 One | K78: 1次/1年 1 time/ 1 year | L78: 风机保养并记录在HLD/CF-04-111-121《设备润滑表》 Fan maintenance and make record in log sheet | M78: 设备人员 Equipment Operators
C79: 侧吹风机 Lateral air blower | D79: 1707 | F79: 侧吹风温度 Lateral air temperature | G79: CC | H79: HLD/CF-03-111-021《化纤部公用工程工艺参数》 Process parameter of utility | I79: 温度传感器 Temperature sensor | J79: 1 | K79: 连续 Continuous | L79: 按照HLD/CF-03-111-028《公用工程工艺管理规定》要求，进行DCS实时监控 DCS real-time monitoring | M79: 设备人员 Equipment Operators | N79: 按HLD/CF-02-111《化纤事业部设备管理程序》进行设备或电气维修 repaire equipment, electric appliances | O79: 设备人员 Equipment Operators
J80: 所有工艺空调 All process air conditions | K80: 1次/1个大检修周期 1 time /1 overhaul cycle | L80: 空调机组保养，记录在HLD/CF-04-111-174《空调机组保养记录表》 Air condition units maintenance,make record in log sheet | M80: 设备人员 Equipment Operators
J81: 所有制冷机 All refrigerators | K81: 1次/年 1 time/ year | L81: 按照HLD/CF-03-111-008《设备维护保养作业规程》要求，进行制冷机保养，供应商提供《制冷保养工单》 Maintenance of refrigerating machine,Refrigeration Maintenance Work Order provided by Supplier | M81: 设备人员 Equipment Operators
J82: 所有工艺空调 All process air conditions | K82: 1次/1个大检修周期 1 time /1 overhaul cycle | L82: 温度传感器校验，记录在HLD/CF-04-132-020《化纤事业部B类监视测量设备台账》 Calibration of temperature sensor,make record in log sheet | M82: 设备人员 Equipment Operators
J83: 所有工艺空调 All process air conditions | K83: 1次/6h 1 time/6h | L83: 按照HLD/CF-03-111-028《公用工程工艺管理规定》要求，巡检并记录在领值系统 Regular check and record for utility facilities,make record in EAMic | M83: 设备人员 Equipment Operators
E84: 断裂伸长 Breaking elongation ratio | G84: CC | H84: HLD/CF-03-041-244《锦纶66工业丝标准》 Product specification | I84: 强伸仪 Tensile tester | J84: 全锭位 All spindles | K84: 1次/12h 1 time/12h | L84: 在2100落丝后按照HLD/CF-03-123-007《化纤事业部成品抽检取样规定》取样，在2300检验过程中检测 Sampling after 2100 Doffing，Detected during 2300 inspection | M84: 卷绕工 Winding worker | N84: 1.按照HLD/CF-03-123-007《化纤事业部成品抽检取样规定》重新取样 Resampling 2.按照HLD/CF-03-051-101《化纤事业部DSD工艺管理规定》要求，分析原因、调整、跟踪 Analyze the cause, adjust and track | O84: 1.卷绕工、工艺工程师 Winding worker、Spinning technician 2.工艺工程师 Spinning technician
J85: 全锭位 All spindles | K85: 1次 / 更换品种 1 time / Change varieties | L85: 在2100落丝后按照HLD/CF-03-123-007《化纤事业部成品抽检取样规定》首件取样，在2300检验过程中检测 First piece sampling after 2100 Doffing，Detected during 2300 inspection | M85: 工艺工程师 Spinning technician
J86: 2个数据点 2 data point | K86: 1次/天 1 time/ day | L86: 按照HLD/CF-03-051-101《化纤事业部DSD工艺管理规定》要求，绘制SPC Xbar-R控制图 SPC Xbar-R management | M86: 工艺工程师 Spinning technician
A87: PA661700 | B87: 冷却成型 Cooling and molding | C87: 侧吹风机 Lateral air blower | D87: 1708 | F87: 侧吹风风速 Lateral air speed | H87: HLD/CF-03-111-021《化纤部公用工程工艺参数》 Process parameter of utility | I87: 压力传感器 Pressure sensor | J87: 1 | K87: 连续 Continuous | L87: 按照HLD/CF-03-111-028《公用工程工艺管理规定》要求，进行DCS实时监控 DCS real-time monitoring | M87: 设备人员 Equipment Operators | N87: 按HLD/CF-02-111《化纤事业部设备管理程序》进行设备或电气维修 repaire equipment, electric appliances | O87: 设备人员 Equipment Operators
J88: 所有工艺空调 All process air conditions | K88: 1次/6h 1 time/6h | L88: 按照HLD/CF-03-111-028《公用工程工艺管理规定》要求，巡检并记录在领值系统 Regular check and record for utility facilities,make record in EAMic | M88: 设备人员 Equipment Operators
J89: 所有工艺空调 All process air conditions | K89: 1次/1个大检修周期 1 time /1 overhaul cycle | L89: 压力传感器校验，记录在HLD/CF-04-132-020《化纤事业部B类监视测量设备台账》 Check pressure sensor,make record in log sheet | M89: 设备人员 Equipment Operators
J90: 所有工艺空调 All process air conditions | K90: 1次/1个大检修周期 1 time /1 overhaul cycle | L90: 空调机组保养，记录在HLD/CF-04-111-174《空调机组保养记录表》 Air condition units maintenance,make record in log sheet | M90: 设备人员 Equipment Operators
H91: HLD/CF-03-041-001《DSD工艺标准》 Standard of spinning process | I91: 风速仪 Anemometer | J91: 所有纺位 All spinning positions | K91: 1次 / 更换品种 1 time / Change varieties | L91: HLD/CF-04-041-038《DSD工艺单》编制、审核 Compilation and review《DSD technology log sheet》 | M91: 工艺工程师、工艺主管 Spinning technician、Head of spinning technician | N91: 按照HLD/CF-03-051-101《化纤事业部DSD工艺管理规定》要求进行工艺调整 Technological adjustment | O91: 工艺工程师 Spinning technician
J92: 所有纺位 All spinning positions | K92: 1次/≤1月 1 time/≤ 1 month | L92: DSD巡回检查并记录在HLD/CF-04-051-115《化纤事业部DSD工艺巡回检查记录表》 Regular DSD checking and recording in Regular DSD check list | M92: 工艺工程师 Spinning technician
J93: 所有纺位 All spinning positions | K93: 任意测试点超标进行清洗 Any test point exceeds the standard for cleaning | L93: 清洗侧吹风板并记录在HLD/CF-04-051-142《化纤事业部侧吹风网板清洗记录》 Clean the plate of lateral air device and make record in Clean the plate of quching air device check list | M93: 工艺工程师 Spinning technician
E94: 线密度变异系数CV of Linear Density | H94: HLD/CF-03-041-244《锦纶66工业丝标准》 Product specification | I94: 缕纱测长仪+电子天平 Measuring reel+Electronic scale | J94: 全锭位 All spindles | K94: 1次/12h 1 time/12h | L94: 在2100落丝后按照HLD/CF-03-123-007《化纤事业部成品抽检取样规定》取样，在2300检验过程中检测 Sampling after 2100 Doffing，Detected during 2300 inspection | M94: 卷绕工 Winding worker | N94: 1.按照HLD/CF-03-123-007《化纤事业部成品抽检取样规定》重新取样 Resampling 2.按照HLD/CF-03-051-101《化纤事业部DSD工艺管理规定》要求，分析原因、调整、跟踪 Analyze the cause, adjust and track | O94: 1.卷绕工、工艺工程师 Winding worker、Spinning technician 2.工艺工程师 Spinning technician
J95: 全锭位 All spindles | K95: 1次 / 更换品种 1 time / Change varieties | L95: 在2100落丝后按照HLD/CF-03-123-007《化纤事业部成品抽检取样规定》首件取样，在2300检验过程中检测 First piece sampling after 2100 Doffing，Detected during 2300 inspection | M95: 工艺工程师 Spinning technician
D96: 1709 | E96: 毛丝根数 The number of broken filament | H96: HLD/CF-03-041-001《DSD工艺标准》 Standard of spinning process | I96: 毛丝检测仪 Broken filament detector | J96: 1 | K96: 连续 Continuous | L96: 在1900毛丝检测过程，按照HLD/CF-03-051-019《化纤事业部卷绕岗位作业指导书-挑灯作业指导书》要求，按亮灯情况分选丝饼及在线实时监控 In 1900 detection of broken filament process，Sorting the bobbin according to the color of the light and Online real-time monitoring | M96: 卷绕工 Winding worker | N96: 按照HLD/CF-03-051-019《化纤事业部卷绕岗位作业指导书-挑灯作业指导书》要求，进行异常处理 Handle exceptions as required | O96: 卷绕工 Winding worker
A97: PA661800 | B97: 上油 Adding oil | C97: 油盒 Oil box | D97: 1801 | F97: 油剂循环 Spin finish circulation | H97: 油剂正常循环 Spin finish circulation without abnormality | I97: 目测 Visual inspection | J97: 所有线位 All positions | K97: 1次/≤4个月 1 time≤4 month | L97: 定期清洗油剂管道并记录在HLD/CF-04-051-141《化纤事业部油剂系统清洗记录》 Clean the oil pipe regularly and record in the Oil System Cleaning Record. | M97: 设备人员、工艺工程师Equipment Operators、Spinning technician | N97: 1.按照HLD/CF-03-051-101《化纤事业部DSD工艺管理规定》要求进行工艺调整 Technological adjustment 2.按HLD/CF-02-111《化纤事业部设备管理程序》进行设备或电气维修 repaire equipment, electric appliances 3.按照HLD/CF-03-051-126《纺丝车间异常管理规定》的要求进行反馈 give feedback on issues | O97: 1.工艺工程师 Spinning technician 2.设备人员 Equipment Operators 3.卷绕工 Winding worker
J98: 所有油剂系统 All oil systems | K98: 1次/≤1周 1 time≤1 week | L98: 油剂循环系统压力巡检并记录在HLD/CF-04-051-115《化纤事业部DSD工艺巡回检查记录表》 Oil circulation system pressure inspection and record in log sheet | M98: 工艺工程师 Spinning technician
J99: 所有油剂泵 All oil pumps | K99: 1次/1个大检修周期 1 time /1 overhaul cycle | L99: 设备保养记录在HLD/CF-04-111-160《油剂泵更换保养记录》 Equipment maintenance,record in log sheet | M99: 设备人员 Equipment Operators
J100: 所有线位 All positions | K100: 1次/≤1周 1 time≤1 week | L100: 检查油轮、油盒中油剂状况并清理，记录在HLD/CF-04-051-115《化纤事业部DSD工艺巡回检查记录表》 Check the condition of oil agent in oil roller and oil tank and clean up,recording in Regular DSD check list | M100: 工艺工程师 Spinning technician
...

Sheet 2.06
F1: 密级：秘密★★，未经允许不可查看；保存期限：长期
A2: 控制计划检查表 Control plan checklist
P3: 序号NO.：2.06
A4: 新产品名称 The name of the new product | D4: ='0.01'!C4 -> 大块金用工业长丝-帘子布事业部PH25657 Nylon 66 tire cord fabric industrial yarn-Tire cord fabric Department PH25657 | H4: 新产品批号和规格 Batch number and specification of new products | M4: ='0.01'!H4 -> PH25657-2800dtex/432f
A5: 顾 客 名 称 The customer name | D5: ='0.01'!H5 -> 帘子布事业部 | H5: 日期 Date | M5: =目录!G30 -> 2023年8月24日
A6: 问 题 The problem | G6: 是 Yes | H6: 否 No | I6: 所要求的意见/措施 Comments/measures requested | M6: 责任人person in charge | P6: 完成日期 Completion date
A7: 1 | B7: 控制措施是根据AlAG控制计划手册中描述的方法制定的吗?
A8: 2 | B8: 是否使用DFMEA和PFMEA来编制控制计划?
A9: 3 | B9: FMEA中识别的所有控制措施是否都包含在控制计划中?
A10: 4 | B10: 是否所有流向PFMEA进行控制的严重度为9—10的DFMEA项目都指定为特殊特性
A11: 5 | B11: 控制计划中是否包含所有产品/过程特殊特性
A12: 6 | B12: 是否识别需要检验的材料规范?
A13: 7 | B13: 控制计划是否涵盖从来料(材料/组件)到加工/组装(包括包装)等步骤?
A14: 8 | B14: 在控制计划中是否包含所可能影响顾客的传递特征?
A15: 9 | B15: 所有相互依赖的过程是否都包含在该控制计划中，或者是否链接到该控制计划?
A16: 10 | B16: 如果存在返工或返修过程，它们是否包含在此控制计划中或包含在与此控制计划链接的单独控制计划中?
A17: 11 | B17: 返修和返工过程是否已获得顾客批准?
A18: 12 | B18: 是否识别了工程性能测试和尺寸要求?
... A27: 21 | B27: 吸取的经验教训和“横向展开”行动是否得到实施?
A28: 编制/日期 Compilation/Date | I28: 审批/日期 Approval/Date
A29: 表单编号：HLD/CF-04-041-027 Form No : HLD/CF-04-041-027 | M29: 格式版次：第一版，第5次修改 Format edition: first edition,5 revision

Sheet 2.07
B1: 密级：秘密★★，未经允许不可查看；保存期限：长期
B2: DSD工艺标准（TMT）
B3: 序号NO.：2.07
B4: 文件编号: | H4: HLD/CF-03-041-001 | U4: 生产线位: | Z4: H线 | AI4: 编制 | AN4: 审核 | AS4: 批准
B5: 客户名称: | H5: ='0.01'!H5 -> 帘子布事业部 | U5: 编制日期: | Z5: =目录!G31 -> 2023年8月25日 | AI5: 沈志远 | AN5: 谢明智 | AS5: 俞锋
B6: 产品规格: | H6: ='0.01'!H4 -> PH25657-2800dtex/432f | U6: 修订日期: | Z6: / | AI6: =Z5 -> 2023年8月25日 | AN6: =Z5 -> 2023年8月25日 | AS6: =Z5 -> 2023年8月25日
B7: 管控要求: | H7: NA
B8: 纺丝部分 | Z8: 卷绕部分
B9: 工艺参数 | J9: CC/SC | M9: 单位 | P9: 设定范围 | V9: 波动报警 | Z9: 工艺参数 | AH9: CC/SC | AK9: 单位 | AN9: 设定范围 | AT9: 波动报警
B10: 螺杆挤压机 | E10: 熔体压力 | J10: - | M10: MPa | P10: 8±3 | V10: M±2 | Z10: 导向罗拉 | AD10: 速度 | AH10: - | AK10: m/min | AN10: / | AT10: /
E11: 一区 | J11: - | M11: ℃ | P11: 288±20 | V11: M±10 | Z11: 一罗拉 | AD11: 速度 | AH11: CC | AK11: m/min | AN11: 491±10 | AT11: /
E12: 二区 | J12: - | M12: ℃ | P12: 290±20 | V12: M±10 | AD12: 温度 | AH12: SC | AK12: ℃ | AN12: 55±10 | AT12: M±5
E13: 三区 | J13: - | M13: ℃ | P13: 295±20 | V13: M±10 | AD13: 绕丝圈数 | AH13: - | AK13: r | AN13: 3 | AT13: /
E14: 四区 | J14: - | M14: ℃ | P14: 290±10 | V14: M±10 | Z14: 二罗拉 | AD14: 速度 | AH14: CC | AK14: m/min | AN14: 501±10 | AT14: /
E15: 四区(风扇) | J15: - | M15: ℃ | P15: / | V15: / | AD15: 温度 | AH15: SC | AK15: ℃ | AN15: 70±10 | AT15: M±5
E16: 五区 | J16: - | M16: ℃ | P16: 276±10 | V16: M±10 | AD16: 绕丝圈数 | AH16: - | AK16: r | AN16: 3 | AT16: /
E17: 五区(风扇) | J17: - | M17: ℃ | P17: / | V17: / | Z17: 三罗拉 | AD17: 速度 | AH17: CC | AK17: m/min | AN17: 1533±30 | AT17: /
E18: 六区 | J18: - | M18: ℃ | P18: 273±10 | V18: M±10 | AD18: 温度 | AH18: SC | AK18: ℃ | AN18: 185±10 | AT18: M±5
E19: 六区(风扇) | J19: - | M19: ℃ | P19: / | V19: / | AD19: 绕丝圈数 | AH19: - | AK19: r | AN19: 4 | AT19: /
E20: 出口温度 | J20: - | M20: ℃ | P20: ≥275 | V20: M±10 | Z20: 四罗拉 | AD20: 速度 | AH20: CC | AK20: m/min | AN20: 2700±30 | AT20: /
B21: 联苯温度 | J21: - | M21: ℃ | P21: 285±2 | V21: M±2 | AD21: 温度 | AH21: SC | AK21: ℃ | AN21: 236±10 | AT21: M±5
B22: 加热罩温度 | J22: CC | M22: ℃ | P22: 310±30 | V22: M±10 | AD22: 绕丝圈数 | AH22: - | AK22: r | AN22: 7 | AT22: /
B23: 隔热筒长度 | J23: - | M23: mm | P23: 150 | V23: / | Z23: 五罗拉 | AD23: 速度 | AH23: CC | AK23: m/min | AN23: 2500±30 | AT23: /
B24: 环吹动压 | J24: - | M24: KPa | P24: / | V24: / | AD24: 温度 | AH24: SC | AK24: ℃ | AN24: / | AT24: /
B25: 侧吹风速 | J25: - | M25: m/s | P25: 0.5 | V25: / | AD25: 绕丝圈数 | AH25: - | AK25: r | AN25: 5.5 | AT25: /
B26: 喷丝板孔数 | J26: - | M26: f | P26: 108 | V26: / | Z26: 六罗拉 | AD26: 速度 | AH26: - | AK26: m/min | AN26: / | AT26: /
B27: 喷丝板孔径×长 | J27: - | M27: mm | P27: 0.4*1.2 | V27: / | AD27: 温度 | AH27: - | AK27: ℃ | AN27: / | AT27: /
B28: 组件滤网孔径 | J28: - | M28: μm | P28: 20 | V28: / | AD28: 绕丝圈数 | AH28: - | AK28: r | AN28: / | AT28: /
B29: 组件压力 | J29: - | M29: MPa | P29: ≤35 | V29: ≤30 | Z29: 计量泵转速 | AH29: SC | AK29: r/min | AN29: 8.87±1.00 | AT29: /
B30: 铲板周期 | J30: - | M30: h | P30: 48±8 | V30: / | Z30: 油轮转速 | AH30: - | AK30: r/min | AN30: 12.5±2.0 | AT30: /
B31: 清洗罗拉周期 | J31: - | M31: h | P31: 24±8 | V31: / | Z31: 卷绕设定速度 | AH31: - | AK31: m/min | AN31: 2500 | AT31: /
B32: 其他参数 | Z32: CR速度 | AH32: - | AK32: m/min | AN32: 2470±30 | AT32: /
Z33: 泵供量 | AH33: - | AK33: g/min | AN33: 705 | AT33: /
B34: 工艺参数 | J34: CC/SC | M34: 单位 | P34: 设定范围 | V34: 波动报警 | Z34: 纸管外径 | AH34: - | AK34: mm | AN34: 106 | AT34: /
B35: 预网络器 | G35: 压力 | J35: - | M35: MPa | P35: 0.1±0.05 | V35: / | Z35: 卷绕时间 | AH35: - | AK35: h/m/s | AN35: 7m | AT35: /
B36: 附加网络器 | G36: 压力 | J36: - | M36: MPa | P36: / | V36: / | Z36: 满卷卷重 | AH36: - | AK36: kg | AN36: 4.87±0.15 | AT36: /
B37: 第二网络器 | G37: 压力 | J37: - | M37: MPa | P37: / | V37: / | Z37: 卷绕控制方式 | AH37: - | AK37: TC/SC | AN37: TC | AT37: /
B38: 主网络器 | G38: 型号 | J38: - | M38: MPa | P38: 35-50 | V38: / | Z38: 卷绕设定 | AC38: 卷绕张力 | AH38: - | AK38: / | AN38: 116±10 | AT38: M±20%
G39: 压力 | J39: - | M39: MPa | P39: 0.5±0.2 | V39: / | AC39: 张力P值 | AH39: - | AK39: % | AN39: 75±20 | AT39: /
B40: 毛检仪型号 | J40: - | M40: / | P40: 恩卡 | V40: / | AC40: 张力I值 | AH40: - | AK40: sec | AN40: 3±3 | AT40: /
B41: 毛检仪探测度 | J41: - | M41: / | P41: 4.5mm | V41: / | AC41: 衰减 | AH41: - | AK41: % | AN41: 0±50 | AT41: /
B42: 在线毛丝检测仪设置 | G42: 绿灯 | J42: - | M42: 个/卷 | P42: 0-100 | V42: / | AC42: 一段比例 | AH42: - | AK42: % | AN42: 100±10 | AT42: /
G43: 黄灯 | J43: - | M43: 个/卷 | P43: 101-150 | V43: / | AC43: 二段比例 | AH43: - | AK43: % | AN43: 100±10 | AT43: /
G44: 红灯 | J44: - | M44: 个/卷 | P44: >150 | V44: / | AC44: 三段比例 | AH44: - | AK44: % | AN44: 100±10 | AT44: /
G45: 红绿灯 | J45: - | M45: 个/卷 | P45: / | V45: / | AC45: 一段时间 | AH45: - | AK45: sec | AN45: 100±100 | AT45: /
B46: 纺丝油剂型号 | J46: - | M46: / | P46: SLT-B-100E | V46: / | AC46: 二段时间 | AH46: - | AK46: sec | AN46: 300±100 | AT46: /
B47: 功能油剂型号 | J47: - | M47: / | P47: / | V47: / | AC47: 三段时间 | AH47: - | AK47: sec | AN47: 900±100 | AT47: /
B48: 功能油剂泵频率 | J48: - | M48: / | P48: / | V48: / | AC48: 初始卷绕角 | AH48: - | AK48: deg | AN48: 8.6±1.0 | AT48: /
B49: 色母粒型号 | J49: - | M49: / | P49: / | V49: / | AC49: 卷绕角范围 | AH49: - | AK49: deg | AN49: 0.18±0.10 | AT49: /
B50: 色母粒添加比例 | J50: - | M50: % | P50: / | V50: / | AC50: 基准周期 | AH50: - | AK50: / | AN50: 7±2 | AT50: /
B51: 断丝感应器 | J51: - | M51: / | P51: 0 | V51: / | AC51: 叠丝间距 | AH51: - | AK51: mm | AN51: 0.22±0.15 | AT51: /
B52: 注：CC代表关键特性；SC代表重要特性；M代表设定值。

Sheet DR (1)
J1: 密级：内部公开，对外保密★；保存期限：长期
A2: 浙江海利得新材料股份有限公司 | H2: RN.：HLD/CF-04-131-018；V1.1
A3: =目录!B91 -> 帘子布事业部 | G3: Dimensional Report | M3: Measurement Date: | O3: 45165
A6: SUPPLIER NAME: | E6: Zhejiang Hailide New Material Co.,Ltd | I6: PART NUMBER: | L6: =目录!B90 -> PH25657-2800dtex/432f
A7: SUPPLIER ID NUMBER: | E7: - | I7: DRAWING NUMBER: | L7: -
A8: PART BATCH NUMBER: | E8: H 202308 | I8: PART NAME: | L8: =目录!B90 -> PH25657-2800dtex/432f
A9: MOLD CAVITY NUMBER: | E9: Line H
A11: REMARKS:
A14: NO. | B14: DIMENSION NUMBERS | C14: DIMENSION / SPECIFICATION | G14: SC/CC | H14: MEASUREMENT METHOD/GAGE | I14: SUPPLIER MEASUREMENT RESULTS | N14: JUDGEMENT | P14: REMARKS | T14: 线密度 | U14: 断裂强力 | V14: 断裂强度 | W14: 断裂伸长率 | X14: 中间伸长 | Y14: 干热收缩率 | Z14: 网络度 | AA14: 含油率
C15: SPECIFICATION | E15: UPPER TOLERANCES | F15: LOWER TOLERANCES | I15: 1 | J15: 2 | K15: 3 | L15: 4 | M15: 5 | N15: OK | O15: NOT OK | T15: 2902 | U15: 252.2 | V15: 8.72 | W15: 20.06 | X15: 10.4 | Y15: 5.27 | Z15: 7 | AA15: 0.98
A16: 1 | B16: Material | C16: PA66 | G16: CC | H16: —— | I16: PET | N16: OK | T16: 2885 | U16: 252.5 | V16: 8.73 | W16: 19.63 | X16: 10.4 | Y16: 5.3 | Z16: 5 | AA16: 0.82
A17: 2 | B17: Linear density | C17: ='0.02'!G11 -> 2880±30 | D17: ='0.02'!E11 -> dtex | E17: 2910 | F17: 2850 | G17: SC | H17: Measuring Reel& Balance | I17: =T15 -> 2902 | J17: =T16 -> 2885 | K17: =T17 -> 2900 | L17: =T18 -> 2879 | M17: =T19 -> 2872 | N17: OK | T17: 2900 | U17: 243.8 | V17: 8.53 | W17: 20.07 | X17: 10.5 | Y17: 5.23 | Z17: 6 | AA17: 0.87
A18: 3 | B18: Breaking strength | C18: ='0.02'!G13 -> ≥245.0 | D18: ='0.02'!E13 -> N | E18: - | F18: 245 | G18: CC | H18: Strength Tester | I18: =I17*I19/100 -> 253.0544 | J18: =J17*J19/100 -> 251.8605 | K18: =K17*K19/100 -> 247.37 | L18: =L17*L19/100 -> 247.594 | M18: =M17*M19/100 -> 249.864 | N18: OK | T18: 2879 | U18: 248.4 | V18: 8.6 | W18: 21.21 | X18: 10.5 | Y18: 5.3 | Z18: 7 | AA18: 0.81
A19: 4 | B19: Tenacity | C19: ='0.02'!G14 -> ≥8.50 | D19: ='0.02'!E14 -> cN/dtex | E19: - | F19: 8.5 | H19: Strength Tester | I19: =V15 -> 8.72 | J19: =V16 -> 8.73 | K19: =V17 -> 8.53 | L19: =V18 -> 8.6 | M19: =V19 -> 8.7 | N19: OK | T19: 2872 | U19: 250.6 | V19: 8.7 | W19: 21.48 | X19: 10 | Y19: 5.41 | Z19: 6 | AA19: 0.85
A20: 5 | B20: Breaking@Elongation | C20: ='0.02'!G16 -> 20.0±3.0 | D20: ='0.02'!E16 -> % | E20: 23 | F20: 17 | G20: CC | H20: Strength Tester | I20: =W15 -> 20.06 | J20: =W16 -> 19.63 | K20: =W17 -> 20.07 | L20: =W18 -> 21.21 | M20: =W19 -> 21.48 | N20: OK
A21: 6 | B21: E.@4.7CN/dtex Load | C21: ='0.02'!G18 -> 11.0±1.5 | D21: ='0.02'!E18 -> % | E21: 12.5 | F21: 9.5 | H21: Strength Tester | I21: =X15 -> 10.4 | J21: =X16 -> 10.4 | K21: =X17 -> 10.5 | L21: =X18 -> 10.5 | M21: =X19 -> 10 | N21: OK
A22: 7 | B22: Hot Air Shrinkage | C22: ='0.02'!G19 -> 6.2±1.5 | D22: ='0.02'!E19 -> % | E22: 7.7 | F22: 4.7 | G22: SC | H22: HAS Tester | I22: =Y15 -> 5.27 | J22: =Y16 -> 5.3 | K22: =Y17 -> 5.23 | L22: =Y18 -> 5.3 | M22: =Y19 -> 5.41 | N22: OK
A23: 8 | B23: Intermingle | C23: ='0.02'!G20 -> 6.0±3.0 | D23: ='0.02'!E20 -> nodes/m | E23: 9 | F23: 3 | H23: Needle | I23: =Z15 -> 7 | J23: =Z16 -> 5 | K23: =Z17 -> 6 | L23: =Z18 -> 7 | M23: =Z19 -> 6 | N23: OK
A24: 9 | B24: Oil pick up | C24: ='0.02'!G21 -> 0.90±0.30 | D24: ='0.02'!E21 -> % | E24: 1.2 | F24: 0.6 | H24: NMR Tester | I24: =AA15 -> 0.98 | J24: =AA16 -> 0.82 | K24: =AA17 -> 0.87 | L24: =AA18 -> 0.81 | M24: =AA19 -> 0.85 | N24: OK
A25: 10 | B25: Strength retention rate | C25: ='0.02'!G22 -> ≥90 | D25: ='0.02'!E22 -> % | E25: - | F25: 90 | H25: Oven&Strength Tester | I25: 93.4 | N25: OK
A26: 11 | B26: Mass | C26: ='0.02'!D25 -> 4.87±0.15 | D26: ='0.02'!C25 -> kg | E26: 5.02 | F26: 4.72 | H26: Electronic Scale | I26: 4.91 | J26: 4.95 | K26: 4.93 | L26: 4.97 | M26: 4.89 | N26: OK
A27: 12 | B27: Bobbin length | C27: 16500 | H27: —— | I27: - | J27: - | K27: - | L27: - | M27: - | N27: -
A28: 13 | B28: Bobbin Diam:d(outer) | C28: ='0.02'!D27 -> ≤230 | D28: ='0.02'!C27 -> mm | E28: 230 | F28: - | H28: Ruler | I28: 209.4 | J28: 210.9 | K28: 210.5 | L28: 210.1 | M28: 209.7 | N28: OK
A29: 14 | B29: Bobbin Stroke:h | C29: ='0.02'!D28 -> 252±10 | D29: ='0.02'!C28 -> mm | E29: 262 | F29: 242 | H29: Vernier Caliper | I29: 249.8 | J29: 250.1 | K29: 248.9 | L29: 251.2 | M29: 250.5 | N29: OK
A30: 15 | B30: Core Height: h | C30: ='0.02'!D29 -> 300.00+0.2/-0.1 | D30: ='0.02'!C29 -> mm | E30: 300.2 | F30: 299.9 | H30: Vernier Caliper | I30: 300.1 | J30: 300.08 | K30: 300.1 | L30: 300.06 | M30: 300.03 | N30: OK
A31: 16 | B31: Core Diam: d (inner) | C31: ='0.02'!D30 -> 94.00+0.2/-0.1 | D31: ='0.02'!C30 -> mm | E31: 94.2 | F31: 93.9 | H31: Vernier Caliper | I31: 94 | J31: 94.02 | K31: 94.08 | L31: 94.01 | M31: 94.05 | N31: OK
A32: 17 | B32: Core Diam: d (outer) | C32: ='0.02'!D31 -> 106.00+0.2/-0.1 | D32: ='0.02'!C31 -> mm | E32: 106.2 | F32: 105.9 | H32: Vernier Caliper | I32: 105.93 | J32: 106.06 | K32: 106.14 | L32: 106.05 | M32: 105.98 | N32: OK
A33: 18 | B33: Core Color | C33: Grey&White | H33: Visual inspection | I33: =C33 -> Grey&White | N33: OK
A35: Supplier Comments: | D35: Qualified | I35: Supplier Information
I36: Approved by:Crystal Cui | M36: Title:Quality manager
A37: Comments(For customer use only):
I38: Prepared by／Date: Deva Xiang | M38: =目录!H33 -> 45166

Sheet 2.09
E1: 密级：秘密★★，未经允许不可查看；保存期限：长期
A2: 设计验证报告 Design verification report
H3: 序号NO.：2.09
A4: 新产品名称 The name of the new product | C4: ='0.01'!C4 -> 大块金用工业长丝-帘子布事业部PH25657 Nylon 66 tire cord fabric industrial yarn-Tire cord fabric Department PH25657 | F4: 新产品批号和规格 Batch number and specification of new products | H4: =目录!B90 -> PH25657-2800dtex/432f
A5: 顾客名称 The customer name | C5: ='0.01'!H5 -> 帘子布事业部 | F5: 日期 Date | H5: =目录!G33 -> 2023年8月28日
A6: 项目目标 project objective | C6: 指标 target | F6: 指标完成情况 index achieving status | I6: 统计时间 statistical time
A7: 1.日程安排 | C7: ='1.01'!C10 -> 2023年8月完成试样 | F7: 2023.8.27完成样件生产 | I7: 第二阶段结束
A8: 2.过程能力 | C8: ='1.01'!C11:E11 -> CC/SC项PPK≥1.67或CPK≥1.67 （当数据符合正态分布且稳定时看CPK，当数据不符合正态分布或不稳定时看PPK） | G8: Ppk | H8: Cpk | I8: 第二阶段、第四阶段结束
F9: =C15 -> 线密度 Linear Density | G9: - | H9: 1.81
F10: =C16 -> 断裂强力 Breaking Strength | G10: - | H10: 1.75
F11: =C17 -> 断裂伸长率 Breaking Elongation Ratio | G11: - | H11: 1.85
F12: =C18 -> 干热收缩率（177℃×2min×0.05cN/dtex) Shrinkage in Hot Air | G12: - | H12: 1.95
A13: 3.开发成本 | C13: ='1.01'!C12 -> 成本控制与其他尼龙66工业长丝产品类似 | F13: NA | I13: 第四阶段结束
A14: 4.生产率 | C14: ='1.01'!C13 -> ≥0.9吨/天/位 | F14: NA | I14: 第四阶段结束
A15: 5.产品符合性（CC/SC项，其余一般特性见《立项报告》）： | C15: ='1.01'!C14 -> 线密度 Linear Density | D15: ='1.01'!D14 -> 2880±30 | E15: ='1.01'!E14 -> dtex | F15: 符合，见全尺寸测试报告 | I15: 第二阶段、第四阶段结束
C16: ='1.01'!C15 -> 断裂强力 Breaking Strength | D16: ='1.01'!D15 -> ≥245.0 | E16: ='1.01'!E15 -> N | I16: 第二阶段、第四阶段结束
C17: ='1.01'!C16 -> 断裂伸长率 Breaking Elongation Ratio | D17: ='1.01'!D16 -> 20.0±3.0 | E17: ='1.01'!E16 -> % | I17: 第二阶段、第四阶段结束
C18: ='1.01'!C17 -> 干热收缩率（177℃×2min×0.05cN/dtex) Shrinkage in Hot Air | D18: ='1.01'!D17 -> 6.2±1.5 | E18: ='1.01'!E17 -> % | I18: 第二阶段、第四阶段结束
A19: 6.可靠性及质量目标 | C19: ='1.01'!C18 -> 优等率≥90% | F19: NA | I19: 第四阶段结束
A20: 7.APQP指标 | C20: 见项目计划 | F20: 均按时完成，见《新产品APQP开发计划》 | I20: 每个阶段结束时
A21: 备注： | C21: 附产品测试COA、全尺寸测试报告
A22: 编制/日期 Compilation/Date | F22: 审批/日期 Approval/Date
A23: 表单编号：HLD/CF-04-041-050 Form No：HLD/CF-04-041-050 | G23: 格式版次：第一版，第0次修改 Format edition: first edition, 0 revision

Sheet 2.10
F1: 密级：秘密★★，未经允许不可查看；保存期限：长期
A2: 设计评审/验证/确认记录 Design review/validation/validation records
H3: 序号NO.：2.10
A4: 新产品名称 The name of the new product | C4: ='0.01'!C4 -> 大块金用工业长丝-帘子布事业部PH25657 Nylon 66 tire cord fabric industrial yarn-Tire cord fabric Department PH25657 | G4: 新产品规格/型号Batch number and specification of new products | H4: ='0.01'!H4 -> PH25657-2800dtex/432f
A5: 顾 客 名 称 The customer name | C5: ='0.01'!H5 -> 帘子布事业部 | G5: 日期 Date | H5: =目录!G34 -> 2023年8月29日
A6: 评审项目 Review project | C6: □设计开发输入 □产品设计输入 □ 可制造性 █ 产品设计输出 □ 过程设计输入 □ 过程设计输出 □安全投产输出 □ 量产输出
A8: 评审内容及记录Review contents and records | C8: 设计开发输入要求 | G8: 对应的输出 | J8: 评审结论
C9: 产品性能要求 | E9: 详见《新产品开发申请立项报告》 | G9: 见全尺寸测试报告 | J9: □满足 □不满足
C10: 特殊特性等产品规范 | E10: 详见《产品技术规范》 | G10: 见全尺寸测试报告 | J10: □满足 □不满足
C11: 适用于产品的法律、法规要求 | E11: ='0.05'!E11:F11 -> 符合GB/T30512、ROHS、REACH | G11: 经评价符合要求，见测试报告 | J11: □满足 □不满足
C12: 适用于产品的标准和行业规范 | E12: ='0.05'!E12:F12 -> 产品满足行标FZ∕T 54013锦纶66工业用长丝标准要求 | G12: 见产品COA报告 | J12: □满足 □不满足
C13: 顾客要求或其它设计要求 | E13: ='2.04'!E12:F12 -> 客户无特殊要求，具体性能要求见立项报告 | G13: 见全尺寸测试报告 | J13: □满足 □不满足
C14: 可利用的类似产品信息 | E14: ='0.05'!E10:F10 -> 涤纶高模低缩产品设计经验、尼龙工业长丝同类产品设计经验 | G14: 设计时已参考类似产品信息，见《产品技术规范》 | J14: □满足 □不满足
C15: 由产品性质所导致的潜在失效后果的管控 | E15: ='0.05'!E13 -> 线密度在标准范围内尽可能保持稳定，降低线密度变异系数 | G15: 已纳入DFMEA中重点分析并在设计时规避，见DFMEA | J15: □满足 □不满足
E16: ='0.05'!E14 -> 断裂强度对成品帘子布的强力影响较大，生产过程中必须保证不低于标准强度
E17: ='0.05'!E15 -> 干热收缩率对帘子布的尺寸稳定性影响较大，生产过程中必须保证干热收缩率在标准范围内
E18: ='0.05'!E16 -> 其余性能指标按照现有的生产技术能力，可以满足客户的要求
A19: 评审内容及记录Review contents and records | C19: 边界和对接要求 | E19: ='1.11'!E10:F10 -> 可容纳丝筒外径≤230mm | G19: 见全尺寸测试报告 | J19: □满足 □不满足
C20: 嵌入工软件的要求 | E20: 不需要 | G20: NA | J20: □满足 □不满足
C21: 包装，标识与可追溯性的要求 | E21: 包装无特殊要求，目前现有包装规范能够满足要求；二维码标签 | G21: 见包装规范、作业指导书 | J21: □满足 □不满足
C22: 替代方案 | E22: ='1.11'!E12:F12 -> 越南尼龙生产线可做F、H线的替代生产线 | G22: 见《过程流程图》 | J22: □满足 □不满足
C23: 新材料 | E23: 无 | G23: 见BOM | J23: □满足 □不满足
C24: 产品搬运及人体工学的要求 | E24: 成品搬运叉车搬运，包装方式设计时需要托盘 | G24: 见包装规范、作业指导书 | J24: □满足 □不满足
C25: 制造与装配设计 | E25: ='2.04'!E16:F16 -> 可制造性：产品毛丝按照尼龙工业长丝标准管控；可装配性：丝筒外径≤230mm | G25: 见工艺标准、全尺寸测试报告 | J25: □满足 □不满足
C26: 防错 | E26: 毛丝检测设计毛丝检测仪，防止毛丝多的产品流出 | G26: 见《控制计划》 | J26: □满足 □不满足
E27: 包装设计扫描枪，防止产品混装
C28: 输入要求的风险评估，以及缓解管理风险 | E28: 详见《风险评估和缓解计划》 | G28: 可行，详见《风险评估和缓解计划》 | J28: □满足 □不满足
C29: 开发目标 | E29: 详见《设计开发任务书》 | G29: 见《设计验证报告》 | J29: □满足 □不满足
A30: 评审结果 The results of the | C30: 开发输出能够满足输入要求，验证通过。
A31: 评审人员会签 The judges will countersign
A32: 编制/日期Compilation/Date | G32: 审批/日期 Approval/Date
A33: 表单编号：HLD/CF-04-041-008 Form No：HLD/CF-04-041-008 | H33: 格式版次：第一版，第2次修改 Format edition: first edition, 2 revision

Sheet 2.11
A1: 密级：秘密★★，未经允许不可查看；保存期限：长期
A2: 设计更改记录 Design change record
E3: 序号NO.：2.11
A4: 新产品名称 New product name | C4: ='0.01'!C4 -> 大块金用工业长丝-帘子布事业部PH25657 Nylon 66 tire cord fabric industrial yarn-Tire cord fabric Department PH25657 | E4: 顾客名称 Customer name | G4: ='0.01'!H5 -> 帘子布事业部
E5: 新产品规格/型号New product specification/model | G5: ='0.01'!H4 -> PH25657-2800dtex/432f
A6: 设计更改日期 Design Change Date | C6: =目录!G35 -> 2023年12月22日 | E6: 实施人 The implementation of one | G6: 俞锋
A7: 更改原因 Reason for change | C7: 与客户沟通，优化包装形式；客户要求COA删除强力
A8: 更改内容 Changed content | C8: 更改前 Before the change | F8: 更改后 After the change
C9: 1.卷重4.87kg;包装形式：25孔泡沫板国内缠绕包装； 2.COA显示强力保持率。 | F9: 1.卷重5.34kg;包装形式：18小孔蜂窝板缠绕包装； 2.COA不显示强力保持率。
A10: 设计更改后评审意见Review comments after design changes | C10: 同意，修改包装标准，试生产按新标准执行。
A13: 会签 sign
A14: 备注 note | C14: COA仅隐藏强力保持率，测试不变。
A15: 编制/日期 Compilation/Date | E15: 审批/日期Approval/Date
A16: 表单编号：HLD/CF-04-041-028 Form No：HLD/CF-04-041-028 | F16: 格式版次：第一版，第1次修改 Format edition: first edition, 1 revision

Sheet 2.11 (2)
A1: 密级：秘密★★，未经允许不可查看；保存期限：长期
A2: 设计更改记录 Design change record
E3: 序号NO.：2.11
A4: 新产品名称 New product name | C4: ='0.01'!C4 -> 大块金用工业长丝-帘子布事业部PH25657 Nylon 66 tire cord fabric industrial yarn-Tire cord fabric Department PH25657 | E4: 顾客名称 Customer name | G4: ='0.01'!H5 -> 帘子布事业部
E5: 新产品规格/型号New product specification/model | G5: ='0.01'!H4 -> PH25657-2800dtex/432f
A6: 设计更改日期 Design Change Date | C6: =目录!I35 -> 2024年6月4日 | E6: 实施人 The implementation of one | G6: 俞锋
A7: 更改原因 Reason for change | C7: 客户要求
A8: 更改内容 Changed content | C8: 更改前 Before the change | F8: 更改后 After the change
C9: 干热收缩率：6.2±1.5% | F9: 干热收缩率：5.2±1.5%
A10: 设计更改后评审意见Review comments after design changes | C10: 同意，修改产品技术规范，试生产按新标准执行。
A13: 会签 sign
A14: 备注 note
A15: 编制/日期 Compilation/Date | E15: 审批/日期Approval/Date
A16: 表单编号：HLD/CF-04-041-028 Form No：HLD/CF-04-041-028 | F16: 格式版次：第一版，第1次修改 Format edition: first edition, 1 revision

Sheet 2.12
F1: 密级：秘密★★，未经允许不可查看；保存期限：长期
A2: 工程规范确认表 Engineering specification confirmation form
A3: 序号NO.：2.12
A4: 产品系列 The series of the product | C4: ='0.01'!C4 -> 大块金用工业长丝-帘子布事业部PH25657 Nylon 66 tire cord fabric industrial yarn-Tire cord fabric Department PH25657 | I4: 新产品规格/型号New product specification/model | K4: ='0.01'!H4 -> PH25657-2800dtex/432f
A5: 顾 客 名 称 The customer name | C5: ='0.01'!H5 -> 帘子布事业部 | I5: 日期 Date | K5: =目录!G36 -> 2023年8月30日
A6: 序号 No. | B6: 确 认 项 目 Confirmed items | C6: 顾客对产品技术要求 Technical requirements of customer | E6: 顾客要求测试方法 Test Method for customer requirements | F6: 内部对产品技术要求 Technical requirements of Internal | H6: 内部测试方法 Test Method for Internal | I6: CC/SC | J6: 测试设备 Test equipment | K6: 频率/容量 Frequency / volume | L6: 过程控制方法Process control methodology | M6: 确认结果 Confirm | N6: 备 注 Remarks
A7: 1 | B7: ='0.02'!B11:D11 -> 线密度 Linear Density | C7: ='0.02'!G11 -> 2880±30 | D7: ='0.02'!E11 -> dtex | E7: ='0.02'!I11 -> GB/T14343 | F7: =C7 -> 2880±30 | G7: =D7 -> dtex | H7: =E7 -> GB/T14343 | I7: SC | J7: 缕纱测长仪 电子天平 | K7: 12h/全锭位 | L7: SPC控制图 | M7: OK
A8: 2 | B8: ='0.02'!B12:D12 -> 线密度变异系数 CV of Linear Density | C8: ='0.02'!G12 -> ≤1.60 | D8: ='0.02'!E12 -> % | E8: ='0.02'!I12 -> GB/T14343 | F8: =C8 -> ≤1.60 | G8: =D8 -> % | H8: =E8 -> GB/T14343 | I8: — | J8: 缕纱测长仪 电子天平 | K8: 12h/全锭位 | L8: - | M8: OK
A9: 3 | B9: ='0.02'!B13:D13 -> 断裂强力 Breaking Strength | C9: ='0.02'!G13 -> ≥245.0 | D9: ='0.02'!E13 -> N | E9: ='0.02'!I13 -> GB/T14344 | F9: =C9 -> ≥245.0 | G9: =D9 -> N | H9: =E9 -> GB/T14344 | I9: CC | J9: 强伸仪 | K9: 12h/全锭位 | L9: SPC控制图 | M9: OK
A10: 4 | B10: ='0.02'!B14:D14 -> 断裂强度 Tenacity | C10: ='0.02'!G14 -> ≥8.50 | D10: ='0.02'!E14 -> cN/dtex | E10: ='0.02'!I14 -> GB/T14344 | F10: =C10 -> ≥8.50 | G10: =D10 -> cN/dtex | H10: =E10 -> GB/T14344 | I10: — | J10: 强伸仪 | K10: 12h/全锭位 | L10: SPC控制图 | M10: OK
A11: 5 | B11: ='0.02'!B15:D15 -> 强度变异系数CV CV of Tenacity | C11: ='0.02'!G15 -> ≤3.00 | D11: ='0.02'!E15 -> % | E11: ='0.02'!I15 -> GB/T14344 | F11: =C11 -> ≤3.00 | G11: =D11 -> % | H11: =E11 -> GB/T14344 | I11: — | J11: 强伸仪 | K11: 12h/全锭位 | L11: - | M11: OK
A12: 6 | B12: ='0.02'!B16:D16 -> 断裂伸长率 Breaking Elongation Ratio | C12: ='0.02'!G16 -> 20.0±3.0 | D12: ='0.02'!E16 -> % | E12: ='0.02'!I16 -> GB/T14344 | F12: =C12 -> 20.0±3.0 | G12: =D12 -> % | H12: =E12 -> GB/T14344 | I12: CC | J12: 强伸仪 | K12: 12h/全锭位 | L12: SPC控制图 | M12: OK
A13: 7 | B13: ='0.02'!B17:D17 -> 伸长变异系数CV CV of Elongation | C13: ='0.02'!G17 -> ≤5.00 | D13: ='0.02'!E17 -> % | E13: ='0.02'!I17 -> GB/T14344 | F13: =C13 -> ≤5.00 | G13: =D13 -> % | H13: =E13 -> GB/T14344 | I13: — | J13: 强伸仪 | K13: 12h/全锭位 | L13: - | M13: OK
A14: 8 | B14: ='0.02'!B18:D18 -> 中间伸长4.7cN/dtex E.@4.7CN/dtex Load | C14: ='0.02'!G18 -> 11.0±1.5 | D14: ='0.02'!E18 -> % | E14: ='0.02'!I18 -> GB/T14344 | F14: =C14 -> 11.0±1.5 | G14: =D14 -> % | H14: =E14 -> GB/T14344 | I14: — | J14: 强伸仪 | K14: 12h/全锭位 | L14: SPC控制图 | M14: OK
A15: 9 | B15: ='0.02'!B19:D19 -> 干热收缩率（177℃×2min×0.05cN/dtex) Shrinkage in Hot Air | C15: ='0.02'!G19 -> 6.2±1.5 | D15: ='0.02'!E19 -> % | E15: ='0.02'!I19 -> HLD method | F15: =C15 -> 6.2±1.5 | G15: =D15 -> % | H15: =E15 -> HLD method | I15: SC | J15: 烘箱 | K15: 12h/全锭位 | L15: SPC控制图 | M15: OK
A16: 10 | B16: ='0.02'!B20:D20 -> 网络度（钩针法） Intermingles（Needle） | C16: ='0.02'!G20 -> 6.0±3.0 | D16: ='0.02'!E20 -> nodes/m | E16: ='0.02'!I20 -> HLD method | F16: =C16 -> 6.0±3.0 | G16: =D16 -> nodes/m | H16: =E16 -> HLD method | I16: — | J16: 钩针 | K16: 12h/全锭位 | L16: SPC控制图 | M16: OK
A17: 11 | B17: ='0.02'!B21:D21 -> 含油率 Spin Finish Oil | C17: ='0.02'!G21 -> 0.90±0.30 | D17: ='0.02'!E21 -> % | E17: ='0.02'!I21 -> GB/T6504-NMR | F17: =C17 -> 0.90±0.30 | G17: =D17 -> % | H17: =E17 -> GB/T6504-NMR | I17: SC | J17: NMR | K17: 12h/全锭位 | L17: SPC控制图 | M17: OK
A18: 12 | B18: ='0.02'!B22:D22 -> 强力保持率（180℃×4h） Strength retention rate | C18: ='0.02'!G22 -> ≥90 | D18: ='0.02'!E22 -> % | E18: ='0.02'!I22 -> HLD method | F18: =C18 -> ≥90 | G18: =D18 -> % | H18: =E18 -> HLD method | I18: — | J18: 烘箱、强力仪 | K18: 1周2次/1锭 | L18: - | M18: OK
A19: 备 注 Remarks
A20: 编制/日期 Compilation/Date | I20: 审批/日期 Approval/Date
A21: 表单编号：HLD/CF-04-041-015 Form No ：HLD/CF-04-041-015 | L21: 格式版次：第一版，第1次修改 Format edition: first edition, 1 revision

Sheet 2.13
E1: 密级：秘密★★，未经允许不可查看；保存期限：长期
A2: 材料规范确认表 Material specification confirmation form
A3: 序号NO.：2.13
A4: 产品系列 The series of the product | C4: ='0.01'!C4 -> 大块金用工业长丝-帘子布事业部PH25657 Nylon 66 tire cord fabric industrial yarn-Tire cord fabric Department PH25657 | F4: 新产品规格/型号 New product specification/model | G4: ='0.01'!H4 -> PH25657-2800dtex/432f
A5: 顾 客 名 称 The customer name | C5: ='0.01'!H5 -> 帘子布事业部 | F5: 日期 Date | G5: =目录!G37 -> 2023年8月31日
A6: 序号 No. | B6: 确 认 项 目 Confirmed items | C6: 顾客对产品技术要求 Technical requirements of customer | D6: 内部对产品技术要求 Technical requirements of Internal | E6: 测试设备 test equipment | F6: 频率/容量 Frequency / volume | G6: 过程控制方法 process control methodology | H6: 确认结果 Confirm | I6: 备 注 Remarks
A7: 1 | B7: 尼龙66切片 | C7: / | D7: 材料技术规范 | E7: / | F7: / | G7: SPC控制 | H7: OK
A8: 2 | B8: 纺丝油剂 | C8: / | D8: 材料技术规范 | E8: / | F8: 1次/批 | G8: 过程使用中发现异常及时反馈按不合格品处理程序处置 | H8: OK
A9: 3 | B9: 纸管 | C9: / | D9: 化纤事业部纸管质量标准 HLD/CF-03-041-206 | E9: / | F9: 2个/规格/批 | H9: OK
A10: 4 | B10: 木托盘 | C10: / | D10: 化纤事业部 托盘质量标准 HLD/CF-03-041-208 | E10: / | F10: 5个/规格/批 | H10: OK
A11: 5 | B11: 塑料袋 | C11: / | D11: 化纤事业部 塑料袋质量标准 HLD/CF-03-041-203 | E11: / | F11: 5个/规格/批 | H11: OK
A12: 6 | B12: 护角 | C12: / | D12: 化纤事业部 纸护角质量标准HLDCF-03-041-204 | E12: / | F12: 1次/批 | H12: OK
A13: 7 | B13: 缠绕膜 | C13: / | D13: 化纤事业部 缠绕膜质量标准 HLD/CF-03-041-201 | E13: / | F13: 抽检 | H13: OK
A14: 8 | B14: 打包带 | C14: / | D14: 化纤事业部打包带质量标准 HLD/CF-03-041-202 | E14: / | F14: 抽检 | H14: OK
A15: 9 | B15: 蜂窝板 | C15: / | D15: 化纤事业部 蜂窝板质量标准 HLD/CF-03-041-210 | E15: / | F15: 5个/规格/批 | H15: OK
A16: 10 | B16: 纸箱 | C16: / | D16: 化纤事业部纸箱质量标准 HLD/CF-03-041-209 | E16: / | F16: 5个/规格/批 | H16: OK
A17: 备 注 Remarks
A18: 编制/日期 Compilation/Date | F18: 审批/日期 Approval/Date
A19: 表单编号：HLD/CF-04-041-016 Form No：HLD/CF-04-041-016 | G19: 格式版次：第一版，第1次修改 Format edition: first edition, 1 revision

Sheet 2.14
E1: 密级：秘密★★，未经允许不可查看；保存期限：长期
A2: 设备、工装和设施清单 List of equipment、tooling and facilities
I3: 序号NO.：2.14
A4: 新产品名称 The name of the new product | D4: ='0.01'!C4 -> 大块金用工业长丝-帘子布事业部PH25657 Nylon 66 tire cord fabric industrial yarn-Tire cord fabric Department PH25657 | G4: 新产品批号和规格 Batch number and specification of new products | I4: ='0.01'!H4 -> PH25657-2800dtex/432f
A5: 顾客名称 The customer name | D5: ='0.01'!H5 -> 帘子布事业部 | G5: 日期 Date | I5: =目录!G38 -> 2023年9月1日
A6: 序号STT | B6: 设备名称 Device name | F6: 设备型号/编号 Equipment model/No | I6: 所需数量The required number of | J6: 是否需新增 Whether to add | K6: 负责人 responsible person | L6: 预计完成日期 finishing dates
A7: 1 | B7: 纺丝机 | F7: TMT | I7: 1 | J7: 否
A8: 2 | B8: 计量泵 | F8: 20CC | I8: 4 | J8: 否
A9: 3 | B9: 喷丝板 | F9: 108f | I9: 8 | J9: 否
A10: 4 | B10: 网络器 | F10: 35-50 | I10: 2 | J10: 否
A11: 5 | B11: 电子秤 | F11: - | I11: 1 | J11: 否
A12: 6 | B12: 地磅 | F12: - | I12: 1 | J12: 否
A13: 7 | B13: 缠绕机 | F13: A0057/T1650F-H | I13: 1 | J13: 否
A14: 8 | B14: 风速仪 | F14: KA33 | I14: 1 | J14: 否
A15: 9 | B15: 张力仪 | F15: ETPB-500 | I15: 1 | J15: 否
A16: 10 | B16: 频闪仪 | F16: PT-L10C/HY-4418 | I16: 1 | J16: 否
A17: 11 | B17: 手电筒 | F17: - | I17: 1 | J17: 否
A18: 12 | B18: 组件组装清洗装置 | F18: - | I18: 1 | J18: 否
... A20: 14 | B20: 全自动镜检仪 | F20: Aspex Incorporated | I20: 1 | J20: 否
A21: 编制/日期Compilation/Date | G21: 审批/日期 Approval/Date
A22: 表单编号：HLD/CF-04-041-017 Form No：HLD/CF-04-041-017 | H22: 格式版次：第一版，第2次修改 Format edition: first edition, 2 revision

Sheet 2.15
E1: 密级：秘密★★，未经允许不可查看；保存期限：长期
A2: 量具/试验设备清单 List of measuring tool/ test equipment
I3: 序号NO.：2.15
A4: 新产品名称 The name of the new product | D4: ='0.01'!C4 -> 大块金用工业长丝-帘子布事业部PH25657 Nylon 66 tire cord fabric industrial yarn-Tire cord fabric Department PH25657 | G4: 新产品批号和规格 Batch number and specification of new products | I4: ='0.01'!H4 -> PH25657-2800dtex/432f
A5: 顾客名称 The customer name | D5: ='0.01'!H5 -> 帘子布事业部 | G5: 日期 Date | I5: =目录!G39 -> 2023年9月1日
A6: 序号STT | B6: 设备名称 Device name | F6: 设备型号/编号 Equipment model/No | I6: 所需数量The required number of | J6: 是否需新增 Whether to add | K6: 负责人 responsible person | L6: 预计完成日期 finishing dates
A7: 1 | B7: 电子天平 | F7: GF-300 | I7: 1 | J7: 否
A8: 2 | B8: 电子天平 | F8: BSA224S | I8: 1 | J8: 否
A9: 3 | B9: 电子秤 | F9: ACS-30 | I9: 1 | J9: 否
A10: 4 | B10: 缕纱测长仪 | F10: YG086W | I10: 1 | J10: 否
A11: 5 | B11: 核磁共振 | F11: PQ001-Fiber | I11: 1 | J11: 否
A12: 6 | B12: 强伸仪/材料试验机 | F12: AND RTG1210 | I12: 1 | J12: 否
A13: 7 | B13: 便携式分光测色仪 | F13: MINISCAN EZ | I13: 1 | J13: 否
A14: 8 | B14: 高温烘箱 | F14: GWX-370F | I14: 1 | J14: 否
A15: 9 | B15: 钢直尺 | F15: 0-500mm | I15: 1 | J15: 否
A16: 10 | B16: 钢直尺 | F16: 0-1500mm | I16: 1 | J16: 否
A17: 11 | B17: 砝码 | F17: - | I17: 1 | J17: 否
A18: 12 | B18: 粘度仪 | F18: HCT-6X | I18: 1 | J18: 否
A19: 13 | B19: Hunterlab分光测色仪 | F19: Hunterlab LabScan XE | I19: 1 | J19: 否
A20: 14 | B20: 电位滴定仪 | F20: 905 | I20: 1 | J20: 否
A21: 15 | B21: 库仑法卡尔费休水分仪 | F21: CA200 | I21: 1 | J21: 否
A22: 16 | B22: 差示扫描量热仪 | F22: DSC-60 | I22: 1 | J22: 否
A23: 17 | B23: 全自动干热收缩仪 | F23: TST2 | I23: 1 | J23: 否
A24: 编制/日期Compilation/Date | G24: 审批/日期 Approval/Date
A25: 表单编号：HLD/CF-04-041-051 Form No：HLD/CF-04-041-051 | H25: 格式版次：第一版，第0次修改 Format edition: first edition, 0 revision

Sheet 2.15修改版
E1: 密级：秘密★★，未经允许不可查看；保存期限：长期
A2: 量具/试验设备清单 List of measuring tool/ test equipment
J3: 序号NO.：2.15
A4: 新产品名称 The name of the new product | D4: ='0.01'!C4 -> 大块金用工业长丝-帘子布事业部PH25657 Nylon 66 tire cord fabric industrial yarn-Tire cord fabric Department PH25657 | G4: 新产品批号和规格 Batch number and specification of new products | I4: ='0.01'!H4 -> PH25657-2800dtex/432f
A5: 顾客名称 The customer name | D5: ='0.01'!H5 -> 帘子布事业部 | G5: 日期 Date | I5: =目录!G39 -> 2023年9月1日
A6: 序号STT | B6: 设备名称 Device name | F6: 设备型号/编号 Equipment model/No | I6: 精度/规格是否满足 | J6: 所需数量The required number of | K6: 是否需新增 Whether to add | L6: 负责人 responsible person | M6: 预计完成日期 finishing dates
A7: 1 | B7: 电子天平 | F7: GF-300 | J7: 1 | K7: 否
A8: 2 | B8: 电子天平 | F8: BSA224S | J8: 1 | K8: 否
A9: 3 | B9: 电子秤 | F9: ACS-30 | J9: 1 | K9: 否
A10: 4 | B10: 缕纱测长仪 | F10: YG086W | J10: 1 | K10: 否
A11: 5 | B11: 核磁共振 | F11: PQ001-Fiber | J11: 1 | K11: 否
A12: 6 | B12: 强伸仪/材料试验机 | F12: AND RTG1210 | J12: 1 | K12: 否
A13: 7 | B13: 便携式分光测色仪 | F13: MINISCAN EZ | J13: 1 | K13: 否
A14: 8 | B14: 高温烘箱 | F14: GWX-370F | J14: 1 | K14: 否
A15: 9 | B15: 钢直尺 | F15: 0-500mm | J15: 1 | K15: 否
A16: 10 | B16: 钢直尺 | F16: 0-1500mm | J16: 1 | K16: 否
A17: 11 | B17: 砝码 | F17: - | J17: 1 | K17: 否
A18: 12 | B18: 粘度仪 | F18: HCT-6X | J18: 1 | K18: 否
A19: 13 | B19: Hunterlab分光测色仪 | F19: Hunterlab LabScan XE | J19: 1 | K19: 否
A20: 14 | B20: 电位滴定仪 | F20: 905 | J20: 1 | K20: 否
A21: 15 | B21: 库仑法卡尔费休水分仪 | F21: CA200 | J21: 1 | K21: 否
A22: 16 | B22: 差示扫描量热仪 | F22: DSC-60 | J22: 1 | K22: 否
A23: 17 | B23: 全自动干热收缩仪 | F23: TST2 | J23: 1 | K23: 否
A24: 编制/日期Compilation/Date | G24: 审批/日期 Approval/Date
A25: 表单编号：HLD/CF-04-041-051 Form No：HLD/CF-04-041-051 | H25: 格式版次：第一版，第0次修改 Format edition: first edition, 0 revision

Sheet 2.16
E1: 密级：秘密★★，未经允许不可查看；保存期限：长期
A2: 产品/过程特殊特性清单 List of product/process special features
F4: 序号NO.：2.16
A5: 新产品名称 The name of the new product | C5: ='0.01'!C4 -> 大块金用工业长丝-帘子布事业部PH25657 Nylon 66 tire cord fabric industrial yarn-Tire cord fabric Department PH25657 | E5: 新产品规格/型号 Batch number and specification of new products | G5: ='0.01'!H4 -> PH25657-2800dtex/432f
A6: 顾 客 名 称 The customer name | C6: ='0.01'!H5 -> 帘子布事业部 | E6: 日期 Date | G6: =目录!G40 -> 2023年9月2日
A7: 序号 STT | B7: 产品特性 Key Produc Characteristic | D7: 过程特性 Key Control Characteristic | F7: 控制手段 Control method | G7: 责任部门 The responsibility department | H7: 备注
B8: 描述Describe | C8: 符号Symbol | D8: 描述Describe | E8: 符号Symbol
A9: 1 | B9: 线密度 Linear density | C9: SC | F9: SPC管控图 | G9: 化纤事业部
A10: 2 | B10: 断裂强力 Tenacity at break | C10: CC | F10: SPC管控图 | G10: 化纤事业部
A11: 3 | B11: 断裂伸长 Elongation at break | C11: CC | F11: SPC管控图 | G11: 化纤事业部
A12: 4 | B12: 干热收缩率 Shinkage in hot air | C12: SC | F12: SPC管控图 | G12: 化纤事业部
A13: 5 | D13: 计量泵转速 speed of metering pump | E13: SC | F13: 100%实时监控 | G13: 化纤事业部
A14: 6 | D14: 加热罩温度 Heating hood temperature | E14: CC | F14: 100%实时监控 | G14: 化纤事业部
A15: 7 | D15: 侧吹风温度 Quenching air temperature | E15: CC | F15: 100%实时监控 | G15: 化纤事业部
A16: 8 | D16: 罗拉温度 temperature of roller | E16: SC | F16: 100%实时监控 | G16: 化纤事业部
A17: 9 | D17: 罗拉速度 speed of roller | E17: CC | F17: 100%实时监控 | G17: 化纤事业部
A18: 备注：CC表示关键特性,SC表示重要特性。
A19: 编制/日期Compilation/Date | E19: 审批/日期Approval/Date
A20: 表单编号：HLD/CF-04-041-012 Form No ：HLD/CF-04-041-012 | F20: 格式版次：第一版，第1次修改 Format edition: first edition, 1 revision

Sheet 2.17
E1: 密级：秘密★★，未经允许不可查看；保存期限：长期
A2: 小组可行性承诺 Group Feasibility Commitment
A3: 序号NO.：2.17
A4: 新产品名称 The name of the new product | D4: ='0.01'!C4 -> 大块金用工业长丝-帘子布事业部PH25657 Nylon 66 tire cord fabric industrial yarn-Tire cord fabric Department PH25657 | H4: 新产品批号和规格 Batch number and specification of new products | J4: ='0.01'!H4 -> PH25657-2800dtex/432f
A5: 顾客名称 The customer name | D5: ='0.01'!H5 -> 帘子布事业部 | H5: 日期 Date | J5: =目录!G41 -> 2023年9月3日
A6: 可行性考虑：Feasibility considerations:
A7: 产品质量策划小组在进行可行性评价时虽然无法做到百分百的面面俱到，但充分考虑了以下问题：所提供的图样或规范已被用来作为分析满足所有规定要求的能力基础。对于所有否定答案都要有识别所关注事项或所提出要求，以满足特定要求的附加规定。Although the product quality planning team cannot be 100% comprehensive in its feasibility evaluation, it has fully considered the following issues: the drawings or specifications provided have been used as the basis for analyzing the ability to meet all specified requirements. For all negative answers there should be additional provisions identifying concerns or requirements to meet specific requirements.
B8: 是 | D8: 否 | F8: 问 题
F9: 产品是否被完全定义（使用要求等）以便能进行可行性评价？ Is the product fully defined (usage requirements, etc.) so that a feasibility assessment can be made?
F10: 工程性能规范是否符合书面要求？Does the engineering performance specification meet the written requirements?
F11: 产品能按规定的公差生产吗？Can the product be manufactured to the specified tolerance?
F12: 产品能用符合要求的CPK值生产吗？Can the product be manufactured with the required CPK value?
F13: 有足够的生产能力生产产品吗？Is there sufficient production capacity to produce the product?
F14: 设计上允许使用高效的材料搬运技术吗？Does the design allow for efficient material handling techniques?
B15: 以下情况不发生异常时，产品是否能正常生产：Whether the product can be normally produced when the following circumstances are not abnormal:
F16: ·生产设备成本的提高？ Increased cost of production equipment?
F17: ·工装成本的提高？· Increased tooling costs?
F18: ·替代的制造方法？· Alternative manufacturing methods?
F19: 是否对产品要求统计过程控制？Are statistical process controls required for products?
F20: 统计过程控制是否用在类似的产品上？Are statistical process controls applied to similar products?
B21: 如果统计过程控制用在类似的产品上：If statistical process control is used for similar products:
F22: ·过程是否处于受控和稳定状态中？· Is the process in a controlled and stable state?
F23: ·CC/SC项PPK≥1.67或CPK≥1.67？· Is the PPK of the CC/SC item ≥1.67 or the CPK≥1.67?
A24: 结论：Conclusion:
A25: □ 可行feasible 产品可按规定不作修改而生产。The product may be produced in accordance with the provisions without modification.
A26: □ 可行feasible 建议作出更改（见附件）。Changes are proposed (see annex).
A27: □ 不可行Is not workable 需要更改设计以生产出符合规定要求的产品。The design needs to be changed to produce a product that meets the specified requirements.
A28: 编制/日期 Compilation/Date | I28: 审批/日期 Approval/Date
A29: 表单编号：HLD/CF-04-041-020 Form No：HLD/CF-04-041-020 | J29: 格式版次：第一版，第1次修改 Format edition: first edition, 1 revision

Sheet 2.18
E1: 密级：秘密★★，未经允许不可查看；保存期限：长期
A2: 阶段性总结和管理者支持 Periodic summary and manager support
I3: 序号NO.：2.18
A4: 新产品名称 The name of the new product | D4: ='0.01'!C4 -> 大块金用工业长丝-帘子布事业部PH25657 Nylon 66 tire cord fabric industrial yarn-Tire cord fabric Department PH25657 | G4: 新产品规格/型号 Batch number and specification of new products | I4: ='0.01'!H4 -> PH25657-2800dtex/432f
A5: 顾客名称 The customer name | D5: ='0.01'!H5 -> 帘子布事业部 | G5: 日期 Date | I5: =目录!G42 -> 2023年9月4日
A6: 一、产品质量先期策划实施和执行阶段： Product quality planning, implementation and Execution stage:
A7: □ 第一阶段：策划和定义项目 ■ 第二阶段：产品设计与开发 □ 第三阶段：过程设计与开发 □ 第四阶段：产品和过程确认
A12: 二、产品质量先期策划实施和执行工作状况（包括每一阶段的质量风险、开发成本、准备时间/前置期、关键路径等内容）：Ii. Work status of product quality planning, implementation and execution in advance (including quality risk, development cost, preparation time/lead time, critical path, etc.)
A13: 1、技术标准已经转换成内部文件，并已发放； 2、工程规范和材料规范均已确认完成； 3、现有的生产设备、工装、实验设备均能满足要求，不需要增加原料和设备； 4、量具、实验设备清单已经完成； 5、小组可行性承诺已完成。 6、样件生产已完成. 7、开发输出能够满足输入要求，验证通过。
A20: 三、公司高阶管理层对产品质量先期策划实施和执行工作的总结和支持：Summary and support of the company's senior management for the early planning, implementation and execution of product quality:
A21: 第二阶段均已完成 ，可进行下阶段的工作
A22: 备 注note
A24: 编制/日期Compilation/Date | G24: 审批/日期Approval/Date
A26: 表单编号：HLD/CF-04-041-013 Form No：：HLD/CF-04-041-013 | I26: 格式版次：第一版，第1次修改 Format edition: first edition, 1 revision

Sheet 2.18修改版
E1: 密级：秘密★★，未经允许不可查看；保存期限：长期
A2: 阶段性总结和管理者支持 Periodic summary and manager support
I3: 序号NO.：2.18 | L3: 替换左侧第二大项
A4: 新产品名称 The name of the new product | D4: ='0.01'!C4 -> 大块金用工业长丝-帘子布事业部PH25657 Nylon 66 tire cord fabric industrial yarn-Tire cord fabric Department PH25657 | G4: 新产品规格/型号 Batch number and specification of new products | I4: ='0.01'!H4 -> PH25657-2800dtex/432f | L4: 评审内容链接 （可点击跳转查看） | P4: 是否OK | R4: 改进行动 | V4: 全星增加项
A5: 顾客名称 The customer name | D5: ='0.01'!H5 -> 帘子布事业部 | G5: 日期 Date | I5: =目录!G42 -> 2023年9月4日 | L5: DFMEA | P5: OK / NG /NG
A6: 一、产品质量先期策划实施和执行阶段： Product quality planning, implementation and Execution stage: | L6: DFMEA检查表 | M6: DFMEA检查表 | N6: DFMEA检查表 | O6: DFMEA检查表 | P6: OK / NG /NG
A7: □ 第一阶段：策划和定义项目 ■ 第二阶段：产品设计与开发 □ 第三阶段：过程设计与开发 □ 第四阶段：产品和过程确认 | L7: 产品技术规范 | M7: 产品技术规范 | N7: 产品技术规范 | O7: 产品技术规范 | P7: OK / NG /NG
L8: 设计评审/验证/确认记录（可制造性评审） | M8: 设计评审/验证/确认记录（可制造性评审） | N8: 设计评审/验证/确认记录（可制造性评审） | O8: 设计评审/验证/确认记录（可制造性评审） | P8: OK / NG /NG
L9: 控制计划（样件） | M9: 控制计划（样件） | N9: 控制计划（样件） | O9: 控制计划（样件） | P9: OK / NG /NG
L10: 控制计划检查表（样件） | M10: 控制计划检查表（样件） | N10: 控制计划检查表（样件） | O10: 控制计划检查表（样件） | P10: OK / NG /NG
L11: 工艺标准（样件） | M11: 工艺标准（样件） | N11: 工艺标准（样件） | O11: 工艺标准（样件） | P11: OK / NG /NG
A12: 二、产品质量先期策划实施和执行工作状况（包括每一阶段的质量风险、开发成本、准备时间/前置期、关键路径等内容）：Ii. Work status of product quality planning, implementation and execution in advance (including quality risk, development cost, preparation time/lead time, critical path, etc.) | L12: 生产通知单（样件） | M12: 生产通知单（样件） | N12: 生产通知单（样件） | O12: 生产通知单（样件） | P12: OK / NG /NG
A13: 1、技术标准已经转换成内部文件，并已发放； 2、工程规范和材料规范均已确认完成； 3、现有的生产设备、工装、实验设备均能满足要求，不需要增加原料和设备； 4、量具、实验设备清单已经完成； 5、小组可行性承诺已完成。 6、样件生产已完成. 7、开发输出能够满足输入要求，验证通过。 | L13: 设计验证报告 | M13: 设计验证报告 | N13: 设计验证报告 | O13: 设计验证报告 | P13: OK / NG /NG
L14: 设计评审/验证/确认记录（产品设计输出） | M14: 设计评审/验证/确认记录（产品设计输出） | N14: 设计评审/验证/确认记录（产品设计输出） | O14: 设计评审/验证/确认记录（产品设计输出） | P14: OK / NG /NG
L15: 设计更改记录 | M15: 设计更改记录 | N15: 设计更改记录 | O15: 设计更改记录 | P15: OK / NG /NG
L16: 工程规范确认表 | M16: 工程规范确认表 | N16: 工程规范确认表 | O16: 工程规范确认表 | P16: OK / NG /NG
L17: 材料规范确认表 | M17: 材料规范确认表 | N17: 材料规范确认表 | O17: 材料规范确认表 | P17: OK / NG /NG
L18: 设备、工装和设施清单 | M18: 设备、工装和设施清单 | N18: 设备、工装和设施清单 | O18: 设备、工装和设施清单 | P18: OK / NG /NG
L19: 量具/试验设备清单 | M19: 量具/试验设备清单 | N19: 量具/试验设备清单 | O19: 量具/试验设备清单 | P19: OK / NG /NG
A20: 三、公司高阶管理层对产品质量先期策划实施和执行工作的总结和支持：Summary and support of the company's senior management for the early planning, implementation and execution of product quality: | L20: 产品/过程特殊特性清单（产品设计后更新） | M20: 产品/过程特殊特性清单（产品设计后更新） | N20: 产品/过程特殊特性清单（产品设计后更新） | O20: 产品/过程特殊特性清单（产品设计后更新） | P20: OK / NG /NG
A21: 第二阶段均已完成 ，可进行下阶段的工作 | L21: 小组可行性承诺 | M21: 小组可行性承诺 | N21: 小组可行性承诺 | O21: 小组可行性承诺 | P21: OK / NG /NG
A22: 备 注note
A24: 编制/日期Compilation/Date | G24: 审批/日期Approval/Date
A26: 表单编号：HLD/CF-04-041-013 Form No：：HLD/CF-04-041-013 | I26: 格式版次：第一版，第1次修改 Format edition: first edition, 1 revision
A28: 序 | B28: 发布日期 | E28: 问题描述 | H28: 责任人 | I28: 措施 | J28: 预计完成日期 | K28: 上传证据 | L28: 实际完成日期 | M28: 状态 | N28: 备注 | O28: 全星增加项

Sheet 4.05线 (2)
E1: 密级：秘密★★，未经允许不可查看；保存期限：长期
A2: 初始过程能力、设备过程能力分析报告
X3: 1 | Y3: 2873.75
S4: 序号NO.：4.05 | X4: 2 | Y4: 2877.25
A5: 新产品名称 The name of the new product | F5: =目录!B89 -> 尼龙66轮胎帘子布用工业长丝-帘子布事业部PH25657 Nylon 66 tire cord fabric industrial yarn-Tire cord fabric Department PH25657 | K5: 新产品批号和规格 Batch number and specification of new products | P5: =目录!B90 -> PH25657-2800dtex/432f | X5: 3 | Y5: 2876
A6: 特殊特性项目名称 | F6: 线密度 | K6: 特性标准值 | P6: 2880±30dtex | X6: 4 | Y6: 2881.25
A7: 1 | B7: =Y3 -> 2873.75 | C7: 11 | D7: =Y13 -> 2873.25 | E7: 21 | F7: =Y23 -> 2889.75 | G7: 31 | H7: =Y33 -> 2887.15 | I7: 41 | J7: =Y43 -> 2883.5 | K7: 51 | L7: =Y53 -> 2887.5 | M7: 61 | N7: =Y63 -> 2885.75 | O7: 71 | P7: =Y73 -> 2889.75 | Q7: 81 | R7: =Y83 -> 2891 | S7: 91 | T7: =Y93 -> 2894.65 | X7: 5 | Y7: 2883.5
A8: 2 | B8: =Y4 -> 2877.25 | C8: 12 | D8: =Y14 -> 2880 | E8: 22 | F8: =Y24 -> 2891 | G8: 32 | H8: =Y34 -> 2888.75 | I8: 42 | J8: =Y44 -> 2877.4 | K8: 52 | L8: =Y54 -> 2883.65 | M8: 62 | N8: =Y64 -> 2887.15 | O8: 72 | P8: =Y74 -> 2892.4 | Q8: 82 | R8: =Y84 -> 2893.65 | S8: 92 | T8: =Y94 -> 2891.75 | X8: 6 | Y8: 2887
A9: 3 | B9: =Y5 -> 2876 | C9: 13 | D9: =Y15 -> 2888.75 | E9: 23 | F9: =Y25 -> 2888.5 | G9: 33 | H9: =Y35 -> 2892.15 | I9: 43 | J9: =Y45 -> 2882 | K9: 53 | L9: =Y55 -> 2888.25 | M9: 63 | N9: =Y65 -> 2884.25 | O9: 73 | P9: =Y75 -> 2893.75 | Q9: 83 | R9: =Y85 -> 2893 | S9: 93 | T9: =Y95 -> 2882.9 | X9: 7 | Y9: 2887.75
A10: 4 | B10: =Y6 -> 2881.25 | C10: 14 | D10: =Y16 -> 2873.25 | E10: 24 | F10: =Y26 -> 2888.25 | G10: 34 | H10: =Y36 -> 2885.5 | I10: 44 | J10: =Y46 -> 2886.5 | K10: 54 | L10: =Y56 -> 2888.25 | M10: 64 | N10: =Y66 -> 2888 | O10: 74 | P10: =Y76 -> 2884.75 | Q10: 84 | R10: =Y86 -> 2891.25 | S10: 94 | T10: =Y96 -> 2889.65 | X10: 8 | Y10: 2879.25
A11: 5 | B11: =Y7 -> 2883.5 | C11: 15 | D11: =Y17 -> 2887 | E11: 25 | F11: =Y27 -> 2887.25 | G11: 35 | H11: =Y37 -> 2889.5 | I11: 45 | J11: =Y47 -> 2886.5 | K11: 55 | L11: =Y57 -> 2892.5 | M11: 65 | N11: =Y67 -> 2888 | O11: 75 | P11: =Y77 -> 2888.9 | Q11: 85 | R11: =Y87 -> 2887.5 | S11: 95 | T11: =Y97 -> 2881.75 | X11: 9 | Y11: 2887.75
A12: 6 | B12: =Y8 -> 2887 | C12: 16 | D12: =Y18 -> 2880.5 | E12: 26 | F12: =Y28 -> 2888.25 | G12: 36 | H12: =Y38 -> 2882.4 | I12: 46 | J12: =Y48 -> 2882.9 | K12: 56 | L12: =Y58 -> 2892 | M12: 66 | N12: =Y68 -> 2877.25 | O12: 76 | P12: =Y78 -> 2892.75 | Q12: 86 | R12: =Y88 -> 2891.4 | S12: 96 | T12: =Y98 -> 2893.9 | X12: 10 | Y12: 2888.5
A13: 7 | B13: =Y9 -> 2887.75 | C13: 17 | D13: =Y19 -> 2887.5 | E13: 27 | F13: =Y29 -> 2890.75 | G13: 37 | H13: =Y39 -> 2890.75 | I13: 47 | J13: =Y49 -> 2891.9 | K13: 57 | L13: =Y59 -> 2892.5 | M13: 67 | N13: =Y69 -> 2881.4 | O13: 77 | P13: =Y79 -> 2889.5 | Q13: 87 | R13: =Y89 -> 2890.75 | S13: 97 | T13: =Y99 -> 2889.15 | X13: 11 | Y13: 2873.25
A14: 8 | B14: =Y10 -> 2879.25 | C14: 18 | D14: =Y20 -> 2880.25 | E14: 28 | F14: =Y30 -> 2889.9 | G14: 38 | H14: =Y40 -> 2887.65 | I14: 48 | J14: =Y50 -> 2891 | K14: 58 | L14: =Y60 -> 2890.25 | M14: 68 | N14: =Y70 -> 2884 | O14: 78 | P14: =Y80 -> 2888.25 | Q14: 88 | R14: =Y90 -> 2891.75 | S14: 98 | T14: =Y100 -> 2885.5 | X14: 12 | Y14: 2880
A15: 9 | B15: =Y11 -> 2887.75 | C15: 19 | D15: =Y21 -> 2890.75 | E15: 29 | F15: =Y31 -> 2885 | G15: 39 | H15: =Y41 -> 2892 | I15: 49 | J15: =Y51 -> 2890.75 | K15: 59 | L15: =Y61 -> 2887.75 | M15: 69 | N15: =Y71 -> 2875.65 | O15: 79 | P15: =Y81 -> 2888.9 | Q15: 89 | R15: =Y91 -> 2893.4 | S15: 99 | T15: =Y101 -> 2885.65 | X15: 13 | Y15: 2888.75
A16: 10 | B16: =Y12 -> 2888.5 | C16: 20 | D16: =Y22 -> 2892.75 | E16: 30 | F16: =Y32 -> 2889.5 | G16: 40 | H16: =Y42 -> 2890.25 | I16: 50 | J16: =Y52 -> 2891.75 | K16: 60 | L16: =Y62 -> 2876.4 | M16: 70 | N16: =Y72 -> 2880.9 | O16: 80 | P16: =Y82 -> 2888.75 | Q16: 90 | R16: =Y92 -> 2894.25 | S16: 100 | T16: =Y102 -> 2889.15 | X16: 14 | Y16: 2873.25
A17: #VALUE! | X17: 15 | Y17: 2887
X18: 16 | Y18: 2880.5
X19: 17 | Y19: 2887.5
X20: 18 | Y20: 2880.25
X21: 19 | Y21: 2890.75
A22: 分析评 价结论 | B22: 过程性能指数PPK为2.02≥1.67，设备性能指数CMK=PPK=2.02≥1.67，符合要求； | X22: 20 | Y22: 2892.75
X23: 21 | Y23: 2889.75
X24: 22 | Y24: 2891
A25: 编制/日期 Compilation/Date | F25: 项宏 | H25: 2024年3月8日 | K25: 审批/日期 Approval/Date | O25: 崔真真 | R25: 2024年3月8日 | X25: 23 | Y25: 2888.5
A26: 表单编号：HLD/CF-04-041-032 Form No ：HLD/CF-04-041-032 | O26: 格式版次：第一版，第0次修改 Format edition: first edition, 0 revision | X26: 24 | Y26: 2888.25
X27: 25 | Y27: 2887.25
X28: 26 | Y28: 2888.25
X29: 27 | Y29: 2890.75
X30: 28 | Y30: 2889.9
X31: 29 | Y31: 2885
X32: 30 | Y32: 2889.5
X33: 31 | Y33: 2887.15
X34: 32 | Y34: 2888.75
X35: 33 | Y35: 2892.15
X36: 34 | Y36: 2885.5
X37: 35 | Y37: 2889.5
X38: 36 | Y38: 2882.4
... X102: 100 | Y102: 2889.15

Sheet 4.05力 (2)
E1: 密级：秘密★★，未经允许不可查看；保存期限：长期
A2: 初始过程能力、设备过程能力分析报告
X3: 1 | Y3: 253.35
S4: 序号NO.：4.05 | X4: 2 | Y4: 254.4
A5: 新产品名称 The name of the new product | F5: =目录!B89 -> 尼龙66轮胎帘子布用工业长丝-帘子布事业部PH25657 Nylon 66 tire cord fabric industrial yarn-Tire cord fabric Department PH25657 | K5: 新产品批号和规格 Batch number and specification of new products | P5: =目录!B90 -> PH25657-2800dtex/432f | X5: 3 | Y5: 251.95
A6: 特殊特性项目名称 | F6: 断裂强力 | K6: 特性标准值 | P6: ≥245.0N | X6: 4 | Y6: 252.05
A7: 1 | B7: =Y3 -> 253.35 | C7: 11 | D7: =Y13 -> 250.1 | E7: 21 | F7: =Y23 -> 250.8 | G7: 31 | H7: =Y33 -> 255.1 | I7: 41 | J7: =Y43 -> 250.2 | K7: 51 | L7: =Y53 -> 253.95 | M7: 61 | N7: =Y63 -> 252.9 | O7: 71 | P7: =Y73 -> 253.85 | Q7: 81 | R7: =Y83 -> 251.5 | S7: 91 | T7: =Y93 -> 254.35 | X7: 5 | Y7: 251.7
A8: 2 | B8: =Y4 -> 254.4 | C8: 12 | D8: =Y14 -> 251.05 | E8: 22 | F8: =Y24 -> 249.45 | G8: 32 | H8: =Y34 -> 254.2 | I8: 42 | J8: =Y44 -> 252.6 | K8: 52 | L8: =Y54 -> 251.45 | M8: 62 | N8: =Y64 -> 250.75 | O8: 72 | P8: =Y74 -> 254 | Q8: 82 | R8: =Y84 -> 251.25 | S8: 92 | T8: =Y94 -> 253.5 | X8: 6 | Y8: 253.55
A9: 3 | B9: =Y5 -> 251.95 | C9: 13 | D9: =Y15 -> 251 | E9: 23 | F9: =Y25 -> 251.5 | G9: 33 | H9: =Y35 -> 253.3 | I9: 43 | J9: =Y45 -> 250.8 | K9: 53 | L9: =Y55 -> 252.4 | M9: 63 | N9: =Y65 -> 253.95 | O9: 73 | P9: =Y75 -> 253.85 | Q9: 83 | R9: =Y85 -> 253.2 | S9: 93 | T9: =Y95 -> 253.9 | X9: 7 | Y9: 251.55
A10: 4 | B10: =Y6 -> 252.05 | C10: 14 | D10: =Y16 -> 248.75 | E10: 24 | F10: =Y26 -> 250.05 | G10: 34 | H10: =Y36 -> 250.25 | I10: 44 | J10: =Y46 -> 252.2 | K10: 54 | L10: =Y56 -> 251.05 | M10: 64 | N10: =Y66 -> 252.4 | O10: 74 | P10: =Y76 -> 252.9 | Q10: 84 | R10: =Y86 -> 252.55 | S10: 94 | T10: =Y96 -> 253.65 | X10: 8 | Y10: 252.6
A11: 5 | B11: =Y7 -> 251.7 | C11: 15 | D11: =Y17 -> 250.65 | E11: 25 | F11: =Y27 -> 252.05 | G11: 35 | H11: =Y37 -> 251.15 | I11: 45 | J11: =Y47 -> 252.2 | K11: 55 | L11: =Y57 -> 252 | M11: 65 | N11: =Y67 -> 252.5 | O11: 75 | P11: =Y77 -> 251.75 | Q11: 85 | R11: =Y87 -> 252.1 | S11: 95 | T11: =Y97 -> 251.85 | X11: 9 | Y11: 252
A12: 6 | B12: =Y8 -> 253.55 | C12: 16 | D12: =Y18 -> 251.8 | E12: 26 | F12: =Y28 -> 250.65 | G12: 36 | H12: =Y38 -> 252.65 | I12: 46 | J12: =Y48 -> 251.45 | K12: 56 | L12: =Y58 -> 253.95 | M12: 66 | N12: =Y68 -> 254 | O12: 76 | P12: =Y78 -> 251.6 | Q12: 86 | R12: =Y88 -> 251.75 | S12: 96 | T12: =Y98 -> 250.3 | X12: 10 | Y12: 252.45
A13: 7 | B13: =Y9 -> 251.55 | C13: 17 | D13: =Y19 -> 249.18225 | E13: 27 | F13: =Y29 -> 249.45 | G13: 37 | H13: =Y39 -> 254.4 | I13: 47 | J13: =Y49 -> 251.5 | K13: 57 | L13: =Y59 -> 252 | M13: 67 | N13: =Y69 -> 254.55 | O13: 77 | P13: =Y79 -> 252.75 | Q13: 87 | R13: =Y89 -> 252.6 | S13: 97 | T13: =Y99 -> 250.9 | X13: 11 | Y13: 250.1
A14: 8 | B14: =Y10 -> 252.6 | C14: 18 | D14: =Y20 -> 251.85 | E14: 28 | F14: =Y30 -> 250.05 | G14: 38 | H14: =Y40 -> 251.7 | I14: 48 | J14: =Y50 -> 253.1 | K14: 58 | L14: =Y60 -> 252.3 | M14: 68 | N14: =Y70 -> 256 | O14: 78 | P14: =Y80 -> 250.15 | Q14: 88 | R14: =Y90 -> 252.7 | S14: 98 | T14: =Y100 -> 253.4 | X14: 12 | Y14: 251.05
A15: 9 | B15: =Y11 -> 252 | C15: 19 | D15: =Y21 -> 249.6 | E15: 29 | F15: =Y31 -> 253.15 | G15: 39 | H15: =Y41 -> 252.35 | I15: 49 | J15: =Y51 -> 252.95 | K15: 59 | L15: =Y61 -> 253.5 | M15: 69 | N15: =Y71 -> 255.25 | O15: 79 | P15: =Y81 -> 251.3 | Q15: 89 | R15: =Y91 -> 252.8 | S15: 99 | T15: =Y101 -> 252.6 | X15: 13 | Y15: 251
A16: 10 | B16: =Y12 -> 252.45 | C16: 20 | D16: =Y22 -> 251.45 | E16: 30 | F16: =Y32 -> 252.2 | G16: 40 | H16: =Y42 -> 252 | I16: 50 | J16: =Y52 -> 251.55 | K16: 60 | L16: =Y62 -> 253.75 | M16: 70 | N16: =Y72 -> 251.7 | O16: 80 | P16: =Y82 -> 249.85 | Q16: 90 | R16: =Y92 -> 252.5 | S16: 100 | T16: =Y102 -> 253 | X16: 14 | Y16: 248.75
A17: #VALUE! | X17: 15 | Y17: 250.65
X18: 16 | Y18: 251.8
X19: 17 | Y19: 249.18225
X20: 18 | Y20: 251.85
X21: 19 | Y21: 249.6
A22: 分析评 价结论 | B22: 过程性能指数PPK为1.72≥1.67，设备性能指数CMK=PPK=1.72≥1.67，符合要求； | X22: 20 | Y22: 251.45
X23: 21 | Y23: 250.8
X24: 22 | Y24: 249.45
A25: 编制/日期 Compilation/Date | F25: 项宏 | H25: 2024年3月8日 | K25: 审批/日期 Approval/Date | O25: 崔真真 | R25: 2024年3月8日 | X25: 23 | Y25: 251.5
A26: 表单编号：HLD/CF-04-041-032 Form No ：HLD/CF-04-041-032 | O26: 格式版次：第一版，第0次修改 Format edition: first edition, 0 revision | X26: 24 | Y26: 250.05
X27: 25 | Y27: 252.05
X28: 26 | Y28: 250.65
X29: 27 | Y29: 249.45
X30: 28 | Y30: 250.05
X31: 29 | Y31: 253.15
X32: 30 | Y32: 252.2
X33: 31 | Y33: 255.1
X34: 32 | Y34: 254.2
X35: 33 | Y35: 253.3
X36: 34 | Y36: 250.25
X37: 35 | Y37: 251.15
X38: 36 | Y38: 252.65
... X102: 100 | Y102: 253

Sheet 4.05伸 (2)
E1: 密级：秘密★★，未经允许不可查看；保存期限：长期
A2: 初始过程能力、设备过程能力分析报告
X3: 1 | Y3: 20.4
S4: 序号NO.：4.05 | X4: 2 | Y4: 20.1
A5: 新产品名称 The name of the new product | F5: =目录!B89 -> 尼龙66轮胎帘子布用工业长丝-帘子布事业部PH25657 Nylon 66 tire cord fabric industrial yarn-Tire cord fabric Department PH25657 | K5: 新产品批号和规格 Batch number and specification of new products | P5: =目录!B90 -> PH25657-2800dtex/432f | X5: 3 | Y5: 19.9
A6: 特殊特性项目名称 | F6: 断裂伸长率 | K6: 特性标准值 | P6: 20.0±3.0% | X6: 4 | Y6: 20.4
A7: 1 | B7: =Y3 -> 20.4 | C7: 11 | D7: =Y13 -> 20.5 | E7: 21 | F7: =Y23 -> 20.1 | G7: 31 | H7: =Y33 -> 20.3 | I7: 41 | J7: =Y43 -> 19.2 | K7: 51 | L7: =Y53 -> 20.3 | M7: 61 | N7: =Y63 -> 20.1 | O7: 71 | P7: =Y73 -> 20 | Q7: 81 | R7: =Y83 -> 19.9 | S7: 91 | T7: =Y93 -> 19.6 | X7: 5 | Y7: 19.9
A8: 2 | B8: =Y4 -> 20.1 | C8: 12 | D8: =Y14 -> 19.3 | E8: 22 | F8: =Y24 -> 20.1 | G8: 32 | H8: =Y34 -> 19.9 | I8: 42 | J8: =Y44 -> 20.5 | K8: 52 | L8: =Y54 -> 21.1 | M8: 62 | N8: =Y64 -> 20.8 | O8: 72 | P8: =Y74 -> 20.1 | Q8: 82 | R8: =Y84 -> 21.1 | S8: 92 | T8: =Y94 -> 20.6 | X8: 6 | Y8: 20.8
A9: 3 | B9: =Y5 -> 19.9 | C9: 13 | D9: =Y15 -> 20.1 | E9: 23 | F9: =Y25 -> 21.1 | G9: 33 | H9: =Y35 -> 20 | I9: 43 | J9: =Y45 -> 20.3 | K9: 53 | L9: =Y55 -> 20.4 | M9: 63 | N9: =Y65 -> 20.7 | O9: 73 | P9: =Y75 -> 20.7 | Q9: 83 | R9: =Y85 -> 21.2 | S9: 93 | T9: =Y95 -> 19.6 | X9: 7 | Y9: 19.2
A10: 4 | B10: =Y6 -> 20.4 | C10: 14 | D10: =Y16 -> 19.3 | E10: 24 | F10: =Y26 -> 20.6 | G10: 34 | H10: =Y36 -> 19.2 | I10: 44 | J10: =Y46 -> 20.7 | K10: 54 | L10: =Y56 -> 19.8 | M10: 64 | N10: =Y66 -> 20.6 | O10: 74 | P10: =Y76 -> 20.5 | Q10: 84 | R10: =Y86 -> 20.7 | S10: 94 | T10: =Y96 -> 20 | X10: 8 | Y10: 20.4
A11: 5 | B11: =Y7 -> 19.9 | C11: 15 | D11: =Y17 -> 19.3 | E11: 25 | F11: =Y27 -> 20.6 | G11: 35 | H11: =Y37 -> 20.3 | I11: 45 | J11: =Y47 -> 20.7 | K11: 55 | L11: =Y57 -> 19.5 | M11: 65 | N11: =Y67 -> 20.5 | O11: 75 | P11: =Y77 -> 21.2 | Q11: 85 | R11: =Y87 -> 20.2 | S11: 95 | T11: =Y97 -> 19.8 | X11: 9 | Y11: 20.1
A12: 6 | B12: =Y8 -> 20.8 | C12: 16 | D12: =Y18 -> 20.4 | E12: 26 | F12: =Y28 -> 20 | G12: 36 | H12: =Y38 -> 20.1 | I12: 46 | J12: =Y48 -> 20.3 | K12: 56 | L12: =Y58 -> 21.1 | M12: 66 | N12: =Y68 -> 19.9 | O12: 76 | P12: =Y78 -> 19.5 | Q12: 86 | R12: =Y88 -> 20.6 | S12: 96 | T12: =Y98 -> 19.5 | X12: 10 | Y12: 19.9
A13: 7 | B13: =Y9 -> 19.2 | C13: 17 | D13: =Y19 -> 20.3 | E13: 27 | F13: =Y29 -> 19.9 | G13: 37 | H13: =Y39 -> 21.1 | I13: 47 | J13: =Y49 -> 20.8 | K13: 57 | L13: =Y59 -> 20.5 | M13: 67 | N13: =Y69 -> 20.8 | O13: 77 | P13: =Y79 -> 20.9 | Q13: 87 | R13: =Y89 -> 20.4 | S13: 97 | T13: =Y99 -> 19.3 | X13: 11 | Y13: 20.5
A14: 8 | B14: =Y10 -> 20.4 | C14: 18 | D14: =Y20 -> 19.8 | E14: 28 | F14: =Y30 -> 19.7 | G14: 38 | H14: =Y40 -> 20.4 | I14: 48 | J14: =Y50 -> 21.2 | K14: 58 | L14: =Y60 -> 20.4 | M14: 68 | N14: =Y70 -> 20.8 | O14: 78 | P14: =Y80 -> 21 | Q14: 88 | R14: =Y90 -> 20.9 | S14: 98 | T14: =Y100 -> 20.6 | X14: 12 | Y14: 19.3
A15: 9 | B15: =Y11 -> 20.1 | C15: 19 | D15: =Y21 -> 20.9 | E15: 29 | F15: =Y31 -> 20 | G15: 39 | H15: =Y41 -> 20.7 | I15: 49 | J15: =Y51 -> 20.7 | K15: 59 | L15: =Y61 -> 19.7 | M15: 69 | N15: =Y71 -> 20.9 | O15: 79 | P15: =Y81 -> 21.2 | Q15: 89 | R15: =Y91 -> 20.4 | S15: 99 | T15: =Y101 -> 19.8 | X15: 13 | Y15: 20.1
A16: 10 | B16: =Y12 -> 19.9 | C16: 20 | D16: =Y22 -> 20.3 | E16: 30 | F16: =Y32 -> 20 | G16: 40 | H16: =Y42 -> 20.5 | I16: 50 | J16: =Y52 -> 20.6 | K16: 60 | L16: =Y62 -> 20.5 | M16: 70 | N16: =Y72 -> 19.5 | O16: 80 | P16: =Y82 -> 21.3 | Q16: 90 | R16: =Y92 -> 21 | S16: 100 | T16: =Y102 -> 19.8 | X16: 14 | Y16: 19.3
A17: #VALUE! | X17: 15 | Y17: 19.3
X18: 16 | Y18: 20.4
X19: 17 | Y19: 20.3
X20: 18 | Y20: 19.8
X21: 19 | Y21: 20.9
A22: 分析评 价结论 | B22: 过程性能指数CPK为1.74≥1.67，设备性能指数CMK=CPK=1.74≥1.67，符合要求； | X22: 20 | Y22: 20.3
X23: 21 | Y23: 20.1
X24: 22 | Y24: 20.1
A25: 编制/日期 Compilation/Date | F25: 项宏 | H25: 2024年3月8日 | K25: 审批/日期 Approval/Date | O25: 崔真真 | R25: 2024年3月8日 | X25: 23 | Y25: 21.1
A26: 表单编号：HLD/CF-04-041-032 Form No ：HLD/CF-04-041-032 | O26: 格式版次：第一版，第0次修改 Format edition: first edition, 0 revision | X26: 24 | Y26: 20.6
X27: 25 | Y27: 20.6
X28: 26 | Y28: 20
X29: 27 | Y29: 19.9
X30: 28 | Y30: 19.7
X31: 29 | Y31: 20
X32: 30 | Y32: 20
X33: 31 | Y33: 20.3
X34: 32 | Y34: 19.9
X35: 33 | Y35: 20
X36: 34 | Y36: 19.2
X37: 35 | Y37: 20.3
X38: 36 | Y38: 20.1
... X102: 100 | Y102: 19.8

Sheet 4.05干 (2)
E1: 密级：秘密★★，未经允许不可查看；保存期限：长期
A2: 初始过程能力、设备过程能力分析报告
X3: 1 | Y3: 5.4
S4: 序号NO.：4.05 | X4: 2 | Y4: 5.5
A5: 新产品名称 The name of the new product | F5: =目录!B89 -> 尼龙66轮胎帘子布用工业长丝-帘子布事业部PH25657 Nylon 66 tire cord fabric industrial yarn-Tire cord fabric Department PH25657 | K5: 新产品批号和规格 Batch number and specification of new products | P5: =目录!B90 -> PH25657-2800dtex/432f | X5: 3 | Y5: 5.6
A6: 特殊特性项目名称 | F6: 干热收缩率 | K6: 特性标准值 | P6: 6.2±1.5% | X6: 4 | Y6: 5.4
A7: 1 | B7: =Y3 -> 5.4 | C7: 11 | D7: =Y13 -> 5.3 | E7: 21 | F7: =Y23 -> 5.8 | G7: 31 | H7: =Y33 -> 5.7 | I7: 41 | J7: =Y43 -> 5.5 | K7: 51 | L7: =Y53 -> 5.5 | M7: 61 | N7: =Y63 -> 5.5 | O7: 71 | P7: =Y73 -> 5.4 | Q7: 81 | R7: =Y83 -> 5.4 | S7: 91 | T7: =Y93 -> 5.5 | X7: 5 | Y7: 5.4
A8: 2 | B8: =Y4 -> 5.5 | C8: 12 | D8: =Y14 -> 5.6 | E8: 22 | F8: =Y24 -> 5.6 | G8: 32 | H8: =Y34 -> 5.5 | I8: 42 | J8: =Y44 -> 5.3 | K8: 52 | L8: =Y54 -> 5.4 | M8: 62 | N8: =Y64 -> 5.5 | O8: 72 | P8: =Y74 -> 5.6 | Q8: 82 | R8: =Y84 -> 5.5 | S8: 92 | T8: =Y94 -> 5.7 | X8: 6 | Y8: 5.5
A9: 3 | B9: =Y5 -> 5.6 | C9: 13 | D9: =Y15 -> 5.4 | E9: 23 | F9: =Y25 -> 5.6 | G9: 33 | H9: =Y35 -> 6.2 | I9: 43 | J9: =Y45 -> 5.3 | K9: 53 | L9: =Y55 -> 5.4 | M9: 63 | N9: =Y65 -> 5.6 | O9: 73 | P9: =Y75 -> 5.6 | Q9: 83 | R9: =Y85 -> 5.7 | S9: 93 | T9: =Y95 -> 5.5 | X9: 7 | Y9: 5.4
A10: 4 | B10: =Y6 -> 5.4 | C10: 14 | D10: =Y16 -> 5.4 | E10: 24 | F10: =Y26 -> 5.6 | G10: 34 | H10: =Y36 -> 5.1 | I10: 44 | J10: =Y46 -> 5.3 | K10: 54 | L10: =Y56 -> 5.4 | M10: 64 | N10: =Y66 -> 5.3 | O10: 74 | P10: =Y76 -> 5.4 | Q10: 84 | R10: =Y86 -> 5.7 | S10: 94 | T10: =Y96 -> 5.5 | X10: 8 | Y10: 5.3
A11: 5 | B11: =Y7 -> 5.4 | C11: 15 | D11: =Y17 -> 5.4 | E11: 25 | F11: =Y27 -> 5.5 | G11: 35 | H11: =Y37 -> 5.4 | I11: 45 | J11: =Y47 -> 5.3 | K11: 55 | L11: =Y57 -> 5.6 | M11: 65 | N11: =Y67 -> 5.6 | O11: 75 | P11: =Y77 -> 5.4 | Q11: 85 | R11: =Y87 -> 5.5 | S11: 95 | T11: =Y97 -> 5.4 | X11: 9 | Y11: 5.5
A12: 6 | B12: =Y8 -> 5.5 | C12: 16 | D12: =Y18 -> 5.6 | E12: 26 | F12: =Y28 -> 5.5 | G12: 36 | H12: =Y38 -> 5.4 | I12: 46 | J12: =Y48 -> 5.5 | K12: 56 | L12: =Y58 -> 5.5 | M12: 66 | N12: =Y68 -> 5.6 | O12: 76 | P12: =Y78 -> 5.4 | Q12: 86 | R12: =Y88 -> 5.7 | S12: 96 | T12: =Y98 -> 5.6 | X12: 10 | Y12: 5.5
A13: 7 | B13: =Y9 -> 5.4 | C13: 17 | D13: =Y19 -> 5.4 | E13: 27 | F13: =Y29 -> 5.6 | G13: 37 | H13: =Y39 -> 5.5 | I13: 47 | J13: =Y49 -> 5.4 | K13: 57 | L13: =Y59 -> 5.6 | M13: 67 | N13: =Y69 -> 5.6 | O13: 77 | P13: =Y79 -> 5.4 | Q13: 87 | R13: =Y89 -> 5.5 | S13: 97 | T13: =Y99 -> 5.6 | X13: 11 | Y13: 5.3
A14: 8 | B14: =Y10 -> 5.3 | C14: 18 | D14: =Y20 -> 5.3 | E14: 28 | F14: =Y30 -> 5.5 | G14: 38 | H14: =Y40 -> 5.3 | I14: 48 | J14: =Y50 -> 5.4 | K14: 58 | L14: =Y60 -> 5.7 | M14: 68 | N14: =Y70 -> 5.4 | O14: 78 | P14: =Y80 -> 5.4 | Q14: 88 | R14: =Y90 -> 5.6 | S14: 98 | T14: =Y100 -> 5.6 | X14: 12 | Y14: 5.6
A15: 9 | B15: =Y11 -> 5.5 | C15: 19 | D15: =Y21 -> 5.3 | E15: 29 | F15: =Y31 -> 5.7 | G15: 39 | H15: =Y41 -> 5.9 | I15: 49 | J15: =Y51 -> 5.4 | K15: 59 | L15: =Y61 -> 5.6 | M15: 69 | N15: =Y71 -> 5.2 | O15: 79 | P15: =Y81 -> 5.5 | Q15: 89 | R15: =Y91 -> 5.6 | S15: 99 | T15: =Y101 -> 5.4 | X15: 13 | Y15: 5.4
